Workbook

Sheet Daily Sale entry 
A1: Date 日期 | B1: Cash sale 现金销售 | C1: Misc Charges 杂项费用 | D1: Other Charges 其他费用 | E1: Credit Collection 赊账收款 | F1: b/f petty cash 上日备用金结转 | G1: c/f petty cash 今日备用金结转 | H1: Cash collection 现金收款 | I1: Cheque(unit) 支票(张数) | J1: Cheque collection 支票收款 | K1: TNG TNG收款 | L1: Advance Salary_M 预支薪水_M | M1: Advance Salary_H 预支薪水_H | O1: Date 日期 | P1: Buyer 买家 | Q1: Type 类别 | R1: Mode 方式 | S1: Amount 金额 | T1: Discount (optional) 折扣(可选) | U1: Remarks 备注 | V1: Bank-in date 存入日期 (cheque) | X1: Date 日期 | Y1: Description 说明 | Z1: Type 类别 | AA1: Debtor name 债务人 | AB1: Cheque (unit) 支票(张数) | AC1: Deposit 存入 | AD1: Withdrawal 提取 | AE1: Balance 余额
E2: =IF(A2="","",SUMPRODUCT(('Daily Sale entry '!$O$2:$O$1501=A2)*('Daily Sale entry '!$Q$2:$Q$1501="Collection 收款")*('Daily Sale entry '!$S$2:$S$1501-'Opening Balance'!$B$15*('Daily Sale entry '!$R$2:$R$1501="Cheque 支票")*('Daily Sale entry '!$S$2:$S$1501-TRUNC('Daily Sale entry '!$S$2:$S$1501))))) | AE2: =IF(X2="","",ROUND('Opening Balance'!$B$4+SUM($AC$2:AC2)-SUM($AD$2:AD2)+SUMPRODUCT(($Q$2:$Q$1501="Collection 收款")*($R$2:$R$1501="Cheque 支票")*($V$2:$V$1501<>"")*($V$2:$V$1501<=X2)*($S$2:$S$1501-'Opening Balance'!$B$15*($R$2:$R$1501="Cheque 支票")*($S$2:$S$1501-TRUNC($S$2:$S$1501))))-'Opening Balance'!$B$15*SUMPRODUCT(($Z$2:Z2="Online collection 网上收款")*($AA$2:AA2<>"")*($AC$2:AC2-TRUNC($AC$2:AC2))),2))
E3: =IF(A3="","",SUMPRODUCT(('Daily Sale entry '!$O$2:$O$1501=A3)*('Daily Sale entry '!$Q$2:$Q$1501="Collection 收款")*('Daily Sale entry '!$S$2:$S$1501-'Opening Balance'!$B$15*('Daily Sale entry '!$R$2:$R$1501="Cheque 支票")*('Daily Sale entry '!$S$2:$S$1501-TRUNC('Daily Sale entry '!$S$2:$S$1501))))) | AE3: =IF(X3="","",ROUND('Opening Balance'!$B$4+SUM($AC$2:AC3)-SUM($AD$2:AD3)+SUMPRODUCT(($Q$2:$Q$1501="Collection 收款")*($R$2:$R$1501="Cheque 支票")*($V$2:$V$1501<>"")*($V$2:$V$1501<=X3)*($S$2:$S$1501-'Opening Balance'!$B$15*($R$2:$R$1501="Cheque 支票")*($S$2:$S$1501-TRUNC($S$2:$S$1501))))-'Opening Balance'!$B$15*SUMPRODUCT(($Z$2:Z3="Online collection 网上收款")*($AA$2:AA3<>"")*($AC$2:AC3-TRUNC($AC$2:AC3))),2))
E4: =IF(A4="","",SUMPRODUCT(('Daily Sale entry '!$O$2:$O$1501=A4)*('Daily Sale entry '!$Q$2:$Q$1501="Collection 收款")*('Daily Sale entry '!$S$2:$S$1501-'Opening Balance'!$B$15*('Daily Sale entry '!$R$2:$R$1501="Cheque 支票")*('Daily Sale entry '!$S$2:$S$1501-TRUNC('Daily Sale entry '!$S$2:$S$1501))))) | AE4: =IF(X4="","",ROUND('Opening Balance'!$B$4+SUM($AC$2:AC4)-SUM($AD$2:AD4)+SUMPRODUCT(($Q$2:$Q$1501="Collection 收款")*($R$2:$R$1501="Cheque 支票")*($V$2:$V$1501<>"")*($V$2:$V$1501<=X4)*($S$2:$S$1501-'Opening Balance'!$B$15*($R$2:$R$1501="Cheque 支票")*($S$2:$S$1501-TRUNC($S$2:$S$1501))))-'Opening Balance'!$B$15*SUMPRODUCT(($Z$2:Z4="Online collection 网上收款")*($AA$2:AA4<>"")*($AC$2:AC4-TRUNC($AC$2:AC4))),2))
E5: =IF(A5="","",SUMPRODUCT(('Daily Sale entry '!$O$2:$O$1501=A5)*('Daily Sale entry '!$Q$2:$Q$1501="Collection 收款")*('Daily Sale entry '!$S$2:$S$1501-'Opening Balance'!$B$15*('Daily Sale entry '!$R$2:$R$1501="Cheque 支票")*('Daily Sale entry '!$S$2:$S$1501-TRUNC('Daily Sale entry '!$S$2:$S$1501))))) | AE5: =IF(X5="","",ROUND('Opening Balance'!$B$4+SUM($AC$2:AC5)-SUM($AD$2:AD5)+SUMPRODUCT(($Q$2:$Q$1501="Collection 收款")*($R$2:$R$1501="Cheque 支票")*($V$2:$V$1501<>"")*($V$2:$V$1501<=X5)*($S$2:$S$1501-'Opening Balance'!$B$15*($R$2:$R$1501="Cheque 支票")*($S$2:$S$1501-TRUNC($S$2:$S$1501))))-'Opening Balance'!$B$15*SUMPRODUCT(($Z$2:Z5="Online collection 网上收款")*($AA$2:AA5<>"")*($AC$2:AC5-TRUNC($AC$2:AC5))),2))
E6: =IF(A6="","",SUMPRODUCT(('Daily Sale entry '!$O$2:$O$1501=A6)*('Daily Sale entry '!$Q$2:$Q$1501="Collection 收款")*('Daily Sale entry '!$S$2:$S$1501-'Opening Balance'!$B$15*('Daily Sale entry '!$R$2:$R$1501="Cheque 支票")*('Daily Sale entry '!$S$2:$S$1501-TRUNC('Daily Sale entry '!$S$2:$S$1501))))) | AE6: =IF(X6="","",ROUND('Opening Balance'!$B$4+SUM($AC$2:AC6)-SUM($AD$2:AD6)+SUMPRODUCT(($Q$2:$Q$1501="Collection 收款")*($R$2:$R$1501="Cheque 支票")*($V$2:$V$1501<>"")*($V$2:$V$1501<=X6)*($S$2:$S$1501-'Opening Balance'!$B$15*($R$2:$R$1501="Cheque 支票")*($S$2:$S$1501-TRUNC($S$2:$S$1501))))-'Opening Balance'!$B$15*SUMPRODUCT(($Z$2:Z6="Online collection 网上收款")*($AA$2:AA6<>"")*($AC$2:AC6-TRUNC($AC$2:AC6))),2))
E7: =IF(A7="","",SUMPRODUCT(('Daily Sale entry '!$O$2:$O$1501=A7)*('Daily Sale entry '!$Q$2:$Q$1501="Collection 收款")*('Daily Sale entry '!$S$2:$S$1501-'Opening Balance'!$B$15*('Daily Sale entry '!$R$2:$R$1501="Cheque 支票")*('Daily Sale entry '!$S$2:$S$1501-TRUNC('Daily Sale entry '!$S$2:$S$1501))))) | AE7: =IF(X7="","",ROUND('Opening Balance'!$B$4+SUM($AC$2:AC7)-SUM($AD$2:AD7)+SUMPRODUCT(($Q$2:$Q$1501="Collection 收款")*($R$2:$R$1501="Cheque 支票")*($V$2:$V$1501<>"")*($V$2:$V$1501<=X7)*($S$2:$S$1501-'Opening Balance'!$B$15*($R$2:$R$1501="Cheque 支票")*($S$2:$S$1501-TRUNC($S$2:$S$1501))))-'Opening Balance'!$B$15*SUMPRODUCT(($Z$2:Z7="Online collection 网上收款")*($AA$2:AA7<>"")*($AC$2:AC7-TRUNC($AC$2:AC7))),2))
E8: =IF(A8="","",SUMPRODUCT(('Daily Sale entry '!$O$2:$O$1501=A8)*('Daily Sale entry '!$Q$2:$Q$1501="Collection 收款")*('Daily Sale entry '!$S$2:$S$1501-'Opening Balance'!$B$15*('Daily Sale entry '!$R$2:$R$1501="Cheque 支票")*('Daily Sale entry '!$S$2:$S$1501-TRUNC('Daily Sale entry '!$S$2:$S$1501))))) | AE8: =IF(X8="","",ROUND('Opening Balance'!$B$4+SUM($AC$2:AC8)-SUM($AD$2:AD8)+SUMPRODUCT(($Q$2:$Q$1501="Collection 收款")*($R$2:$R$1501="Cheque 支票")*($V$2:$V$1501<>"")*($V$2:$V$1501<=X8)*($S$2:$S$1501-'Opening Balance'!$B$15*($R$2:$R$1501="Cheque 支票")*($S$2:$S$1501-TRUNC($S$2:$S$1501))))-'Opening Balance'!$B$15*SUMPRODUCT(($Z$2:Z8="Online collection 网上收款")*($AA$2:AA8<>"")*($AC$2:AC8-TRUNC($AC$2:AC8))),2))
E9: =IF(A9="","",SUMPRODUCT(('Daily Sale entry '!$O$2:$O$1501=A9)*('Daily Sale entry '!$Q$2:$Q$1501="Collection 收款")*('Daily Sale entry '!$S$2:$S$1501-'Opening Balance'!$B$15*('Daily Sale entry '!$R$2:$R$1501="Cheque 支票")*('Daily Sale entry '!$S$2:$S$1501-TRUNC('Daily Sale entry '!$S$2:$S$1501))))) | AE9: =IF(X9="","",ROUND('Opening Balance'!$B$4+SUM($AC$2:AC9)-SUM($AD$2:AD9)+SUMPRODUCT(($Q$2:$Q$1501="Collection 收款")*($R$2:$R$1501="Cheque 支票")*($V$2:$V$1501<>"")*($V$2:$V$1501<=X9)*($S$2:$S$1501-'Opening Balance'!$B$15*($R$2:$R$1501="Cheque 支票")*($S$2:$S$1501-TRUNC($S$2:$S$1501))))-'Opening Balance'!$B$15*SUMPRODUCT(($Z$2:Z9="Online collection 网上收款")*($AA$2:AA9<>"")*($AC$2:AC9-TRUNC($AC$2:AC9))),2))
E10: =IF(A10="","",SUMPRODUCT(('Daily Sale entry '!$O$2:$O$1501=A10)*('Daily Sale entry '!$Q$2:$Q$1501="Collection 收款")*('Daily Sale entry '!$S$2:$S$1501-'Opening Balance'!$B$15*('Daily Sale entry '!$R$2:$R$1501="Cheque 支票")*('Daily Sale entry '!$S$2:$S$1501-TRUNC('Daily Sale entry '!$S$2:$S$1501))))) | AE10: =IF(X10="","",ROUND('Opening Balance'!$B$4+SUM($AC$2:AC10)-SUM($AD$2:AD10)+SUMPRODUCT(($Q$2:$Q$1501="Collection 收款")*($R$2:$R$1501="Cheque 支票")*($V$2:$V$1501<>"")*($V$2:$V$1501<=X10)*($S$2:$S$1501-'Opening Balance'!$B$15*($R$2:$R$1501="Cheque 支票")*($S$2:$S$1501-TRUNC($S$2:$S$1501))))-'Opening Balance'!$B$15*SUMPRODUCT(($Z$2:Z10="Online collection 网上收款")*($AA$2:AA10<>"")*($AC$2:AC10-TRUNC($AC$2:AC10))),2))
E11: =IF(A11="","",SUMPRODUCT(('Daily Sale entry '!$O$2:$O$1501=A11)*('Daily Sale entry '!$Q$2:$Q$1501="Collection 收款")*('Daily Sale entry '!$S$2:$S$1501-'Opening Balance'!$B$15*('Daily Sale entry '!$R$2:$R$1501="Cheque 支票")*('Daily Sale entry '!$S$2:$S$1501-TRUNC('Daily Sale entry '!$S$2:$S$1501))))) | AE11: =IF(X11="","",ROUND('Opening Balance'!$B$4+SUM($AC$2:AC11)-SUM($AD$2:AD11)+SUMPRODUCT(($Q$2:$Q$1501="Collection 收款")*($R$2:$R$1501="Cheque 支票")*($V$2:$V$1501<>"")*($V$2:$V$1501<=X11)*($S$2:$S$1501-'Opening Balance'!$B$15*($R$2:$R$1501="Cheque 支票")*($S$2:$S$1501-TRUNC($S$2:$S$1501))))-'Opening Balance'!$B$15*SUMPRODUCT(($Z$2:Z11="Online collection 网上收款")*($AA$2:AA11<>"")*($AC$2:AC11-TRUNC($AC$2:AC11))),2))
E12: =IF(A12="","",SUMPRODUCT(('Daily Sale entry '!$O$2:$O$1501=A12)*('Daily Sale entry '!$Q$2:$Q$1501="Collection 收款")*('Daily Sale entry '!$S$2:$S$1501-'Opening Balance'!$B$15*('Daily Sale entry '!$R$2:$R$1501="Cheque 支票")*('Daily Sale entry '!$S$2:$S$1501-TRUNC('Daily Sale entry '!$S$2:$S$1501))))) | AE12: =IF(X12="","",ROUND('Opening Balance'!$B$4+SUM($AC$2:AC12)-SUM($AD$2:AD12)+SUMPRODUCT(($Q$2:$Q$1501="Collection 收款")*($R$2:$R$1501="Cheque 支票")*($V$2:$V$1501<>"")*($V$2:$V$1501<=X12)*($S$2:$S$1501-'Opening Balance'!$B$15*($R$2:$R$1501="Cheque 支票")*($S$2:$S$1501-TRUNC($S$2:$S$1501))))-'Opening Balance'!$B$15*SUMPRODUCT(($Z$2:Z12="Online collection 网上收款")*($AA$2:AA12<>"")*($AC$2:AC12-TRUNC($AC$2:AC12))),2))
E13: =IF(A13="","",SUMPRODUCT(('Daily Sale entry '!$O$2:$O$1501=A13)*('Daily Sale entry '!$Q$2:$Q$1501="Collection 收款")*('Daily Sale entry '!$S$2:$S$1501-'Opening Balance'!$B$15*('Daily Sale entry '!$R$2:$R$1501="Cheque 支票")*('Daily Sale entry '!$S$2:$S$1501-TRUNC('Daily Sale entry '!$S$2:$S$1501))))) | AE13: =IF(X13="","",ROUND('Opening Balance'!$B$4+SUM($AC$2:AC13)-SUM($AD$2:AD13)+SUMPRODUCT(($Q$2:$Q$1501="Collection 收款")*($R$2:$R$1501="Cheque 支票")*($V$2:$V$1501<>"")*($V$2:$V$1501<=X13)*($S$2:$S$1501-'Opening Balance'!$B$15*($R$2:$R$1501="Cheque 支票")*($S$2:$S$1501-TRUNC($S$2:$S$1501))))-'Opening Balance'!$B$15*SUMPRODUCT(($Z$2:Z13="Online collection 网上收款")*($AA$2:AA13<>"")*($AC$2:AC13-TRUNC($AC$2:AC13))),2))
... E367: =IF(A367="","",SUMPRODUCT(('Daily Sale entry '!$O$2:$O$1501=A367)*('Daily Sale entry '!$Q$2:$Q$1501="Collection 收款")*('Daily Sale entry '!$S$2:$S$1501-'Opening Balance'!$B$15*('Daily Sale entry '!$R$2:$R$1501="Cheque 支票")*('Daily Sale entry '!$S$2:$S$1501-TRUNC('Daily Sale entry '!$S$2:$S$1501))))) | AE367: =IF(X367="","",ROUND('Opening Balance'!$B$4+SUM($AC$2:AC367)-SUM($AD$2:AD367)+SUMPRODUCT(($Q$2:$Q$1501="Collection 收款")*($R$2:$R$1501="Cheque 支票")*($V$2:$V$1501<>"")*($V$2:$V$1501<=X367)*($S$2:$S$1501-'Opening Balance'!$B$15*($R$2:$R$1501="Cheque 支票")*($S$2:$S$1501-TRUNC($S$2:$S$1501))))-'Opening Balance'!$B$15*SUMPRODUCT(($Z$2:Z367="Online collection 网上收款")*($AA$2:AA367<>"")*($AC$2:AC367-TRUNC($AC$2:AC367))),2))
AE368: =IF(X368="","",ROUND('Opening Balance'!$B$4+SUM($AC$2:AC368)-SUM($AD$2:AD368)+SUMPRODUCT(($Q$2:$Q$1501="Collection 收款")*($R$2:$R$1501="Cheque 支票")*($V$2:$V$1501<>"")*($V$2:$V$1501<=X368)*($S$2:$S$1501-'Opening Balance'!$B$15*($R$2:$R$1501="Cheque 支票")*($S$2:$S$1501-TRUNC($S$2:$S$1501))))-'Opening Balance'!$B$15*SUMPRODUCT(($Z$2:Z368="Online collection 网上收款")*($AA$2:AA368<>"")*($AC$2:AC368-TRUNC($AC$2:AC368))),2))
AE369: =IF(X369="","",ROUND('Opening Balance'!$B$4+SUM($AC$2:AC369)-SUM($AD$2:AD369)+SUMPRODUCT(($Q$2:$Q$1501="Collection 收款")*($R$2:$R$1501="Cheque 支票")*($V$2:$V$1501<>"")*($V$2:$V$1501<=X369)*($S$2:$S$1501-'Opening Balance'!$B$15*($R$2:$R$1501="Cheque 支票")*($S$2:$S$1501-TRUNC($S$2:$S$1501))))-'Opening Balance'!$B$15*SUMPRODUCT(($Z$2:Z369="Online collection 网上收款")*($AA$2:AA369<>"")*($AC$2:AC369-TRUNC($AC$2:AC369))),2))
AE370: =IF(X370="","",ROUND('Opening Balance'!$B$4+SUM($AC$2:AC370)-SUM($AD$2:AD370)+SUMPRODUCT(($Q$2:$Q$1501="Collection 收款")*($R$2:$R$1501="Cheque 支票")*($V$2:$V$1501<>"")*($V$2:$V$1501<=X370)*($S$2:$S$1501-'Opening Balance'!$B$15*($R$2:$R$1501="Cheque 支票")*($S$2:$S$1501-TRUNC($S$2:$S$1501))))-'Opening Balance'!$B$15*SUMPRODUCT(($Z$2:Z370="Online collection 网上收款")*($AA$2:AA370<>"")*($AC$2:AC370-TRUNC($AC$2:AC370))),2))
AE371: =IF(X371="","",ROUND('Opening Balance'!$B$4+SUM($AC$2:AC371)-SUM($AD$2:AD371)+SUMPRODUCT(($Q$2:$Q$1501="Collection 收款")*($R$2:$R$1501="Cheque 支票")*($V$2:$V$1501<>"")*($V$2:$V$1501<=X371)*($S$2:$S$1501-'Opening Balance'!$B$15*($R$2:$R$1501="Cheque 支票")*($S$2:$S$1501-TRUNC($S$2:$S$1501))))-'Opening Balance'!$B$15*SUMPRODUCT(($Z$2:Z371="Online collection 网上收款")*($AA$2:AA371<>"")*($AC$2:AC371-TRUNC($AC$2:AC371))),2))
AE372: =IF(X372="","",ROUND('Opening Balance'!$B$4+SUM($AC$2:AC372)-SUM($AD$2:AD372)+SUMPRODUCT(($Q$2:$Q$1501="Collection 收款")*($R$2:$R$1501="Cheque 支票")*($V$2:$V$1501<>"")*($V$2:$V$1501<=X372)*($S$2:$S$1501-'Opening Balance'!$B$15*($R$2:$R$1501="Cheque 支票")*($S$2:$S$1501-TRUNC($S$2:$S$1501))))-'Opening Balance'!$B$15*SUMPRODUCT(($Z$2:Z372="Online collection 网上收款")*($AA$2:AA372<>"")*($AC$2:AC372-TRUNC($AC$2:AC372))),2))
AE373: =IF(X373="","",ROUND('Opening Balance'!$B$4+SUM($AC$2:AC373)-SUM($AD$2:AD373)+SUMPRODUCT(($Q$2:$Q$1501="Collection 收款")*($R$2:$R$1501="Cheque 支票")*($V$2:$V$1501<>"")*($V$2:$V$1501<=X373)*($S$2:$S$1501-'Opening Balance'!$B$15*($R$2:$R$1501="Cheque 支票")*($S$2:$S$1501-TRUNC($S$2:$S$1501))))-'Opening Balance'!$B$15*SUMPRODUCT(($Z$2:Z373="Online collection 网上收款")*($AA$2:AA373<>"")*($AC$2:AC373-TRUNC($AC$2:AC373))),2))
AE374: =IF(X374="","",ROUND('Opening Balance'!$B$4+SUM($AC$2:AC374)-SUM($AD$2:AD374)+SUMPRODUCT(($Q$2:$Q$1501="Collection 收款")*($R$2:$R$1501="Cheque 支票")*($V$2:$V$1501<>"")*($V$2:$V$1501<=X374)*($S$2:$S$1501-'Opening Balance'!$B$15*($R$2:$R$1501="Cheque 支票")*($S$2:$S$1501-TRUNC($S$2:$S$1501))))-'Opening Balance'!$B$15*SUMPRODUCT(($Z$2:Z374="Online collection 网上收款")*($AA$2:AA374<>"")*($AC$2:AC374-TRUNC($AC$2:AC374))),2))
AE375: =IF(X375="","",ROUND('Opening Balance'!$B$4+SUM($AC$2:AC375)-SUM($AD$2:AD375)+SUMPRODUCT(($Q$2:$Q$1501="Collection 收款")*($R$2:$R$1501="Cheque 支票")*($V$2:$V$1501<>"")*($V$2:$V$1501<=X375)*($S$2:$S$1501-'Opening Balance'!$B$15*($R$2:$R$1501="Cheque 支票")*($S$2:$S$1501-TRUNC($S$2:$S$1501))))-'Opening Balance'!$B$15*SUMPRODUCT(($Z$2:Z375="Online collection 网上收款")*($AA$2:AA375<>"")*($AC$2:AC375-TRUNC($AC$2:AC375))),2))
AE376: =IF(X376="","",ROUND('Opening Balance'!$B$4+SUM($AC$2:AC376)-SUM($AD$2:AD376)+SUMPRODUCT(($Q$2:$Q$1501="Collection 收款")*($R$2:$R$1501="Cheque 支票")*($V$2:$V$1501<>"")*($V$2:$V$1501<=X376)*($S$2:$S$1501-'Opening Balance'!$B$15*($R$2:$R$1501="Cheque 支票")*($S$2:$S$1501-TRUNC($S$2:$S$1501))))-'Opening Balance'!$B$15*SUMPRODUCT(($Z$2:Z376="Online collection 网上收款")*($AA$2:AA376<>"")*($AC$2:AC376-TRUNC($AC$2:AC376))),2))
AE377: =IF(X377="","",ROUND('Opening Balance'!$B$4+SUM($AC$2:AC377)-SUM($AD$2:AD377)+SUMPRODUCT(($Q$2:$Q$1501="Collection 收款")*($R$2:$R$1501="Cheque 支票")*($V$2:$V$1501<>"")*($V$2:$V$1501<=X377)*($S$2:$S$1501-'Opening Balance'!$B$15*($R$2:$R$1501="Cheque 支票")*($S$2:$S$1501-TRUNC($S$2:$S$1501))))-'Opening Balance'!$B$15*SUMPRODUCT(($Z$2:Z377="Online collection 网上收款")*($AA$2:AA377<>"")*($AC$2:AC377-TRUNC($AC$2:AC377))),2))
AE378: =IF(X378="","",ROUND('Opening Balance'!$B$4+SUM($AC$2:AC378)-SUM($AD$2:AD378)+SUMPRODUCT(($Q$2:$Q$1501="Collection 收款")*($R$2:$R$1501="Cheque 支票")*($V$2:$V$1501<>"")*($V$2:$V$1501<=X378)*($S$2:$S$1501-'Opening Balance'!$B$15*($R$2:$R$1501="Cheque 支票")*($S$2:$S$1501-TRUNC($S$2:$S$1501))))-'Opening Balance'!$B$15*SUMPRODUCT(($Z$2:Z378="Online collection 网上收款")*($AA$2:AA378<>"")*($AC$2:AC378-TRUNC($AC$2:AC378))),2))
AE379: =IF(X379="","",ROUND('Opening Balance'!$B$4+SUM($AC$2:AC379)-SUM($AD$2:AD379)+SUMPRODUCT(($Q$2:$Q$1501="Collection 收款")*($R$2:$R$1501="Cheque 支票")*($V$2:$V$1501<>"")*($V$2:$V$1501<=X379)*($S$2:$S$1501-'Opening Balance'!$B$15*($R$2:$R$1501="Cheque 支票")*($S$2:$S$1501-TRUNC($S$2:$S$1501))))-'Opening Balance'!$B$15*SUMPRODUCT(($Z$2:Z379="Online collection 网上收款")*($AA$2:AA379<>"")*($AC$2:AC379-TRUNC($AC$2:AC379))),2))
... AE1501: =IF(X1501="","",ROUND('Opening Balance'!$B$4+SUM($AC$2:AC1501)-SUM($AD$2:AD1501)+SUMPRODUCT(($Q$2:$Q$1501="Collection 收款")*($R$2:$R$1501="Cheque 支票")*($V$2:$V$1501<>"")*($V$2:$V$1501<=X1501)*($S$2:$S$1501-'Opening Balance'!$B$15*($R$2:$R$1501="Cheque 支票")*($S$2:$S$1501-TRUNC($S$2:$S$1501))))-'Opening Balance'!$B$15*SUMPRODUCT(($Z$2:Z1501="Online collection 网上收款")*($AA$2:AA1501<>"")*($AC$2:AC1501-TRUNC($AC$2:AC1501))),2))

Sheet Sales & Collection
A1: Date 日期 | B1: =IF('Daily Sale entry '!$A2="","",'Daily Sale entry '!$A2) | H1: After 调整后 (After) | I1: =IF($B1="","",B1)
A2: Cash Sales 现金销售 | B2: =IF($B1="","",'Daily Sale entry '!B2) | D2: c/f petty cash 今日备用金结转 | E2: =IF($B1="","",'Daily Sale entry '!G2) | H2: Cash Sales 现金销售 | I2: =IF($B1="","",IF(AND(ABS(B12)>'Opening Balance'!$B$13,B12<0),ROUND(B2-B12,2),B2)) | K2: c/f petty cash 今日备用金结转 | L2: =IF($B1="","",IF(ABS(B12)<='Opening Balance'!$B$13,ROUND(E2+B12,2),E2))
A3: Misc Charges 杂项费用 | B3: =IF($B1="","",'Daily Sale entry '!C2) | D3: cash collection 现金收款 | E3: =IF($B1="","",'Daily Sale entry '!H2) | H3: Misc Charges 杂项费用 | I3: =IF($B1="","",IF(AND(ABS(B12)>'Opening Balance'!$B$13,B12>0),ROUND(B3+B12,2),B3)) | K3: cash collection 现金收款 | L3: =IF($B1="","",E3)
A4: Other Charges 其他费用 | B4: =IF($B1="","",'Daily Sale entry '!D2) | D4: Cheque Collection 支票收款 | E4: =IF($B1="","",'Daily Sale entry '!J2) | H4: Other Charges 其他费用 | I4: =IF($B1="","",B4) | K4: Cheque Collection 支票收款 | L4: =IF($B1="","",E4)
A5: Amount 金额 (Cash Sales - Misc - Other) | B5: =IF($B1="","",ROUND(B2-B3-B4,2)) | D5: TNG collection TNG收款 | E5: =IF($B1="","",'Daily Sale entry '!K2) | H5: Amount 金额 (Cash Sales - Misc - Other) | I5: =IF($B1="","",ROUND(I2-I3-I4,2)) | K5: TNG collection TNG收款 | L5: =IF($B1="","",E5)
A6: Credit Collection 赊账收款 | B6: =IF($B1="","",'Daily Sale entry '!E2) | D6: Advance Salary_M 预支薪水_M | E6: =IF($B1="","",'Daily Sale entry '!L2) | H6: Credit Collection 赊账收款 | I6: =IF($B1="","",B6) | K6: Advance Salary_M 预支薪水_M | L6: =IF($B1="","",E6)
A7: Amount 2 金额2 (Amount + Credit Collection) | B7: =IF($B1="","",ROUND(B5+B6,2)) | D7: Advance Salary_H 预支薪水_H | E7: =IF($B1="","",'Daily Sale entry '!M2) | H7: Amount 2 金额2 (Amount + Credit Collection) | I7: =IF($B1="","",ROUND(I5+I6,2)) | K7: Advance Salary_H 预支薪水_H | L7: =IF($B1="","",E7)
A9: b/f petty cash 上日备用金结转 | B9: =IF($B1="","",'Daily Sale entry '!F2) | H9: b/f petty cash 上日备用金结转 | I9: =IF($B1="","",B9)
A10: Total (A) 总计 (A) | B10: =IF($B1="","",ROUND(B7+B9,2)) | D10: Total(B) 总计 (B) | E10: =IF($B1="","",ROUND(E2+E3+E4+E5+E6+E7,2)) | H10: Total© 总计 (C) | I10: =IF($B1="","",ROUND(I7+I9,2)) | K10: Total(D) 总计 (D) | L10: =IF($B1="","",ROUND(L2+L3+L4+L5+L6+L7,2))
A11: Total = Amount 2 + b/f petty cash (金额2 + 上日备用金) | H11: Total = Amount 2 + b/f petty cash (金额2 + 上日备用金)
A12: Different 差额 | B12: =IF($B1="","",ROUND(B10-E10,2)) | D12: =IF($B1="","",IF(ABS(B12)>'Opening Balance'!$B$16,"ALERT 警报: Different over RM"&'Opening Balance'!$B$16&" 差额超过RM"&'Opening Balance'!$B$16&" - please check 请检查",IF(B12=0,"Tied 平衡",IF(ABS(B12)<='Opening Balance'!$B$13,"Small difference 小额差额: adjusted on c/f petty cash 已调整备用金",IF(B12>0,"Short 短收: added to Misc Charges 已加入杂项费用","Over 多收: added to Cash Sales 已加入现金销售"))))) | H12: Different 差额 | I12: =IF($B1="","",ROUND(I10-L10,2))
A15: Date 日期 | B15: =IF('Daily Sale entry '!$A3="","",'Daily Sale entry '!$A3) | H15: After 调整后 (After) | I15: =IF($B15="","",B15)
A16: Cash Sales 现金销售 | B16: =IF($B15="","",'Daily Sale entry '!B3) | D16: c/f petty cash 今日备用金结转 | E16: =IF($B15="","",'Daily Sale entry '!G3) | H16: Cash Sales 现金销售 | I16: =IF($B15="","",IF(AND(ABS(B26)>'Opening Balance'!$B$13,B26<0),ROUND(B16-B26,2),B16)) | K16: c/f petty cash 今日备用金结转 | L16: =IF($B15="","",IF(ABS(B26)<='Opening Balance'!$B$13,ROUND(E16+B26,2),E16))
A17: Misc Charges 杂项费用 | B17: =IF($B15="","",'Daily Sale entry '!C3) | D17: cash collection 现金收款 | E17: =IF($B15="","",'Daily Sale entry '!H3) | H17: Misc Charges 杂项费用 | I17: =IF($B15="","",IF(AND(ABS(B26)>'Opening Balance'!$B$13,B26>0),ROUND(B17+B26,2),B17)) | K17: cash collection 现金收款 | L17: =IF($B15="","",E17)
A18: Other Charges 其他费用 | B18: =IF($B15="","",'Daily Sale entry '!D3) | D18: Cheque Collection 支票收款 | E18: =IF($B15="","",'Daily Sale entry '!J3) | H18: Other Charges 其他费用 | I18: =IF($B15="","",B18) | K18: Cheque Collection 支票收款 | L18: =IF($B15="","",E18)
A19: Amount 金额 (Cash Sales - Misc - Other) | B19: =IF($B15="","",ROUND(B16-B17-B18,2)) | D19: TNG collection TNG收款 | E19: =IF($B15="","",'Daily Sale entry '!K3) | H19: Amount 金额 (Cash Sales - Misc - Other) | I19: =IF($B15="","",ROUND(I16-I17-I18,2)) | K19: TNG collection TNG收款 | L19: =IF($B15="","",E19)
A20: Credit Collection 赊账收款 | B20: =IF($B15="","",'Daily Sale entry '!E3) | D20: Advance Salary_M 预支薪水_M | E20: =IF($B15="","",'Daily Sale entry '!L3) | H20: Credit Collection 赊账收款 | I20: =IF($B15="","",B20) | K20: Advance Salary_M 预支薪水_M | L20: =IF($B15="","",E20)
A21: Amount 2 金额2 (Amount + Credit Collection) | B21: =IF($B15="","",ROUND(B19+B20,2)) | D21: Advance Salary_H 预支薪水_H | E21: =IF($B15="","",'Daily Sale entry '!M3) | H21: Amount 2 金额2 (Amount + Credit Collection) | I21: =IF($B15="","",ROUND(I19+I20,2)) | K21: Advance Salary_H 预支薪水_H | L21: =IF($B15="","",E21)
A23: b/f petty cash 上日备用金结转 | B23: =IF($B15="","",'Daily Sale entry '!F3) | H23: b/f petty cash 上日备用金结转 | I23: =IF($B15="","",B23)
A24: Total (A) 总计 (A) | B24: =IF($B15="","",ROUND(B21+B23,2)) | D24: Total(B) 总计 (B) | E24: =IF($B15="","",ROUND(E16+E17+E18+E19+E20+E21,2)) | H24: Total© 总计 (C) | I24: =IF($B15="","",ROUND(I21+I23,2)) | K24: Total(D) 总计 (D) | L24: =IF($B15="","",ROUND(L16+L17+L18+L19+L20+L21,2))
A25: Total = Amount 2 + b/f petty cash (金额2 + 上日备用金) | H25: Total = Amount 2 + b/f petty cash (金额2 + 上日备用金)
A26: Different 差额 | B26: =IF($B15="","",ROUND(B24-E24,2)) | D26: =IF($B15="","",IF(ABS(B26)>'Opening Balance'!$B$16,"ALERT 警报: Different over RM"&'Opening Balance'!$B$16&" 差额超过RM"&'Opening Balance'!$B$16&" - please check 请检查",IF(B26=0,"Tied 平衡",IF(ABS(B26)<='Opening Balance'!$B$13,"Small difference 小额差额: adjusted on c/f petty cash 已调整备用金",IF(B26>0,"Short 短收: added to Misc Charges 已加入杂项费用","Over 多收: added to Cash Sales 已加入现金销售"))))) | H26: Different 差额 | I26: =IF($B15="","",ROUND(I24-L24,2))
A29: Date 日期 | B29: =IF('Daily Sale entry '!$A4="","",'Daily Sale entry '!$A4) | H29: After 调整后 (After) | I29: =IF($B29="","",B29)
A30: Cash Sales 现金销售 | B30: =IF($B29="","",'Daily Sale entry '!B4) | D30: c/f petty cash 今日备用金结转 | E30: =IF($B29="","",'Daily Sale entry '!G4) | H30: Cash Sales 现金销售 | I30: =IF($B29="","",IF(AND(ABS(B40)>'Opening Balance'!$B$13,B40<0),ROUND(B30-B40,2),B30)) | K30: c/f petty cash 今日备用金结转 | L30: =IF($B29="","",IF(ABS(B40)<='Opening Balance'!$B$13,ROUND(E30+B40,2),E30))
A31: Misc Charges 杂项费用 | B31: =IF($B29="","",'Daily Sale entry '!C4) | D31: cash collection 现金收款 | E31: =IF($B29="","",'Daily Sale entry '!H4) | H31: Misc Charges 杂项费用 | I31: =IF($B29="","",IF(AND(ABS(B40)>'Opening Balance'!$B$13,B40>0),ROUND(B31+B40,2),B31)) | K31: cash collection 现金收款 | L31: =IF($B29="","",E31)
A32: Other Charges 其他费用 | B32: =IF($B29="","",'Daily Sale entry '!D4) | D32: Cheque Collection 支票收款 | E32: =IF($B29="","",'Daily Sale entry '!J4) | H32: Other Charges 其他费用 | I32: =IF($B29="","",B32) | K32: Cheque Collection 支票收款 | L32: =IF($B29="","",E32)
A33: Amount 金额 (Cash Sales - Misc - Other) | B33: =IF($B29="","",ROUND(B30-B31-B32,2)) | D33: TNG collection TNG收款 | E33: =IF($B29="","",'Daily Sale entry '!K4) | H33: Amount 金额 (Cash Sales - Misc - Other) | I33: =IF($B29="","",ROUND(I30-I31-I32,2)) | K33: TNG collection TNG收款 | L33: =IF($B29="","",E33)
A34: Credit Collection 赊账收款 | B34: =IF($B29="","",'Daily Sale entry '!E4) | D34: Advance Salary_M 预支薪水_M | E34: =IF($B29="","",'Daily Sale entry '!L4) | H34: Credit Collection 赊账收款 | I34: =IF($B29="","",B34) | K34: Advance Salary_M 预支薪水_M | L34: =IF($B29="","",E34)
A35: Amount 2 金额2 (Amount + Credit Collection) | B35: =IF($B29="","",ROUND(B33+B34,2)) | D35: Advance Salary_H 预支薪水_H | E35: =IF($B29="","",'Daily Sale entry '!M4) | H35: Amount 2 金额2 (Amount + Credit Collection) | I35: =IF($B29="","",ROUND(I33+I34,2)) | K35: Advance Salary_H 预支薪水_H | L35: =IF($B29="","",E35)
A37: b/f petty cash 上日备用金结转 | B37: =IF($B29="","",'Daily Sale entry '!F4) | H37: b/f petty cash 上日备用金结转 | I37: =IF($B29="","",B37)
A38: Total (A) 总计 (A) | B38: =IF($B29="","",ROUND(B35+B37,2)) | D38: Total(B) 总计 (B) | E38: =IF($B29="","",ROUND(E30+E31+E32+E33+E34+E35,2)) | H38: Total© 总计 (C) | I38: =IF($B29="","",ROUND(I35+I37,2)) | K38: Total(D) 总计 (D) | L38: =IF($B29="","",ROUND(L30+L31+L32+L33+L34+L35,2))
A39: Total = Amount 2 + b/f petty cash (金额2 + 上日备用金) | H39: Total = Amount 2 + b/f petty cash (金额2 + 上日备用金)
A40: Different 差额 | B40: =IF($B29="","",ROUND(B38-E38,2)) | D40: =IF($B29="","",IF(ABS(B40)>'Opening Balance'!$B$16,"ALERT 警报: Different over RM"&'Opening Balance'!$B$16&" 差额超过RM"&'Opening Balance'!$B$16&" - please check 请检查",IF(B40=0,"Tied 平衡",IF(ABS(B40)<='Opening Balance'!$B$13,"Small difference 小额差额: adjusted on c/f petty cash 已调整备用金",IF(B40>0,"Short 短收: added to Misc Charges 已加入杂项费用","Over 多收: added to Cash Sales 已加入现金销售"))))) | H40: Different 差额 | I40: =IF($B29="","",ROUND(I38-L38,2))
A43: Date 日期 | B43: =IF('Daily Sale entry '!$A5="","",'Daily Sale entry '!$A5) | H43: After 调整后 (After) | I43: =IF($B43="","",B43)
A44: Cash Sales 现金销售 | B44: =IF($B43="","",'Daily Sale entry '!B5) | D44: c/f petty cash 今日备用金结转 | E44: =IF($B43="","",'Daily Sale entry '!G5) | H44: Cash Sales 现金销售 | I44: =IF($B43="","",IF(AND(ABS(B54)>'Opening Balance'!$B$13,B54<0),ROUND(B44-B54,2),B44)) | K44: c/f petty cash 今日备用金结转 | L44: =IF($B43="","",IF(ABS(B54)<='Opening Balance'!$B$13,ROUND(E44+B54,2),E44))
A45: Misc Charges 杂项费用 | B45: =IF($B43="","",'Daily Sale entry '!C5) | D45: cash collection 现金收款 | E45: =IF($B43="","",'Daily Sale entry '!H5) | H45: Misc Charges 杂项费用 | I45: =IF($B43="","",IF(AND(ABS(B54)>'Opening Balance'!$B$13,B54>0),ROUND(B45+B54,2),B45)) | K45: cash collection 现金收款 | L45: =IF($B43="","",E45)
A46: Other Charges 其他费用 | B46: =IF($B43="","",'Daily Sale entry '!D5) | D46: Cheque Collection 支票收款 | E46: =IF($B43="","",'Daily Sale entry '!J5) | H46: Other Charges 其他费用 | I46: =IF($B43="","",B46) | K46: Cheque Collection 支票收款 | L46: =IF($B43="","",E46)
A47: Amount 金额 (Cash Sales - Misc - Other) | B47: =IF($B43="","",ROUND(B44-B45-B46,2)) | D47: TNG collection TNG收款 | E47: =IF($B43="","",'Daily Sale entry '!K5) | H47: Amount 金额 (Cash Sales - Misc - Other) | I47: =IF($B43="","",ROUND(I44-I45-I46,2)) | K47: TNG collection TNG收款 | L47: =IF($B43="","",E47)
A48: Credit Collection 赊账收款 | B48: =IF($B43="","",'Daily Sale entry '!E5) | D48: Advance Salary_M 预支薪水_M | E48: =IF($B43="","",'Daily Sale entry '!L5) | H48: Credit Collection 赊账收款 | I48: =IF($B43="","",B48) | K48: Advance Salary_M 预支薪水_M | L48: =IF($B43="","",E48)
A49: Amount 2 金额2 (Amount + Credit Collection) | B49: =IF($B43="","",ROUND(B47+B48,2)) | D49: Advance Salary_H 预支薪水_H | E49: =IF($B43="","",'Daily Sale entry '!M5) | H49: Amount 2 金额2 (Amount + Credit Collection) | I49: =IF($B43="","",ROUND(I47+I48,2)) | K49: Advance Salary_H 预支薪水_H | L49: =IF($B43="","",E49)
A51: b/f petty cash 上日备用金结转 | B51: =IF($B43="","",'Daily Sale entry '!F5) | H51: b/f petty cash 上日备用金结转 | I51: =IF($B43="","",B51)
A52: Total (A) 总计 (A) | B52: =IF($B43="","",ROUND(B49+B51,2)) | D52: Total(B) 总计 (B) | E52: =IF($B43="","",ROUND(E44+E45+E46+E47+E48+E49,2)) | H52: Total© 总计 (C) | I52: =IF($B43="","",ROUND(I49+I51,2)) | K52: Total(D) 总计 (D) | L52: =IF($B43="","",ROUND(L44+L45+L46+L47+L48+L49,2))
A53: Total = Amount 2 + b/f petty cash (金额2 + 上日备用金) | H53: Total = Amount 2 + b/f petty cash (金额2 + 上日备用金)
A54: Different 差额 | B54: =IF($B43="","",ROUND(B52-E52,2)) | D54: =IF($B43="","",IF(ABS(B54)>'Opening Balance'!$B$16,"ALERT 警报: Different over RM"&'Opening Balance'!$B$16&" 差额超过RM"&'Opening Balance'!$B$16&" - please check 请检查",IF(B54=0,"Tied 平衡",IF(ABS(B54)<='Opening Balance'!$B$13,"Small difference 小额差额: adjusted on c/f petty cash 已调整备用金",IF(B54>0,"Short 短收: added to Misc Charges 已加入杂项费用","Over 多收: added to Cash Sales 已加入现金销售"))))) | H54: Different 差额 | I54: =IF($B43="","",ROUND(I52-L52,2))
A57: Date 日期 | B57: =IF('Daily Sale entry '!$A6="","",'Daily Sale entry '!$A6) | H57: After 调整后 (After) | I57: =IF($B57="","",B57)
A58: Cash Sales 现金销售 | B58: =IF($B57="","",'Daily Sale entry '!B6) | D58: c/f petty cash 今日备用金结转 | E58: =IF($B57="","",'Daily Sale entry '!G6) | H58: Cash Sales 现金销售 | I58: =IF($B57="","",IF(AND(ABS(B68)>'Opening Balance'!$B$13,B68<0),ROUND(B58-B68,2),B58)) | K58: c/f petty cash 今日备用金结转 | L58: =IF($B57="","",IF(ABS(B68)<='Opening Balance'!$B$13,ROUND(E58+B68,2),E58))
A59: Misc Charges 杂项费用 | B59: =IF($B57="","",'Daily Sale entry '!C6) | D59: cash collection 现金收款 | E59: =IF($B57="","",'Daily Sale entry '!H6) | H59: Misc Charges 杂项费用 | I59: =IF($B57="","",IF(AND(ABS(B68)>'Opening Balance'!$B$13,B68>0),ROUND(B59+B68,2),B59)) | K59: cash collection 现金收款 | L59: =IF($B57="","",E59)
A60: Other Charges 其他费用 | B60: =IF($B57="","",'Daily Sale entry '!D6) | D60: Cheque Collection 支票收款 | E60: =IF($B57="","",'Daily Sale entry '!J6) | H60: Other Charges 其他费用 | I60: =IF($B57="","",B60) | K60: Cheque Collection 支票收款 | L60: =IF($B57="","",E60)
A61: Amount 金额 (Cash Sales - Misc - Other) | B61: =IF($B57="","",ROUND(B58-B59-B60,2)) | D61: TNG collection TNG收款 | E61: =IF($B57="","",'Daily Sale entry '!K6) | H61: Amount 金额 (Cash Sales - Misc - Other) | I61: =IF($B57="","",ROUND(I58-I59-I60,2)) | K61: TNG collection TNG收款 | L61: =IF($B57="","",E61)
A62: Credit Collection 赊账收款 | B62: =IF($B57="","",'Daily Sale entry '!E6) | D62: Advance Salary_M 预支薪水_M | E62: =IF($B57="","",'Daily Sale entry '!L6) | H62: Credit Collection 赊账收款 | I62: =IF($B57="","",B62) | K62: Advance Salary_M 预支薪水_M | L62: =IF($B57="","",E62)
A63: Amount 2 金额2 (Amount + Credit Collection) | B63: =IF($B57="","",ROUND(B61+B62,2)) | D63: Advance Salary_H 预支薪水_H | E63: =IF($B57="","",'Daily Sale entry '!M6) | H63: Amount 2 金额2 (Amount + Credit Collection) | I63: =IF($B57="","",ROUND(I61+I62,2)) | K63: Advance Salary_H 预支薪水_H | L63: =IF($B57="","",E63)
A65: b/f petty cash 上日备用金结转 | B65: =IF($B57="","",'Daily Sale entry '!F6) | H65: b/f petty cash 上日备用金结转 | I65: =IF($B57="","",B65)
A66: Total (A) 总计 (A) | B66: =IF($B57="","",ROUND(B63+B65,2)) | D66: Total(B) 总计 (B) | E66: =IF($B57="","",ROUND(E58+E59+E60+E61+E62+E63,2)) | H66: Total© 总计 (C) | I66: =IF($B57="","",ROUND(I63+I65,2)) | K66: Total(D) 总计 (D) | L66: =IF($B57="","",ROUND(L58+L59+L60+L61+L62+L63,2))
A67: Total = Amount 2 + b/f petty cash (金额2 + 上日备用金) | H67: Total = Amount 2 + b/f petty cash (金额2 + 上日备用金)
A68: Different 差额 | B68: =IF($B57="","",ROUND(B66-E66,2)) | D68: =IF($B57="","",IF(ABS(B68)>'Opening Balance'!$B$16,"ALERT 警报: Different over RM"&'Opening Balance'!$B$16&" 差额超过RM"&'Opening Balance'!$B$16&" - please check 请检查",IF(B68=0,"Tied 平衡",IF(ABS(B68)<='Opening Balance'!$B$13,"Small difference 小额差额: adjusted on c/f petty cash 已调整备用金",IF(B68>0,"Short 短收: added to Misc Charges 已加入杂项费用","Over 多收: added to Cash Sales 已加入现金销售"))))) | H68: Different 差额 | I68: =IF($B57="","",ROUND(I66-L66,2))
A71: Date 日期 | B71: =IF('Daily Sale entry '!$A7="","",'Daily Sale entry '!$A7) | H71: After 调整后 (After) | I71: =IF($B71="","",B71)
A72: Cash Sales 现金销售 | B72: =IF($B71="","",'Daily Sale entry '!B7) | D72: c/f petty cash 今日备用金结转 | E72: =IF($B71="","",'Daily Sale entry '!G7) | H72: Cash Sales 现金销售 | I72: =IF($B71="","",IF(AND(ABS(B82)>'Opening Balance'!$B$13,B82<0),ROUND(B72-B82,2),B72)) | K72: c/f petty cash 今日备用金结转 | L72: =IF($B71="","",IF(ABS(B82)<='Opening Balance'!$B$13,ROUND(E72+B82,2),E72))
A73: Misc Charges 杂项费用 | B73: =IF($B71="","",'Daily Sale entry '!C7) | D73: cash collection 现金收款 | E73: =IF($B71="","",'Daily Sale entry '!H7) | H73: Misc Charges 杂项费用 | I73: =IF($B71="","",IF(AND(ABS(B82)>'Opening Balance'!$B$13,B82>0),ROUND(B73+B82,2),B73)) | K73: cash collection 现金收款 | L73: =IF($B71="","",E73)
A74: Other Charges 其他费用 | B74: =IF($B71="","",'Daily Sale entry '!D7) | D74: Cheque Collection 支票收款 | E74: =IF($B71="","",'Daily Sale entry '!J7) | H74: Other Charges 其他费用 | I74: =IF($B71="","",B74) | K74: Cheque Collection 支票收款 | L74: =IF($B71="","",E74)
A75: Amount 金额 (Cash Sales - Misc - Other) | B75: =IF($B71="","",ROUND(B72-B73-B74,2)) | D75: TNG collection TNG收款 | E75: =IF($B71="","",'Daily Sale entry '!K7) | H75: Amount 金额 (Cash Sales - Misc - Other) | I75: =IF($B71="","",ROUND(I72-I73-I74,2)) | K75: TNG collection TNG收款 | L75: =IF($B71="","",E75)
A76: Credit Collection 赊账收款 | B76: =IF($B71="","",'Daily Sale entry '!E7) | D76: Advance Salary_M 预支薪水_M | E76: =IF($B71="","",'Daily Sale entry '!L7) | H76: Credit Collection 赊账收款 | I76: =IF($B71="","",B76) | K76: Advance Salary_M 预支薪水_M | L76: =IF($B71="","",E76)
A77: Amount 2 金额2 (Amount + Credit Collection) | B77: =IF($B71="","",ROUND(B75+B76,2)) | D77: Advance Salary_H 预支薪水_H | E77: =IF($B71="","",'Daily Sale entry '!M7) | H77: Amount 2 金额2 (Amount + Credit Collection) | I77: =IF($B71="","",ROUND(I75+I76,2)) | K77: Advance Salary_H 预支薪水_H | L77: =IF($B71="","",E77)
A79: b/f petty cash 上日备用金结转 | B79: =IF($B71="","",'Daily Sale entry '!F7) | H79: b/f petty cash 上日备用金结转 | I79: =IF($B71="","",B79)
A80: Total (A) 总计 (A) | B80: =IF($B71="","",ROUND(B77+B79,2)) | D80: Total(B) 总计 (B) | E80: =IF($B71="","",ROUND(E72+E73+E74+E75+E76+E77,2)) | H80: Total© 总计 (C) | I80: =IF($B71="","",ROUND(I77+I79,2)) | K80: Total(D) 总计 (D) | L80: =IF($B71="","",ROUND(L72+L73+L74+L75+L76+L77,2))
A81: Total = Amount 2 + b/f petty cash (金额2 + 上日备用金) | H81: Total = Amount 2 + b/f petty cash (金额2 + 上日备用金)
A82: Different 差额 | B82: =IF($B71="","",ROUND(B80-E80,2)) | D82: =IF($B71="","",IF(ABS(B82)>'Opening Balance'!$B$16,"ALERT 警报: Different over RM"&'Opening Balance'!$B$16&" 差额超过RM"&'Opening Balance'!$B$16&" - please check 请检查",IF(B82=0,"Tied 平衡",IF(ABS(B82)<='Opening Balance'!$B$13,"Small difference 小额差额: adjusted on c/f petty cash 已调整备用金",IF(B82>0,"Short 短收: added to Misc Charges 已加入杂项费用","Over 多收: added to Cash Sales 已加入现金销售"))))) | H82: Different 差额 | I82: =IF($B71="","",ROUND(I80-L80,2))
A85: Date 日期 | B85: =IF('Daily Sale entry '!$A8="","",'Daily Sale entry '!$A8) | H85: After 调整后 (After) | I85: =IF($B85="","",B85)
A86: Cash Sales 现金销售 | B86: =IF($B85="","",'Daily Sale entry '!B8) | D86: c/f petty cash 今日备用金结转 | E86: =IF($B85="","",'Daily Sale entry '!G8) | H86: Cash Sales 现金销售 | I86: =IF($B85="","",IF(AND(ABS(B96)>'Opening Balance'!$B$13,B96<0),ROUND(B86-B96,2),B86)) | K86: c/f petty cash 今日备用金结转 | L86: =IF($B85="","",IF(ABS(B96)<='Opening Balance'!$B$13,ROUND(E86+B96,2),E86))
A87: Misc Charges 杂项费用 | B87: =IF($B85="","",'Daily Sale entry '!C8) | D87: cash collection 现金收款 | E87: =IF($B85="","",'Daily Sale entry '!H8) | H87: Misc Charges 杂项费用 | I87: =IF($B85="","",IF(AND(ABS(B96)>'Opening Balance'!$B$13,B96>0),ROUND(B87+B96,2),B87)) | K87: cash collection 现金收款 | L87: =IF($B85="","",E87)
A88: Other Charges 其他费用 | B88: =IF($B85="","",'Daily Sale entry '!D8) | D88: Cheque Collection 支票收款 | E88: =IF($B85="","",'Daily Sale entry '!J8) | H88: Other Charges 其他费用 | I88: =IF($B85="","",B88) | K88: Cheque Collection 支票收款 | L88: =IF($B85="","",E88)
A89: Amount 金额 (Cash Sales - Misc - Other) | B89: =IF($B85="","",ROUND(B86-B87-B88,2)) | D89: TNG collection TNG收款 | E89: =IF($B85="","",'Daily Sale entry '!K8) | H89: Amount 金额 (Cash Sales - Misc - Other) | I89: =IF($B85="","",ROUND(I86-I87-I88,2)) | K89: TNG collection TNG收款 | L89: =IF($B85="","",E89)
A90: Credit Collection 赊账收款 | B90: =IF($B85="","",'Daily Sale entry '!E8) | D90: Advance Salary_M 预支薪水_M | E90: =IF($B85="","",'Daily Sale entry '!L8) | H90: Credit Collection 赊账收款 | I90: =IF($B85="","",B90) | K90: Advance Salary_M 预支薪水_M | L90: =IF($B85="","",E90)
A91: Amount 2 金额2 (Amount + Credit Collection) | B91: =IF($B85="","",ROUND(B89+B90,2)) | D91: Advance Salary_H 预支薪水_H | E91: =IF($B85="","",'Daily Sale entry '!M8) | H91: Amount 2 金额2 (Amount + Credit Collection) | I91: =IF($B85="","",ROUND(I89+I90,2)) | K91: Advance Salary_H 预支薪水_H | L91: =IF($B85="","",E91)
A93: b/f petty cash 上日备用金结转 | B93: =IF($B85="","",'Daily Sale entry '!F8) | H93: b/f petty cash 上日备用金结转 | I93: =IF($B85="","",B93)
A94: Total (A) 总计 (A) | B94: =IF($B85="","",ROUND(B91+B93,2)) | D94: Total(B) 总计 (B) | E94: =IF($B85="","",ROUND(E86+E87+E88+E89+E90+E91,2)) | H94: Total© 总计 (C) | I94: =IF($B85="","",ROUND(I91+I93,2)) | K94: Total(D) 总计 (D) | L94: =IF($B85="","",ROUND(L86+L87+L88+L89+L90+L91,2))
A95: Total = Amount 2 + b/f petty cash (金额2 + 上日备用金) | H95: Total = Amount 2 + b/f petty cash (金额2 + 上日备用金)
A96: Different 差额 | B96: =IF($B85="","",ROUND(B94-E94,2)) | D96: =IF($B85="","",IF(ABS(B96)>'Opening Balance'!$B$16,"ALERT 警报: Different over RM"&'Opening Balance'!$B$16&" 差额超过RM"&'Opening Balance'!$B$16&" - please check 请检查",IF(B96=0,"Tied 平衡",IF(ABS(B96)<='Opening Balance'!$B$13,"Small difference 小额差额: adjusted on c/f petty cash 已调整备用金",IF(B96>0,"Short 短收: added to Misc Charges 已加入杂项费用","Over 多收: added to Cash Sales 已加入现金销售"))))) | H96: Different 差额 | I96: =IF($B85="","",ROUND(I94-L94,2))
A99: Date 日期 | B99: =IF('Daily Sale entry '!$A9="","",'Daily Sale entry '!$A9) | H99: After 调整后 (After) | I99: =IF($B99="","",B99)
A100: Cash Sales 现金销售 | B100: =IF($B99="","",'Daily Sale entry '!B9) | D100: c/f petty cash 今日备用金结转 | E100: =IF($B99="","",'Daily Sale entry '!G9) | H100: Cash Sales 现金销售 | I100: =IF($B99="","",IF(AND(ABS(B110)>'Opening Balance'!$B$13,B110<0),ROUND(B100-B110,2),B100)) | K100: c/f petty cash 今日备用金结转 | L100: =IF($B99="","",IF(ABS(B110)<='Opening Balance'!$B$13,ROUND(E100+B110,2),E100))
A101: Misc Charges 杂项费用 | B101: =IF($B99="","",'Daily Sale entry '!C9) | D101: cash collection 现金收款 | E101: =IF($B99="","",'Daily Sale entry '!H9) | H101: Misc Charges 杂项费用 | I101: =IF($B99="","",IF(AND(ABS(B110)>'Opening Balance'!$B$13,B110>0),ROUND(B101+B110,2),B101)) | K101: cash collection 现金收款 | L101: =IF($B99="","",E101)
A102: Other Charges 其他费用 | B102: =IF($B99="","",'Daily Sale entry '!D9) | D102: Cheque Collection 支票收款 | E102: =IF($B99="","",'Daily Sale entry '!J9) | H102: Other Charges 其他费用 | I102: =IF($B99="","",B102) | K102: Cheque Collection 支票收款 | L102: =IF($B99="","",E102)
A103: Amount 金额 (Cash Sales - Misc - Other) | B103: =IF($B99="","",ROUND(B100-B101-B102,2)) | D103: TNG collection TNG收款 | E103: =IF($B99="","",'Daily Sale entry '!K9) | H103: Amount 金额 (Cash Sales - Misc - Other) | I103: =IF($B99="","",ROUND(I100-I101-I102,2)) | K103: TNG collection TNG收款 | L103: =IF($B99="","",E103)
A104: Credit Collection 赊账收款 | B104: =IF($B99="","",'Daily Sale entry '!E9) | D104: Advance Salary_M 预支薪水_M | E104: =IF($B99="","",'Daily Sale entry '!L9) | H104: Credit Collection 赊账收款 | I104: =IF($B99="","",B104) | K104: Advance Salary_M 预支薪水_M | L104: =IF($B99="","",E104)
A105: Amount 2 金额2 (Amount + Credit Collection) | B105: =IF($B99="","",ROUND(B103+B104,2)) | D105: Advance Salary_H 预支薪水_H | E105: =IF($B99="","",'Daily Sale entry '!M9) | H105: Amount 2 金额2 (Amount + Credit Collection) | I105: =IF($B99="","",ROUND(I103+I104,2)) | K105: Advance Salary_H 预支薪水_H | L105: =IF($B99="","",E105)
A107: b/f petty cash 上日备用金结转 | B107: =IF($B99="","",'Daily Sale entry '!F9) | H107: b/f petty cash 上日备用金结转 | I107: =IF($B99="","",B107)
A108: Total (A) 总计 (A) | B108: =IF($B99="","",ROUND(B105+B107,2)) | D108: Total(B) 总计 (B) | E108: =IF($B99="","",ROUND(E100+E101+E102+E103+E104+E105,2)) | H108: Total© 总计 (C) | I108: =IF($B99="","",ROUND(I105+I107,2)) | K108: Total(D) 总计 (D) | L108: =IF($B99="","",ROUND(L100+L101+L102+L103+L104+L105,2))
A109: Total = Amount 2 + b/f petty cash (金额2 + 上日备用金) | H109: Total = Amount 2 + b/f petty cash (金额2 + 上日备用金)
A110: Different 差额 | B110: =IF($B99="","",ROUND(B108-E108,2)) | D110: =IF($B99="","",IF(ABS(B110)>'Opening Balance'!$B$16,"ALERT 警报: Different over RM"&'Opening Balance'!$B$16&" 差额超过RM"&'Opening Balance'!$B$16&" - please check 请检查",IF(B110=0,"Tied 平衡",IF(ABS(B110)<='Opening Balance'!$B$13,"Small difference 小额差额: adjusted on c/f petty cash 已调整备用金",IF(B110>0,"Short 短收: added to Misc Charges 已加入杂项费用","Over 多收: added to Cash Sales 已加入现金销售"))))) | H110: Different 差额 | I110: =IF($B99="","",ROUND(I108-L108,2))
A113: Date 日期 | B113: =IF('Daily Sale entry '!$A10="","",'Daily Sale entry '!$A10) | H113: After 调整后 (After) | I113: =IF($B113="","",B113)
A114: Cash Sales 现金销售 | B114: =IF($B113="","",'Daily Sale entry '!B10) | D114: c/f petty cash 今日备用金结转 | E114: =IF($B113="","",'Daily Sale entry '!G10) | H114: Cash Sales 现金销售 | I114: =IF($B113="","",IF(AND(ABS(B124)>'Opening Balance'!$B$13,B124<0),ROUND(B114-B124,2),B114)) | K114: c/f petty cash 今日备用金结转 | L114: =IF($B113="","",IF(ABS(B124)<='Opening Balance'!$B$13,ROUND(E114+B124,2),E114))
A115: Misc Charges 杂项费用 | B115: =IF($B113="","",'Daily Sale entry '!C10) | D115: cash collection 现金收款 | E115: =IF($B113="","",'Daily Sale entry '!H10) | H115: Misc Charges 杂项费用 | I115: =IF($B113="","",IF(AND(ABS(B124)>'Opening Balance'!$B$13,B124>0),ROUND(B115+B124,2),B115)) | K115: cash collection 现金收款 | L115: =IF($B113="","",E115)
A116: Other Charges 其他费用 | B116: =IF($B113="","",'Daily Sale entry '!D10) | D116: Cheque Collection 支票收款 | E116: =IF($B113="","",'Daily Sale entry '!J10) | H116: Other Charges 其他费用 | I116: =IF($B113="","",B116) | K116: Cheque Collection 支票收款 | L116: =IF($B113="","",E116)
A117: Amount 金额 (Cash Sales - Misc - Other) | B117: =IF($B113="","",ROUND(B114-B115-B116,2)) | D117: TNG collection TNG收款 | E117: =IF($B113="","",'Daily Sale entry '!K10) | H117: Amount 金额 (Cash Sales - Misc - Other) | I117: =IF($B113="","",ROUND(I114-I115-I116,2)) | K117: TNG collection TNG收款 | L117: =IF($B113="","",E117)
A118: Credit Collection 赊账收款 | B118: =IF($B113="","",'Daily Sale entry '!E10) | D118: Advance Salary_M 预支薪水_M | E118: =IF($B113="","",'Daily Sale entry '!L10) | H118: Credit Collection 赊账收款 | I118: =IF($B113="","",B118) | K118: Advance Salary_M 预支薪水_M | L118: =IF($B113="","",E118)
A119: Amount 2 金额2 (Amount + Credit Collection) | B119: =IF($B113="","",ROUND(B117+B118,2)) | D119: Advance Salary_H 预支薪水_H | E119: =IF($B113="","",'Daily Sale entry '!M10) | H119: Amount 2 金额2 (Amount + Credit Collection) | I119: =IF($B113="","",ROUND(I117+I118,2)) | K119: Advance Salary_H 预支薪水_H | L119: =IF($B113="","",E119)
A121: b/f petty cash 上日备用金结转 | B121: =IF($B113="","",'Daily Sale entry '!F10) | H121: b/f petty cash 上日备用金结转 | I121: =IF($B113="","",B121)
A122: Total (A) 总计 (A) | B122: =IF($B113="","",ROUND(B119+B121,2)) | D122: Total(B) 总计 (B) | E122: =IF($B113="","",ROUND(E114+E115+E116+E117+E118+E119,2)) | H122: Total© 总计 (C) | I122: =IF($B113="","",ROUND(I119+I121,2)) | K122: Total(D) 总计 (D) | L122: =IF($B113="","",ROUND(L114+L115+L116+L117+L118+L119,2))
A123: Total = Amount 2 + b/f petty cash (金额2 + 上日备用金) | H123: Total = Amount 2 + b/f petty cash (金额2 + 上日备用金)
A124: Different 差额 | B124: =IF($B113="","",ROUND(B122-E122,2)) | D124: =IF($B113="","",IF(ABS(B124)>'Opening Balance'!$B$16,"ALERT 警报: Different over RM"&'Opening Balance'!$B$16&" 差额超过RM"&'Opening Balance'!$B$16&" - please check 请检查",IF(B124=0,"Tied 平衡",IF(ABS(B124)<='Opening Balance'!$B$13,"Small difference 小额差额: adjusted on c/f petty cash 已调整备用金",IF(B124>0,"Short 短收: added to Misc Charges 已加入杂项费用","Over 多收: added to Cash Sales 已加入现金销售"))))) | H124: Different 差额 | I124: =IF($B113="","",ROUND(I122-L122,2))
A127: Date 日期 | B127: =IF('Daily Sale entry '!$A11="","",'Daily Sale entry '!$A11) | H127: After 调整后 (After) | I127: =IF($B127="","",B127)
...

Sheet Cash flow
A1: Date 日期 | B1: Bank balance 银行余额 | C1: Cheque in hand(unit) 手头支票(张) | D1: Cheque in hand(RM) 手头支票(RM) | E1: petty cash 备用金 | F1: advance salary 预支薪水 | G1: balance cash(yet reach RM 5000) 零散现金(未满RM5000) | H1: Cash in hand (RM) 手头现金(RM) | I1: Total 总计 | J1: AR & AP Balance c/f AR&AP 结余转下日 | K1: Check (should be 0) 核对(应为0) | L1: Alert 警报
A2: =IF('Daily Sale entry '!A2="","",'Daily Sale entry '!A2) | B2: =IF($A2="","",ROUND('Opening Balance'!$B$4+SUM('Daily Sale entry '!$K$2:K2)+SUMIFS('Daily Sale entry '!$AC$2:$AC$1501,'Daily Sale entry '!$X$2:$X$1501,"<="&$A2)-SUMIFS('Daily Sale entry '!$AD$2:$AD$1501,'Daily Sale entry '!$X$2:$X$1501,"<="&$A2)+SUMPRODUCT(('Daily Sale entry '!$Q$2:$Q$1501="Collection 收款")*('Daily Sale entry '!$R$2:$R$1501="Cheque 支票")*('Daily Sale entry '!$V$2:$V$1501<>"")*('Daily Sale entry '!$V$2:$V$1501<=$A2)*('Daily Sale entry '!$S$2:$S$1501-'Opening Balance'!$B$15*('Daily Sale entry '!$R$2:$R$1501="Cheque 支票")*('Daily Sale entry '!$S$2:$S$1501-TRUNC('Daily Sale entry '!$S$2:$S$1501))))-'Opening Balance'!$B$15*SUMPRODUCT(('Daily Sale entry '!$X$2:$X$1501<=$A2)*('Daily Sale entry '!$Z$2:$Z$1501="Online collection 网上收款")*('Daily Sale entry '!$AA$2:$AA$1501<>"")*('Daily Sale entry '!$AC$2:$AC$1501-TRUNC('Daily Sale entry '!$AC$2:$AC$1501))),2)) | C2: =IF($A2="","",'Opening Balance'!$B$5+SUM('Daily Sale entry '!$I$2:I2)-SUMIFS('Daily Sale entry '!$AB$2:$AB$1501,'Daily Sale entry '!$X$2:$X$1501,"<="&$A2,'Daily Sale entry '!$Z$2:$Z$1501,"Cheque deposit 支票存入")-COUNTIFS('Daily Sale entry '!$Q$2:$Q$1501,"Collection 收款",'Daily Sale entry '!$R$2:$R$1501,"Cheque 支票",'Daily Sale entry '!$V$2:$V$1501,"<="&$A2)) | D2: =IF($A2="","",ROUND('Opening Balance'!$B$6+SUM('Daily Sale entry '!$J$2:J2)-SUMIFS('Daily Sale entry '!$AC$2:$AC$1501,'Daily Sale entry '!$X$2:$X$1501,"<="&$A2,'Daily Sale entry '!$Z$2:$Z$1501,"Cheque deposit 支票存入")-SUMPRODUCT(('Daily Sale entry '!$Q$2:$Q$1501="Collection 收款")*('Daily Sale entry '!$R$2:$R$1501="Cheque 支票")*('Daily Sale entry '!$V$2:$V$1501<>"")*('Daily Sale entry '!$V$2:$V$1501<=$A2)*('Daily Sale entry '!$S$2:$S$1501-'Opening Balance'!$B$15*('Daily Sale entry '!$R$2:$R$1501="Cheque 支票")*('Daily Sale entry '!$S$2:$S$1501-TRUNC('Daily Sale entry '!$S$2:$S$1501)))),2)) | E2: =IF($A2="","",'Opening Balance'!$B$7) | F2: =IF($A2="","",ROUND(SUMIFS('Daily Sale entry '!$L$2:$L$367,'Daily Sale entry '!$A$2:$A$367,">="&DATE(YEAR($A2),MONTH($A2),1),'Daily Sale entry '!$A$2:$A$367,"<="&$A2)+SUMIFS('Daily Sale entry '!$M$2:$M$367,'Daily Sale entry '!$A$2:$A$367,">="&DATE(YEAR($A2),MONTH($A2),1),'Daily Sale entry '!$A$2:$A$367,"<="&$A2)+IF(AND(YEAR($A2)=YEAR('Daily Sale entry '!$A$2),MONTH($A2)=MONTH('Daily Sale entry '!$A$2)),'Opening Balance'!$B$8,0),2)) | G2: =IF($A2="","",MOD(ROUND('Opening Balance'!$B$9+SUMIFS('Sales & Collection'!$L$1:$L$3,'Sales & Collection'!$K$1:$K$3,"cash collection*"),2),'Opening Balance'!$B$11)) | H2: =IF($A2="","",ROUND('Opening Balance'!$B$10+'Opening Balance'!$B$9+SUMIFS('Sales & Collection'!$L$1:$L$3,'Sales & Collection'!$K$1:$K$3,"cash collection*")-G2-SUMIFS('Daily Sale entry '!$AC$2:$AC$1501,'Daily Sale entry '!$X$2:$X$1501,"<="&$A2,'Daily Sale entry '!$Z$2:$Z$1501,"Cash deposit 现金存入"),2)) | I2: =IF($A2="","",ROUND(B2+D2+E2+F2+G2+H2,2)) | J2: =IF($A2="","",'AR & AP'!K3) | K2: =IF($A2="","",ROUND(I2-J2-SUMIFS('Daily Sale entry '!$AC$2:$AC$1501,'Daily Sale entry '!$X$2:$X$1501,"<="&$A2,'Daily Sale entry '!$Z$2:$Z$1501,"Other deposit 其他存入")+SUMIFS('Daily Sale entry '!$AD$2:$AD$1501,'Daily Sale entry '!$X$2:$X$1501,"<="&$A2)+('Opening Balance'!$B$8+SUM('Daily Sale entry '!$L$2:M2)-F2),2)) | L2: =IF($A2="","",IF(ABS('Sales & Collection'!$B$12)>'Opening Balance'!$B$16,"ALERT 警报: Different "&TEXT('Sales & Collection'!$B$12,"#,##0.00")&" 差额过大",""))
A3: =IF('Daily Sale entry '!A3="","",'Daily Sale entry '!A3) | B3: =IF($A3="","",ROUND('Opening Balance'!$B$4+SUM('Daily Sale entry '!$K$2:K3)+SUMIFS('Daily Sale entry '!$AC$2:$AC$1501,'Daily Sale entry '!$X$2:$X$1501,"<="&$A3)-SUMIFS('Daily Sale entry '!$AD$2:$AD$1501,'Daily Sale entry '!$X$2:$X$1501,"<="&$A3)+SUMPRODUCT(('Daily Sale entry '!$Q$2:$Q$1501="Collection 收款")*('Daily Sale entry '!$R$2:$R$1501="Cheque 支票")*('Daily Sale entry '!$V$2:$V$1501<>"")*('Daily Sale entry '!$V$2:$V$1501<=$A3)*('Daily Sale entry '!$S$2:$S$1501-'Opening Balance'!$B$15*('Daily Sale entry '!$R$2:$R$1501="Cheque 支票")*('Daily Sale entry '!$S$2:$S$1501-TRUNC('Daily Sale entry '!$S$2:$S$1501))))-'Opening Balance'!$B$15*SUMPRODUCT(('Daily Sale entry '!$X$2:$X$1501<=$A3)*('Daily Sale entry '!$Z$2:$Z$1501="Online collection 网上收款")*('Daily Sale entry '!$AA$2:$AA$1501<>"")*('Daily Sale entry '!$AC$2:$AC$1501-TRUNC('Daily Sale entry '!$AC$2:$AC$1501))),2)) | C3: =IF($A3="","",'Opening Balance'!$B$5+SUM('Daily Sale entry '!$I$2:I3)-SUMIFS('Daily Sale entry '!$AB$2:$AB$1501,'Daily Sale entry '!$X$2:$X$1501,"<="&$A3,'Daily Sale entry '!$Z$2:$Z$1501,"Cheque deposit 支票存入")-COUNTIFS('Daily Sale entry '!$Q$2:$Q$1501,"Collection 收款",'Daily Sale entry '!$R$2:$R$1501,"Cheque 支票",'Daily Sale entry '!$V$2:$V$1501,"<="&$A3)) | D3: =IF($A3="","",ROUND('Opening Balance'!$B$6+SUM('Daily Sale entry '!$J$2:J3)-SUMIFS('Daily Sale entry '!$AC$2:$AC$1501,'Daily Sale entry '!$X$2:$X$1501,"<="&$A3,'Daily Sale entry '!$Z$2:$Z$1501,"Cheque deposit 支票存入")-SUMPRODUCT(('Daily Sale entry '!$Q$2:$Q$1501="Collection 收款")*('Daily Sale entry '!$R$2:$R$1501="Cheque 支票")*('Daily Sale entry '!$V$2:$V$1501<>"")*('Daily Sale entry '!$V$2:$V$1501<=$A3)*('Daily Sale entry '!$S$2:$S$1501-'Opening Balance'!$B$15*('Daily Sale entry '!$R$2:$R$1501="Cheque 支票")*('Daily Sale entry '!$S$2:$S$1501-TRUNC('Daily Sale entry '!$S$2:$S$1501)))),2)) | E3: =IF($A3="","",'Opening Balance'!$B$7) | F3: =IF($A3="","",ROUND(SUMIFS('Daily Sale entry '!$L$2:$L$367,'Daily Sale entry '!$A$2:$A$367,">="&DATE(YEAR($A3),MONTH($A3),1),'Daily Sale entry '!$A$2:$A$367,"<="&$A3)+SUMIFS('Daily Sale entry '!$M$2:$M$367,'Daily Sale entry '!$A$2:$A$367,">="&DATE(YEAR($A3),MONTH($A3),1),'Daily Sale entry '!$A$2:$A$367,"<="&$A3)+IF(AND(YEAR($A3)=YEAR('Daily Sale entry '!$A$2),MONTH($A3)=MONTH('Daily Sale entry '!$A$2)),'Opening Balance'!$B$8,0),2)) | G3: =IF($A3="","",MOD(ROUND('Opening Balance'!$B$9+SUMIFS('Sales & Collection'!$L$1:$L$17,'Sales & Collection'!$K$1:$K$17,"cash collection*"),2),'Opening Balance'!$B$11)) | H3: =IF($A3="","",ROUND('Opening Balance'!$B$10+'Opening Balance'!$B$9+SUMIFS('Sales & Collection'!$L$1:$L$17,'Sales & Collection'!$K$1:$K$17,"cash collection*")-G3-SUMIFS('Daily Sale entry '!$AC$2:$AC$1501,'Daily Sale entry '!$X$2:$X$1501,"<="&$A3,'Daily Sale entry '!$Z$2:$Z$1501,"Cash deposit 现金存入"),2)) | I3: =IF($A3="","",ROUND(B3+D3+E3+F3+G3+H3,2)) | J3: =IF($A3="","",'AR & AP'!K4) | K3: =IF($A3="","",ROUND(I3-J3-SUMIFS('Daily Sale entry '!$AC$2:$AC$1501,'Daily Sale entry '!$X$2:$X$1501,"<="&$A3,'Daily Sale entry '!$Z$2:$Z$1501,"Other deposit 其他存入")+SUMIFS('Daily Sale entry '!$AD$2:$AD$1501,'Daily Sale entry '!$X$2:$X$1501,"<="&$A3)+('Opening Balance'!$B$8+SUM('Daily Sale entry '!$L$2:M3)-F3),2)) | L3: =IF($A3="","",IF(ABS('Sales & Collection'!$B$26)>'Opening Balance'!$B$16,"ALERT 警报: Different "&TEXT('Sales & Collection'!$B$26,"#,##0.00")&" 差额过大",""))
A4: =IF('Daily Sale entry '!A4="","",'Daily Sale entry '!A4) | B4: =IF($A4="","",ROUND('Opening Balance'!$B$4+SUM('Daily Sale entry '!$K$2:K4)+SUMIFS('Daily Sale entry '!$AC$2:$AC$1501,'Daily Sale entry '!$X$2:$X$1501,"<="&$A4)-SUMIFS('Daily Sale entry '!$AD$2:$AD$1501,'Daily Sale entry '!$X$2:$X$1501,"<="&$A4)+SUMPRODUCT(('Daily Sale entry '!$Q$2:$Q$1501="Collection 收款")*('Daily Sale entry '!$R$2:$R$1501="Cheque 支票")*('Daily Sale entry '!$V$2:$V$1501<>"")*('Daily Sale entry '!$V$2:$V$1501<=$A4)*('Daily Sale entry '!$S$2:$S$1501-'Opening Balance'!$B$15*('Daily Sale entry '!$R$2:$R$1501="Cheque 支票")*('Daily Sale entry '!$S$2:$S$1501-TRUNC('Daily Sale entry '!$S$2:$S$1501))))-'Opening Balance'!$B$15*SUMPRODUCT(('Daily Sale entry '!$X$2:$X$1501<=$A4)*('Daily Sale entry '!$Z$2:$Z$1501="Online collection 网上收款")*('Daily Sale entry '!$AA$2:$AA$1501<>"")*('Daily Sale entry '!$AC$2:$AC$1501-TRUNC('Daily Sale entry '!$AC$2:$AC$1501))),2)) | C4: =IF($A4="","",'Opening Balance'!$B$5+SUM('Daily Sale entry '!$I$2:I4)-SUMIFS('Daily Sale entry '!$AB$2:$AB$1501,'Daily Sale entry '!$X$2:$X$1501,"<="&$A4,'Daily Sale entry '!$Z$2:$Z$1501,"Cheque deposit 支票存入")-COUNTIFS('Daily Sale entry '!$Q$2:$Q$1501,"Collection 收款",'Daily Sale entry '!$R$2:$R$1501,"Cheque 支票",'Daily Sale entry '!$V$2:$V$1501,"<="&$A4)) | D4: =IF($A4="","",ROUND('Opening Balance'!$B$6+SUM('Daily Sale entry '!$J$2:J4)-SUMIFS('Daily Sale entry '!$AC$2:$AC$1501,'Daily Sale entry '!$X$2:$X$1501,"<="&$A4,'Daily Sale entry '!$Z$2:$Z$1501,"Cheque deposit 支票存入")-SUMPRODUCT(('Daily Sale entry '!$Q$2:$Q$1501="Collection 收款")*('Daily Sale entry '!$R$2:$R$1501="Cheque 支票")*('Daily Sale entry '!$V$2:$V$1501<>"")*('Daily Sale entry '!$V$2:$V$1501<=$A4)*('Daily Sale entry '!$S$2:$S$1501-'Opening Balance'!$B$15*('Daily Sale entry '!$R$2:$R$1501="Cheque 支票")*('Daily Sale entry '!$S$2:$S$1501-TRUNC('Daily Sale entry '!$S$2:$S$1501)))),2)) | E4: =IF($A4="","",'Opening Balance'!$B$7) | F4: =IF($A4="","",ROUND(SUMIFS('Daily Sale entry '!$L$2:$L$367,'Daily Sale entry '!$A$2:$A$367,">="&DATE(YEAR($A4),MONTH($A4),1),'Daily Sale entry '!$A$2:$A$367,"<="&$A4)+SUMIFS('Daily Sale entry '!$M$2:$M$367,'Daily Sale entry '!$A$2:$A$367,">="&DATE(YEAR($A4),MONTH($A4),1),'Daily Sale entry '!$A$2:$A$367,"<="&$A4)+IF(AND(YEAR($A4)=YEAR('Daily Sale entry '!$A$2),MONTH($A4)=MONTH('Daily Sale entry '!$A$2)),'Opening Balance'!$B$8,0),2)) | G4: =IF($A4="","",MOD(ROUND('Opening Balance'!$B$9+SUMIFS('Sales & Collection'!$L$1:$L$31,'Sales & Collection'!$K$1:$K$31,"cash collection*"),2),'Opening Balance'!$B$11)) | H4: =IF($A4="","",ROUND('Opening Balance'!$B$10+'Opening Balance'!$B$9+SUMIFS('Sales & Collection'!$L$1:$L$31,'Sales & Collection'!$K$1:$K$31,"cash collection*")-G4-SUMIFS('Daily Sale entry '!$AC$2:$AC$1501,'Daily Sale entry '!$X$2:$X$1501,"<="&$A4,'Daily Sale entry '!$Z$2:$Z$1501,"Cash deposit 现金存入"),2)) | I4: =IF($A4="","",ROUND(B4+D4+E4+F4+G4+H4,2)) | J4: =IF($A4="","",'AR & AP'!K5) | K4: =IF($A4="","",ROUND(I4-J4-SUMIFS('Daily Sale entry '!$AC$2:$AC$1501,'Daily Sale entry '!$X$2:$X$1501,"<="&$A4,'Daily Sale entry '!$Z$2:$Z$1501,"Other deposit 其他存入")+SUMIFS('Daily Sale entry '!$AD$2:$AD$1501,'Daily Sale entry '!$X$2:$X$1501,"<="&$A4)+('Opening Balance'!$B$8+SUM('Daily Sale entry '!$L$2:M4)-F4),2)) | L4: =IF($A4="","",IF(ABS('Sales & Collection'!$B$40)>'Opening Balance'!$B$16,"ALERT 警报: Different "&TEXT('Sales & Collection'!$B$40,"#,##0.00")&" 差额过大",""))
A5: =IF('Daily Sale entry '!A5="","",'Daily Sale entry '!A5) | B5: =IF($A5="","",ROUND('Opening Balance'!$B$4+SUM('Daily Sale entry '!$K$2:K5)+SUMIFS('Daily Sale entry '!$AC$2:$AC$1501,'Daily Sale entry '!$X$2:$X$1501,"<="&$A5)-SUMIFS('Daily Sale entry '!$AD$2:$AD$1501,'Daily Sale entry '!$X$2:$X$1501,"<="&$A5)+SUMPRODUCT(('Daily Sale entry '!$Q$2:$Q$1501="Collection 收款")*('Daily Sale entry '!$R$2:$R$1501="Cheque 支票")*('Daily Sale entry '!$V$2:$V$1501<>"")*('Daily Sale entry '!$V$2:$V$1501<=$A5)*('Daily Sale entry '!$S$2:$S$1501-'Opening Balance'!$B$15*('Daily Sale entry '!$R$2:$R$1501="Cheque 支票")*('Daily Sale entry '!$S$2:$S$1501-TRUNC('Daily Sale entry '!$S$2:$S$1501))))-'Opening Balance'!$B$15*SUMPRODUCT(('Daily Sale entry '!$X$2:$X$1501<=$A5)*('Daily Sale entry '!$Z$2:$Z$1501="Online collection 网上收款")*('Daily Sale entry '!$AA$2:$AA$1501<>"")*('Daily Sale entry '!$AC$2:$AC$1501-TRUNC('Daily Sale entry '!$AC$2:$AC$1501))),2)) | C5: =IF($A5="","",'Opening Balance'!$B$5+SUM('Daily Sale entry '!$I$2:I5)-SUMIFS('Daily Sale entry '!$AB$2:$AB$1501,'Daily Sale entry '!$X$2:$X$1501,"<="&$A5,'Daily Sale entry '!$Z$2:$Z$1501,"Cheque deposit 支票存入")-COUNTIFS('Daily Sale entry '!$Q$2:$Q$1501,"Collection 收款",'Daily Sale entry '!$R$2:$R$1501,"Cheque 支票",'Daily Sale entry '!$V$2:$V$1501,"<="&$A5)) | D5: =IF($A5="","",ROUND('Opening Balance'!$B$6+SUM('Daily Sale entry '!$J$2:J5)-SUMIFS('Daily Sale entry '!$AC$2:$AC$1501,'Daily Sale entry '!$X$2:$X$1501,"<="&$A5,'Daily Sale entry '!$Z$2:$Z$1501,"Cheque deposit 支票存入")-SUMPRODUCT(('Daily Sale entry '!$Q$2:$Q$1501="Collection 收款")*('Daily Sale entry '!$R$2:$R$1501="Cheque 支票")*('Daily Sale entry '!$V$2:$V$1501<>"")*('Daily Sale entry '!$V$2:$V$1501<=$A5)*('Daily Sale entry '!$S$2:$S$1501-'Opening Balance'!$B$15*('Daily Sale entry '!$R$2:$R$1501="Cheque 支票")*('Daily Sale entry '!$S$2:$S$1501-TRUNC('Daily Sale entry '!$S$2:$S$1501)))),2)) | E5: =IF($A5="","",'Opening Balance'!$B$7) | F5: =IF($A5="","",ROUND(SUMIFS('Daily Sale entry '!$L$2:$L$367,'Daily Sale entry '!$A$2:$A$367,">="&DATE(YEAR($A5),MONTH($A5),1),'Daily Sale entry '!$A$2:$A$367,"<="&$A5)+SUMIFS('Daily Sale entry '!$M$2:$M$367,'Daily Sale entry '!$A$2:$A$367,">="&DATE(YEAR($A5),MONTH($A5),1),'Daily Sale entry '!$A$2:$A$367,"<="&$A5)+IF(AND(YEAR($A5)=YEAR('Daily Sale entry '!$A$2),MONTH($A5)=MONTH('Daily Sale entry '!$A$2)),'Opening Balance'!$B$8,0),2)) | G5: =IF($A5="","",MOD(ROUND('Opening Balance'!$B$9+SUMIFS('Sales & Collection'!$L$1:$L$45,'Sales & Collection'!$K$1:$K$45,"cash collection*"),2),'Opening Balance'!$B$11)) | H5: =IF($A5="","",ROUND('Opening Balance'!$B$10+'Opening Balance'!$B$9+SUMIFS('Sales & Collection'!$L$1:$L$45,'Sales & Collection'!$K$1:$K$45,"cash collection*")-G5-SUMIFS('Daily Sale entry '!$AC$2:$AC$1501,'Daily Sale entry '!$X$2:$X$1501,"<="&$A5,'Daily Sale entry '!$Z$2:$Z$1501,"Cash deposit 现金存入"),2)) | I5: =IF($A5="","",ROUND(B5+D5+E5+F5+G5+H5,2)) | J5: =IF($A5="","",'AR & AP'!K6) | K5: =IF($A5="","",ROUND(I5-J5-SUMIFS('Daily Sale entry '!$AC$2:$AC$1501,'Daily Sale entry '!$X$2:$X$1501,"<="&$A5,'Daily Sale entry '!$Z$2:$Z$1501,"Other deposit 其他存入")+SUMIFS('Daily Sale entry '!$AD$2:$AD$1501,'Daily Sale entry '!$X$2:$X$1501,"<="&$A5)+('Opening Balance'!$B$8+SUM('Daily Sale entry '!$L$2:M5)-F5),2)) | L5: =IF($A5="","",IF(ABS('Sales & Collection'!$B$54)>'Opening Balance'!$B$16,"ALERT 警报: Different "&TEXT('Sales & Collection'!$B$54,"#,##0.00")&" 差额过大",""))
A6: =IF('Daily Sale entry '!A6="","",'Daily Sale entry '!A6) | B6: =IF($A6="","",ROUND('Opening Balance'!$B$4+SUM('Daily Sale entry '!$K$2:K6)+SUMIFS('Daily Sale entry '!$AC$2:$AC$1501,'Daily Sale entry '!$X$2:$X$1501,"<="&$A6)-SUMIFS('Daily Sale entry '!$AD$2:$AD$1501,'Daily Sale entry '!$X$2:$X$1501,"<="&$A6)+SUMPRODUCT(('Daily Sale entry '!$Q$2:$Q$1501="Collection 收款")*('Daily Sale entry '!$R$2:$R$1501="Cheque 支票")*('Daily Sale entry '!$V$2:$V$1501<>"")*('Daily Sale entry '!$V$2:$V$1501<=$A6)*('Daily Sale entry '!$S$2:$S$1501-'Opening Balance'!$B$15*('Daily Sale entry '!$R$2:$R$1501="Cheque 支票")*('Daily Sale entry '!$S$2:$S$1501-TRUNC('Daily Sale entry '!$S$2:$S$1501))))-'Opening Balance'!$B$15*SUMPRODUCT(('Daily Sale entry '!$X$2:$X$1501<=$A6)*('Daily Sale entry '!$Z$2:$Z$1501="Online collection 网上收款")*('Daily Sale entry '!$AA$2:$AA$1501<>"")*('Daily Sale entry '!$AC$2:$AC$1501-TRUNC('Daily Sale entry '!$AC$2:$AC$1501))),2)) | C6: =IF($A6="","",'Opening Balance'!$B$5+SUM('Daily Sale entry '!$I$2:I6)-SUMIFS('Daily Sale entry '!$AB$2:$AB$1501,'Daily Sale entry '!$X$2:$X$1501,"<="&$A6,'Daily Sale entry '!$Z$2:$Z$1501,"Cheque deposit 支票存入")-COUNTIFS('Daily Sale entry '!$Q$2:$Q$1501,"Collection 收款",'Daily Sale entry '!$R$2:$R$1501,"Cheque 支票",'Daily Sale entry '!$V$2:$V$1501,"<="&$A6)) | D6: =IF($A6="","",ROUND('Opening Balance'!$B$6+SUM('Daily Sale entry '!$J$2:J6)-SUMIFS('Daily Sale entry '!$AC$2:$AC$1501,'Daily Sale entry '!$X$2:$X$1501,"<="&$A6,'Daily Sale entry '!$Z$2:$Z$1501,"Cheque deposit 支票存入")-SUMPRODUCT(('Daily Sale entry '!$Q$2:$Q$1501="Collection 收款")*('Daily Sale entry '!$R$2:$R$1501="Cheque 支票")*('Daily Sale entry '!$V$2:$V$1501<>"")*('Daily Sale entry '!$V$2:$V$1501<=$A6)*('Daily Sale entry '!$S$2:$S$1501-'Opening Balance'!$B$15*('Daily Sale entry '!$R$2:$R$1501="Cheque 支票")*('Daily Sale entry '!$S$2:$S$1501-TRUNC('Daily Sale entry '!$S$2:$S$1501)))),2)) | E6: =IF($A6="","",'Opening Balance'!$B$7) | F6: =IF($A6="","",ROUND(SUMIFS('Daily Sale entry '!$L$2:$L$367,'Daily Sale entry '!$A$2:$A$367,">="&DATE(YEAR($A6),MONTH($A6),1),'Daily Sale entry '!$A$2:$A$367,"<="&$A6)+SUMIFS('Daily Sale entry '!$M$2:$M$367,'Daily Sale entry '!$A$2:$A$367,">="&DATE(YEAR($A6),MONTH($A6),1),'Daily Sale entry '!$A$2:$A$367,"<="&$A6)+IF(AND(YEAR($A6)=YEAR('Daily Sale entry '!$A$2),MONTH($A6)=MONTH('Daily Sale entry '!$A$2)),'Opening Balance'!$B$8,0),2)) | G6: =IF($A6="","",MOD(ROUND('Opening Balance'!$B$9+SUMIFS('Sales & Collection'!$L$1:$L$59,'Sales & Collection'!$K$1:$K$59,"cash collection*"),2),'Opening Balance'!$B$11)) | H6: =IF($A6="","",ROUND('Opening Balance'!$B$10+'Opening Balance'!$B$9+SUMIFS('Sales & Collection'!$L$1:$L$59,'Sales & Collection'!$K$1:$K$59,"cash collection*")-G6-SUMIFS('Daily Sale entry '!$AC$2:$AC$1501,'Daily Sale entry '!$X$2:$X$1501,"<="&$A6,'Daily Sale entry '!$Z$2:$Z$1501,"Cash deposit 现金存入"),2)) | I6: =IF($A6="","",ROUND(B6+D6+E6+F6+G6+H6,2)) | J6: =IF($A6="","",'AR & AP'!K7) | K6: =IF($A6="","",ROUND(I6-J6-SUMIFS('Daily Sale entry '!$AC$2:$AC$1501,'Daily Sale entry '!$X$2:$X$1501,"<="&$A6,'Daily Sale entry '!$Z$2:$Z$1501,"Other deposit 其他存入")+SUMIFS('Daily Sale entry '!$AD$2:$AD$1501,'Daily Sale entry '!$X$2:$X$1501,"<="&$A6)+('Opening Balance'!$B$8+SUM('Daily Sale entry '!$L$2:M6)-F6),2)) | L6: =IF($A6="","",IF(ABS('Sales & Collection'!$B$68)>'Opening Balance'!$B$16,"ALERT 警报: Different "&TEXT('Sales & Collection'!$B$68,"#,##0.00")&" 差额过大",""))
A7: =IF('Daily Sale entry '!A7="","",'Daily Sale entry '!A7) | B7: =IF($A7="","",ROUND('Opening Balance'!$B$4+SUM('Daily Sale entry '!$K$2:K7)+SUMIFS('Daily Sale entry '!$AC$2:$AC$1501,'Daily Sale entry '!$X$2:$X$1501,"<="&$A7)-SUMIFS('Daily Sale entry '!$AD$2:$AD$1501,'Daily Sale entry '!$X$2:$X$1501,"<="&$A7)+SUMPRODUCT(('Daily Sale entry '!$Q$2:$Q$1501="Collection 收款")*('Daily Sale entry '!$R$2:$R$1501="Cheque 支票")*('Daily Sale entry '!$V$2:$V$1501<>"")*('Daily Sale entry '!$V$2:$V$1501<=$A7)*('Daily Sale entry '!$S$2:$S$1501-'Opening Balance'!$B$15*('Daily Sale entry '!$R$2:$R$1501="Cheque 支票")*('Daily Sale entry '!$S$2:$S$1501-TRUNC('Daily Sale entry '!$S$2:$S$1501))))-'Opening Balance'!$B$15*SUMPRODUCT(('Daily Sale entry '!$X$2:$X$1501<=$A7)*('Daily Sale entry '!$Z$2:$Z$1501="Online collection 网上收款")*('Daily Sale entry '!$AA$2:$AA$1501<>"")*('Daily Sale entry '!$AC$2:$AC$1501-TRUNC('Daily Sale entry '!$AC$2:$AC$1501))),2)) | C7: =IF($A7="","",'Opening Balance'!$B$5+SUM('Daily Sale entry '!$I$2:I7)-SUMIFS('Daily Sale entry '!$AB$2:$AB$1501,'Daily Sale entry '!$X$2:$X$1501,"<="&$A7,'Daily Sale entry '!$Z$2:$Z$1501,"Cheque deposit 支票存入")-COUNTIFS('Daily Sale entry '!$Q$2:$Q$1501,"Collection 收款",'Daily Sale entry '!$R$2:$R$1501,"Cheque 支票",'Daily Sale entry '!$V$2:$V$1501,"<="&$A7)) | D7: =IF($A7="","",ROUND('Opening Balance'!$B$6+SUM('Daily Sale entry '!$J$2:J7)-SUMIFS('Daily Sale entry '!$AC$2:$AC$1501,'Daily Sale entry '!$X$2:$X$1501,"<="&$A7,'Daily Sale entry '!$Z$2:$Z$1501,"Cheque deposit 支票存入")-SUMPRODUCT(('Daily Sale entry '!$Q$2:$Q$1501="Collection 收款")*('Daily Sale entry '!$R$2:$R$1501="Cheque 支票")*('Daily Sale entry '!$V$2:$V$1501<>"")*('Daily Sale entry '!$V$2:$V$1501<=$A7)*('Daily Sale entry '!$S$2:$S$1501-'Opening Balance'!$B$15*('Daily Sale entry '!$R$2:$R$1501="Cheque 支票")*('Daily Sale entry '!$S$2:$S$1501-TRUNC('Daily Sale entry '!$S$2:$S$1501)))),2)) | E7: =IF($A7="","",'Opening Balance'!$B$7) | F7: =IF($A7="","",ROUND(SUMIFS('Daily Sale entry '!$L$2:$L$367,'Daily Sale entry '!$A$2:$A$367,">="&DATE(YEAR($A7),MONTH($A7),1),'Daily Sale entry '!$A$2:$A$367,"<="&$A7)+SUMIFS('Daily Sale entry '!$M$2:$M$367,'Daily Sale entry '!$A$2:$A$367,">="&DATE(YEAR($A7),MONTH($A7),1),'Daily Sale entry '!$A$2:$A$367,"<="&$A7)+IF(AND(YEAR($A7)=YEAR('Daily Sale entry '!$A$2),MONTH($A7)=MONTH('Daily Sale entry '!$A$2)),'Opening Balance'!$B$8,0),2)) | G7: =IF($A7="","",MOD(ROUND('Opening Balance'!$B$9+SUMIFS('Sales & Collection'!$L$1:$L$73,'Sales & Collection'!$K$1:$K$73,"cash collection*"),2),'Opening Balance'!$B$11)) | H7: =IF($A7="","",ROUND('Opening Balance'!$B$10+'Opening Balance'!$B$9+SUMIFS('Sales & Collection'!$L$1:$L$73,'Sales & Collection'!$K$1:$K$73,"cash collection*")-G7-SUMIFS('Daily Sale entry '!$AC$2:$AC$1501,'Daily Sale entry '!$X$2:$X$1501,"<="&$A7,'Daily Sale entry '!$Z$2:$Z$1501,"Cash deposit 现金存入"),2)) | I7: =IF($A7="","",ROUND(B7+D7+E7+F7+G7+H7,2)) | J7: =IF($A7="","",'AR & AP'!K8) | K7: =IF($A7="","",ROUND(I7-J7-SUMIFS('Daily Sale entry '!$AC$2:$AC$1501,'Daily Sale entry '!$X$2:$X$1501,"<="&$A7,'Daily Sale entry '!$Z$2:$Z$1501,"Other deposit 其他存入")+SUMIFS('Daily Sale entry '!$AD$2:$AD$1501,'Daily Sale entry '!$X$2:$X$1501,"<="&$A7)+('Opening Balance'!$B$8+SUM('Daily Sale entry '!$L$2:M7)-F7),2)) | L7: =IF($A7="","",IF(ABS('Sales & Collection'!$B$82)>'Opening Balance'!$B$16,"ALERT 警报: Different "&TEXT('Sales & Collection'!$B$82,"#,##0.00")&" 差额过大",""))
A8: =IF('Daily Sale entry '!A8="","",'Daily Sale entry '!A8) | B8: =IF($A8="","",ROUND('Opening Balance'!$B$4+SUM('Daily Sale entry '!$K$2:K8)+SUMIFS('Daily Sale entry '!$AC$2:$AC$1501,'Daily Sale entry '!$X$2:$X$1501,"<="&$A8)-SUMIFS('Daily Sale entry '!$AD$2:$AD$1501,'Daily Sale entry '!$X$2:$X$1501,"<="&$A8)+SUMPRODUCT(('Daily Sale entry '!$Q$2:$Q$1501="Collection 收款")*('Daily Sale entry '!$R$2:$R$1501="Cheque 支票")*('Daily Sale entry '!$V$2:$V$1501<>"")*('Daily Sale entry '!$V$2:$V$1501<=$A8)*('Daily Sale entry '!$S$2:$S$1501-'Opening Balance'!$B$15*('Daily Sale entry '!$R$2:$R$1501="Cheque 支票")*('Daily Sale entry '!$S$2:$S$1501-TRUNC('Daily Sale entry '!$S$2:$S$1501))))-'Opening Balance'!$B$15*SUMPRODUCT(('Daily Sale entry '!$X$2:$X$1501<=$A8)*('Daily Sale entry '!$Z$2:$Z$1501="Online collection 网上收款")*('Daily Sale entry '!$AA$2:$AA$1501<>"")*('Daily Sale entry '!$AC$2:$AC$1501-TRUNC('Daily Sale entry '!$AC$2:$AC$1501))),2)) | C8: =IF($A8="","",'Opening Balance'!$B$5+SUM('Daily Sale entry '!$I$2:I8)-SUMIFS('Daily Sale entry '!$AB$2:$AB$1501,'Daily Sale entry '!$X$2:$X$1501,"<="&$A8,'Daily Sale entry '!$Z$2:$Z$1501,"Cheque deposit 支票存入")-COUNTIFS('Daily Sale entry '!$Q$2:$Q$1501,"Collection 收款",'Daily Sale entry '!$R$2:$R$1501,"Cheque 支票",'Daily Sale entry '!$V$2:$V$1501,"<="&$A8)) | D8: =IF($A8="","",ROUND('Opening Balance'!$B$6+SUM('Daily Sale entry '!$J$2:J8)-SUMIFS('Daily Sale entry '!$AC$2:$AC$1501,'Daily Sale entry '!$X$2:$X$1501,"<="&$A8,'Daily Sale entry '!$Z$2:$Z$1501,"Cheque deposit 支票存入")-SUMPRODUCT(('Daily Sale entry '!$Q$2:$Q$1501="Collection 收款")*('Daily Sale entry '!$R$2:$R$1501="Cheque 支票")*('Daily Sale entry '!$V$2:$V$1501<>"")*('Daily Sale entry '!$V$2:$V$1501<=$A8)*('Daily Sale entry '!$S$2:$S$1501-'Opening Balance'!$B$15*('Daily Sale entry '!$R$2:$R$1501="Cheque 支票")*('Daily Sale entry '!$S$2:$S$1501-TRUNC('Daily Sale entry '!$S$2:$S$1501)))),2)) | E8: =IF($A8="","",'Opening Balance'!$B$7) | F8: =IF($A8="","",ROUND(SUMIFS('Daily Sale entry '!$L$2:$L$367,'Daily Sale entry '!$A$2:$A$367,">="&DATE(YEAR($A8),MONTH($A8),1),'Daily Sale entry '!$A$2:$A$367,"<="&$A8)+SUMIFS('Daily Sale entry '!$M$2:$M$367,'Daily Sale entry '!$A$2:$A$367,">="&DATE(YEAR($A8),MONTH($A8),1),'Daily Sale entry '!$A$2:$A$367,"<="&$A8)+IF(AND(YEAR($A8)=YEAR('Daily Sale entry '!$A$2),MONTH($A8)=MONTH('Daily Sale entry '!$A$2)),'Opening Balance'!$B$8,0),2)) | G8: =IF($A8="","",MOD(ROUND('Opening Balance'!$B$9+SUMIFS('Sales & Collection'!$L$1:$L$87,'Sales & Collection'!$K$1:$K$87,"cash collection*"),2),'Opening Balance'!$B$11)) | H8: =IF($A8="","",ROUND('Opening Balance'!$B$10+'Opening Balance'!$B$9+SUMIFS('Sales & Collection'!$L$1:$L$87,'Sales & Collection'!$K$1:$K$87,"cash collection*")-G8-SUMIFS('Daily Sale entry '!$AC$2:$AC$1501,'Daily Sale entry '!$X$2:$X$1501,"<="&$A8,'Daily Sale entry '!$Z$2:$Z$1501,"Cash deposit 现金存入"),2)) | I8: =IF($A8="","",ROUND(B8+D8+E8+F8+G8+H8,2)) | J8: =IF($A8="","",'AR & AP'!K9) | K8: =IF($A8="","",ROUND(I8-J8-SUMIFS('Daily Sale entry '!$AC$2:$AC$1501,'Daily Sale entry '!$X$2:$X$1501,"<="&$A8,'Daily Sale entry '!$Z$2:$Z$1501,"Other deposit 其他存入")+SUMIFS('Daily Sale entry '!$AD$2:$AD$1501,'Daily Sale entry '!$X$2:$X$1501,"<="&$A8)+('Opening Balance'!$B$8+SUM('Daily Sale entry '!$L$2:M8)-F8),2)) | L8: =IF($A8="","",IF(ABS('Sales & Collection'!$B$96)>'Opening Balance'!$B$16,"ALERT 警报: Different "&TEXT('Sales & Collection'!$B$96,"#,##0.00")&" 差额过大",""))
A9: =IF('Daily Sale entry '!A9="","",'Daily Sale entry '!A9) | B9: =IF($A9="","",ROUND('Opening Balance'!$B$4+SUM('Daily Sale entry '!$K$2:K9)+SUMIFS('Daily Sale entry '!$AC$2:$AC$1501,'Daily Sale entry '!$X$2:$X$1501,"<="&$A9)-SUMIFS('Daily Sale entry '!$AD$2:$AD$1501,'Daily Sale entry '!$X$2:$X$1501,"<="&$A9)+SUMPRODUCT(('Daily Sale entry '!$Q$2:$Q$1501="Collection 收款")*('Daily Sale entry '!$R$2:$R$1501="Cheque 支票")*('Daily Sale entry '!$V$2:$V$1501<>"")*('Daily Sale entry '!$V$2:$V$1501<=$A9)*('Daily Sale entry '!$S$2:$S$1501-'Opening Balance'!$B$15*('Daily Sale entry '!$R$2:$R$1501="Cheque 支票")*('Daily Sale entry '!$S$2:$S$1501-TRUNC('Daily Sale entry '!$S$2:$S$1501))))-'Opening Balance'!$B$15*SUMPRODUCT(('Daily Sale entry '!$X$2:$X$1501<=$A9)*('Daily Sale entry '!$Z$2:$Z$1501="Online collection 网上收款")*('Daily Sale entry '!$AA$2:$AA$1501<>"")*('Daily Sale entry '!$AC$2:$AC$1501-TRUNC('Daily Sale entry '!$AC$2:$AC$1501))),2)) | C9: =IF($A9="","",'Opening Balance'!$B$5+SUM('Daily Sale entry '!$I$2:I9)-SUMIFS('Daily Sale entry '!$AB$2:$AB$1501,'Daily Sale entry '!$X$2:$X$1501,"<="&$A9,'Daily Sale entry '!$Z$2:$Z$1501,"Cheque deposit 支票存入")-COUNTIFS('Daily Sale entry '!$Q$2:$Q$1501,"Collection 收款",'Daily Sale entry '!$R$2:$R$1501,"Cheque 支票",'Daily Sale entry '!$V$2:$V$1501,"<="&$A9)) | D9: =IF($A9="","",ROUND('Opening Balance'!$B$6+SUM('Daily Sale entry '!$J$2:J9)-SUMIFS('Daily Sale entry '!$AC$2:$AC$1501,'Daily Sale entry '!$X$2:$X$1501,"<="&$A9,'Daily Sale entry '!$Z$2:$Z$1501,"Cheque deposit 支票存入")-SUMPRODUCT(('Daily Sale entry '!$Q$2:$Q$1501="Collection 收款")*('Daily Sale entry '!$R$2:$R$1501="Cheque 支票")*('Daily Sale entry '!$V$2:$V$1501<>"")*('Daily Sale entry '!$V$2:$V$1501<=$A9)*('Daily Sale entry '!$S$2:$S$1501-'Opening Balance'!$B$15*('Daily Sale entry '!$R$2:$R$1501="Cheque 支票")*('Daily Sale entry '!$S$2:$S$1501-TRUNC('Daily Sale entry '!$S$2:$S$1501)))),2)) | E9: =IF($A9="","",'Opening Balance'!$B$7) | F9: =IF($A9="","",ROUND(SUMIFS('Daily Sale entry '!$L$2:$L$367,'Daily Sale entry '!$A$2:$A$367,">="&DATE(YEAR($A9),MONTH($A9),1),'Daily Sale entry '!$A$2:$A$367,"<="&$A9)+SUMIFS('Daily Sale entry '!$M$2:$M$367,'Daily Sale entry '!$A$2:$A$367,">="&DATE(YEAR($A9),MONTH($A9),1),'Daily Sale entry '!$A$2:$A$367,"<="&$A9)+IF(AND(YEAR($A9)=YEAR('Daily Sale entry '!$A$2),MONTH($A9)=MONTH('Daily Sale entry '!$A$2)),'Opening Balance'!$B$8,0),2)) | G9: =IF($A9="","",MOD(ROUND('Opening Balance'!$B$9+SUMIFS('Sales & Collection'!$L$1:$L$101,'Sales & Collection'!$K$1:$K$101,"cash collection*"),2),'Opening Balance'!$B$11)) | H9: =IF($A9="","",ROUND('Opening Balance'!$B$10+'Opening Balance'!$B$9+SUMIFS('Sales & Collection'!$L$1:$L$101,'Sales & Collection'!$K$1:$K$101,"cash collection*")-G9-SUMIFS('Daily Sale entry '!$AC$2:$AC$1501,'Daily Sale entry '!$X$2:$X$1501,"<="&$A9,'Daily Sale entry '!$Z$2:$Z$1501,"Cash deposit 现金存入"),2)) | I9: =IF($A9="","",ROUND(B9+D9+E9+F9+G9+H9,2)) | J9: =IF($A9="","",'AR & AP'!K10) | K9: =IF($A9="","",ROUND(I9-J9-SUMIFS('Daily Sale entry '!$AC$2:$AC$1501,'Daily Sale entry '!$X$2:$X$1501,"<="&$A9,'Daily Sale entry '!$Z$2:$Z$1501,"Other deposit 其他存入")+SUMIFS('Daily Sale entry '!$AD$2:$AD$1501,'Daily Sale entry '!$X$2:$X$1501,"<="&$A9)+('Opening Balance'!$B$8+SUM('Daily Sale entry '!$L$2:M9)-F9),2)) | L9: =IF($A9="","",IF(ABS('Sales & Collection'!$B$110)>'Opening Balance'!$B$16,"ALERT 警报: Different "&TEXT('Sales & Collection'!$B$110,"#,##0.00")&" 差额过大",""))
A10: =IF('Daily Sale entry '!A10="","",'Daily Sale entry '!A10) | B10: =IF($A10="","",ROUND('Opening Balance'!$B$4+SUM('Daily Sale entry '!$K$2:K10)+SUMIFS('Daily Sale entry '!$AC$2:$AC$1501,'Daily Sale entry '!$X$2:$X$1501,"<="&$A10)-SUMIFS('Daily Sale entry '!$AD$2:$AD$1501,'Daily Sale entry '!$X$2:$X$1501,"<="&$A10)+SUMPRODUCT(('Daily Sale entry '!$Q$2:$Q$1501="Collection 收款")*('Daily Sale entry '!$R$2:$R$1501="Cheque 支票")*('Daily Sale entry '!$V$2:$V$1501<>"")*('Daily Sale entry '!$V$2:$V$1501<=$A10)*('Daily Sale entry '!$S$2:$S$1501-'Opening Balance'!$B$15*('Daily Sale entry '!$R$2:$R$1501="Cheque 支票")*('Daily Sale entry '!$S$2:$S$1501-TRUNC('Daily Sale entry '!$S$2:$S$1501))))-'Opening Balance'!$B$15*SUMPRODUCT(('Daily Sale entry '!$X$2:$X$1501<=$A10)*('Daily Sale entry '!$Z$2:$Z$1501="Online collection 网上收款")*('Daily Sale entry '!$AA$2:$AA$1501<>"")*('Daily Sale entry '!$AC$2:$AC$1501-TRUNC('Daily Sale entry '!$AC$2:$AC$1501))),2)) | C10: =IF($A10="","",'Opening Balance'!$B$5+SUM('Daily Sale entry '!$I$2:I10)-SUMIFS('Daily Sale entry '!$AB$2:$AB$1501,'Daily Sale entry '!$X$2:$X$1501,"<="&$A10,'Daily Sale entry '!$Z$2:$Z$1501,"Cheque deposit 支票存入")-COUNTIFS('Daily Sale entry '!$Q$2:$Q$1501,"Collection 收款",'Daily Sale entry '!$R$2:$R$1501,"Cheque 支票",'Daily Sale entry '!$V$2:$V$1501,"<="&$A10)) | D10: =IF($A10="","",ROUND('Opening Balance'!$B$6+SUM('Daily Sale entry '!$J$2:J10)-SUMIFS('Daily Sale entry '!$AC$2:$AC$1501,'Daily Sale entry '!$X$2:$X$1501,"<="&$A10,'Daily Sale entry '!$Z$2:$Z$1501,"Cheque deposit 支票存入")-SUMPRODUCT(('Daily Sale entry '!$Q$2:$Q$1501="Collection 收款")*('Daily Sale entry '!$R$2:$R$1501="Cheque 支票")*('Daily Sale entry '!$V$2:$V$1501<>"")*('Daily Sale entry '!$V$2:$V$1501<=$A10)*('Daily Sale entry '!$S$2:$S$1501-'Opening Balance'!$B$15*('Daily Sale entry '!$R$2:$R$1501="Cheque 支票")*('Daily Sale entry '!$S$2:$S$1501-TRUNC('Daily Sale entry '!$S$2:$S$1501)))),2)) | E10: =IF($A10="","",'Opening Balance'!$B$7) | F10: =IF($A10="","",ROUND(SUMIFS('Daily Sale entry '!$L$2:$L$367,'Daily Sale entry '!$A$2:$A$367,">="&DATE(YEAR($A10),MONTH($A10),1),'Daily Sale entry '!$A$2:$A$367,"<="&$A10)+SUMIFS('Daily Sale entry '!$M$2:$M$367,'Daily Sale entry '!$A$2:$A$367,">="&DATE(YEAR($A10),MONTH($A10),1),'Daily Sale entry '!$A$2:$A$367,"<="&$A10)+IF(AND(YEAR($A10)=YEAR('Daily Sale entry '!$A$2),MONTH($A10)=MONTH('Daily Sale entry '!$A$2)),'Opening Balance'!$B$8,0),2)) | G10: =IF($A10="","",MOD(ROUND('Opening Balance'!$B$9+SUMIFS('Sales & Collection'!$L$1:$L$115,'Sales & Collection'!$K$1:$K$115,"cash collection*"),2),'Opening Balance'!$B$11)) | H10: =IF($A10="","",ROUND('Opening Balance'!$B$10+'Opening Balance'!$B$9+SUMIFS('Sales & Collection'!$L$1:$L$115,'Sales & Collection'!$K$1:$K$115,"cash collection*")-G10-SUMIFS('Daily Sale entry '!$AC$2:$AC$1501,'Daily Sale entry '!$X$2:$X$1501,"<="&$A10,'Daily Sale entry '!$Z$2:$Z$1501,"Cash deposit 现金存入"),2)) | I10: =IF($A10="","",ROUND(B10+D10+E10+F10+G10+H10,2)) | J10: =IF($A10="","",'AR & AP'!K11) | K10: =IF($A10="","",ROUND(I10-J10-SUMIFS('Daily Sale entry '!$AC$2:$AC$1501,'Daily Sale entry '!$X$2:$X$1501,"<="&$A10,'Daily Sale entry '!$Z$2:$Z$1501,"Other deposit 其他存入")+SUMIFS('Daily Sale entry '!$AD$2:$AD$1501,'Daily Sale entry '!$X$2:$X$1501,"<="&$A10)+('Opening Balance'!$B$8+SUM('Daily Sale entry '!$L$2:M10)-F10),2)) | L10: =IF($A10="","",IF(ABS('Sales & Collection'!$B$124)>'Opening Balance'!$B$16,"ALERT 警报: Different "&TEXT('Sales & Collection'!$B$124,"#,##0.00")&" 差额过大",""))
A11: =IF('Daily Sale entry '!A11="","",'Daily Sale entry '!A11) | B11: =IF($A11="","",ROUND('Opening Balance'!$B$4+SUM('Daily Sale entry '!$K$2:K11)+SUMIFS('Daily Sale entry '!$AC$2:$AC$1501,'Daily Sale entry '!$X$2:$X$1501,"<="&$A11)-SUMIFS('Daily Sale entry '!$AD$2:$AD$1501,'Daily Sale entry '!$X$2:$X$1501,"<="&$A11)+SUMPRODUCT(('Daily Sale entry '!$Q$2:$Q$1501="Collection 收款")*('Daily Sale entry '!$R$2:$R$1501="Cheque 支票")*('Daily Sale entry '!$V$2:$V$1501<>"")*('Daily Sale entry '!$V$2:$V$1501<=$A11)*('Daily Sale entry '!$S$2:$S$1501-'Opening Balance'!$B$15*('Daily Sale entry '!$R$2:$R$1501="Cheque 支票")*('Daily Sale entry '!$S$2:$S$1501-TRUNC('Daily Sale entry '!$S$2:$S$1501))))-'Opening Balance'!$B$15*SUMPRODUCT(('Daily Sale entry '!$X$2:$X$1501<=$A11)*('Daily Sale entry '!$Z$2:$Z$1501="Online collection 网上收款")*('Daily Sale entry '!$AA$2:$AA$1501<>"")*('Daily Sale entry '!$AC$2:$AC$1501-TRUNC('Daily Sale entry '!$AC$2:$AC$1501))),2)) | C11: =IF($A11="","",'Opening Balance'!$B$5+SUM('Daily Sale entry '!$I$2:I11)-SUMIFS('Daily Sale entry '!$AB$2:$AB$1501,'Daily Sale entry '!$X$2:$X$1501,"<="&$A11,'Daily Sale entry '!$Z$2:$Z$1501,"Cheque deposit 支票存入")-COUNTIFS('Daily Sale entry '!$Q$2:$Q$1501,"Collection 收款",'Daily Sale entry '!$R$2:$R$1501,"Cheque 支票",'Daily Sale entry '!$V$2:$V$1501,"<="&$A11)) | D11: =IF($A11="","",ROUND('Opening Balance'!$B$6+SUM('Daily Sale entry '!$J$2:J11)-SUMIFS('Daily Sale entry '!$AC$2:$AC$1501,'Daily Sale entry '!$X$2:$X$1501,"<="&$A11,'Daily Sale entry '!$Z$2:$Z$1501,"Cheque deposit 支票存入")-SUMPRODUCT(('Daily Sale entry '!$Q$2:$Q$1501="Collection 收款")*('Daily Sale entry '!$R$2:$R$1501="Cheque 支票")*('Daily Sale entry '!$V$2:$V$1501<>"")*('Daily Sale entry '!$V$2:$V$1501<=$A11)*('Daily Sale entry '!$S$2:$S$1501-'Opening Balance'!$B$15*('Daily Sale entry '!$R$2:$R$1501="Cheque 支票")*('Daily Sale entry '!$S$2:$S$1501-TRUNC('Daily Sale entry '!$S$2:$S$1501)))),2)) | E11: =IF($A11="","",'Opening Balance'!$B$7) | F11: =IF($A11="","",ROUND(SUMIFS('Daily Sale entry '!$L$2:$L$367,'Daily Sale entry '!$A$2:$A$367,">="&DATE(YEAR($A11),MONTH($A11),1),'Daily Sale entry '!$A$2:$A$367,"<="&$A11)+SUMIFS('Daily Sale entry '!$M$2:$M$367,'Daily Sale entry '!$A$2:$A$367,">="&DATE(YEAR($A11),MONTH($A11),1),'Daily Sale entry '!$A$2:$A$367,"<="&$A11)+IF(AND(YEAR($A11)=YEAR('Daily Sale entry '!$A$2),MONTH($A11)=MONTH('Daily Sale entry '!$A$2)),'Opening Balance'!$B$8,0),2)) | G11: =IF($A11="","",MOD(ROUND('Opening Balance'!$B$9+SUMIFS('Sales & Collection'!$L$1:$L$129,'Sales & Collection'!$K$1:$K$129,"cash collection*"),2),'Opening Balance'!$B$11)) | H11: =IF($A11="","",ROUND('Opening Balance'!$B$10+'Opening Balance'!$B$9+SUMIFS('Sales & Collection'!$L$1:$L$129,'Sales & Collection'!$K$1:$K$129,"cash collection*")-G11-SUMIFS('Daily Sale entry '!$AC$2:$AC$1501,'Daily Sale entry '!$X$2:$X$1501,"<="&$A11,'Daily Sale entry '!$Z$2:$Z$1501,"Cash deposit 现金存入"),2)) | I11: =IF($A11="","",ROUND(B11+D11+E11+F11+G11+H11,2)) | J11: =IF($A11="","",'AR & AP'!K12) | K11: =IF($A11="","",ROUND(I11-J11-SUMIFS('Daily Sale entry '!$AC$2:$AC$1501,'Daily Sale entry '!$X$2:$X$1501,"<="&$A11,'Daily Sale entry '!$Z$2:$Z$1501,"Other deposit 其他存入")+SUMIFS('Daily Sale entry '!$AD$2:$AD$1501,'Daily Sale entry '!$X$2:$X$1501,"<="&$A11)+('Opening Balance'!$B$8+SUM('Daily Sale entry '!$L$2:M11)-F11),2)) | L11: =IF($A11="","",IF(ABS('Sales & Collection'!$B$138)>'Opening Balance'!$B$16,"ALERT 警报: Different "&TEXT('Sales & Collection'!$B$138,"#,##0.00")&" 差额过大",""))
A12: =IF('Daily Sale entry '!A12="","",'Daily Sale entry '!A12) | B12: =IF($A12="","",ROUND('Opening Balance'!$B$4+SUM('Daily Sale entry '!$K$2:K12)+SUMIFS('Daily Sale entry '!$AC$2:$AC$1501,'Daily Sale entry '!$X$2:$X$1501,"<="&$A12)-SUMIFS('Daily Sale entry '!$AD$2:$AD$1501,'Daily Sale entry '!$X$2:$X$1501,"<="&$A12)+SUMPRODUCT(('Daily Sale entry '!$Q$2:$Q$1501="Collection 收款")*('Daily Sale entry '!$R$2:$R$1501="Cheque 支票")*('Daily Sale entry '!$V$2:$V$1501<>"")*('Daily Sale entry '!$V$2:$V$1501<=$A12)*('Daily Sale entry '!$S$2:$S$1501-'Opening Balance'!$B$15*('Daily Sale entry '!$R$2:$R$1501="Cheque 支票")*('Daily Sale entry '!$S$2:$S$1501-TRUNC('Daily Sale entry '!$S$2:$S$1501))))-'Opening Balance'!$B$15*SUMPRODUCT(('Daily Sale entry '!$X$2:$X$1501<=$A12)*('Daily Sale entry '!$Z$2:$Z$1501="Online collection 网上收款")*('Daily Sale entry '!$AA$2:$AA$1501<>"")*('Daily Sale entry '!$AC$2:$AC$1501-TRUNC('Daily Sale entry '!$AC$2:$AC$1501))),2)) | C12: =IF($A12="","",'Opening Balance'!$B$5+SUM('Daily Sale entry '!$I$2:I12)-SUMIFS('Daily Sale entry '!$AB$2:$AB$1501,'Daily Sale entry '!$X$2:$X$1501,"<="&$A12,'Daily Sale entry '!$Z$2:$Z$1501,"Cheque deposit 支票存入")-COUNTIFS('Daily Sale entry '!$Q$2:$Q$1501,"Collection 收款",'Daily Sale entry '!$R$2:$R$1501,"Cheque 支票",'Daily Sale entry '!$V$2:$V$1501,"<="&$A12)) | D12: =IF($A12="","",ROUND('Opening Balance'!$B$6+SUM('Daily Sale entry '!$J$2:J12)-SUMIFS('Daily Sale entry '!$AC$2:$AC$1501,'Daily Sale entry '!$X$2:$X$1501,"<="&$A12,'Daily Sale entry '!$Z$2:$Z$1501,"Cheque deposit 支票存入")-SUMPRODUCT(('Daily Sale entry '!$Q$2:$Q$1501="Collection 收款")*('Daily Sale entry '!$R$2:$R$1501="Cheque 支票")*('Daily Sale entry '!$V$2:$V$1501<>"")*('Daily Sale entry '!$V$2:$V$1501<=$A12)*('Daily Sale entry '!$S$2:$S$1501-'Opening Balance'!$B$15*('Daily Sale entry '!$R$2:$R$1501="Cheque 支票")*('Daily Sale entry '!$S$2:$S$1501-TRUNC('Daily Sale entry '!$S$2:$S$1501)))),2)) | E12: =IF($A12="","",'Opening Balance'!$B$7) | F12: =IF($A12="","",ROUND(SUMIFS('Daily Sale entry '!$L$2:$L$367,'Daily Sale entry '!$A$2:$A$367,">="&DATE(YEAR($A12),MONTH($A12),1),'Daily Sale entry '!$A$2:$A$367,"<="&$A12)+SUMIFS('Daily Sale entry '!$M$2:$M$367,'Daily Sale entry '!$A$2:$A$367,">="&DATE(YEAR($A12),MONTH($A12),1),'Daily Sale entry '!$A$2:$A$367,"<="&$A12)+IF(AND(YEAR($A12)=YEAR('Daily Sale entry '!$A$2),MONTH($A12)=MONTH('Daily Sale entry '!$A$2)),'Opening Balance'!$B$8,0),2)) | G12: =IF($A12="","",MOD(ROUND('Opening Balance'!$B$9+SUMIFS('Sales & Collection'!$L$1:$L$143,'Sales & Collection'!$K$1:$K$143,"cash collection*"),2),'Opening Balance'!$B$11)) | H12: =IF($A12="","",ROUND('Opening Balance'!$B$10+'Opening Balance'!$B$9+SUMIFS('Sales & Collection'!$L$1:$L$143,'Sales & Collection'!$K$1:$K$143,"cash collection*")-G12-SUMIFS('Daily Sale entry '!$AC$2:$AC$1501,'Daily Sale entry '!$X$2:$X$1501,"<="&$A12,'Daily Sale entry '!$Z$2:$Z$1501,"Cash deposit 现金存入"),2)) | I12: =IF($A12="","",ROUND(B12+D12+E12+F12+G12+H12,2)) | J12: =IF($A12="","",'AR & AP'!K13) | K12: =IF($A12="","",ROUND(I12-J12-SUMIFS('Daily Sale entry '!$AC$2:$AC$1501,'Daily Sale entry '!$X$2:$X$1501,"<="&$A12,'Daily Sale entry '!$Z$2:$Z$1501,"Other deposit 其他存入")+SUMIFS('Daily Sale entry '!$AD$2:$AD$1501,'Daily Sale entry '!$X$2:$X$1501,"<="&$A12)+('Opening Balance'!$B$8+SUM('Daily Sale entry '!$L$2:M12)-F12),2)) | L12: =IF($A12="","",IF(ABS('Sales & Collection'!$B$152)>'Opening Balance'!$B$16,"ALERT 警报: Different "&TEXT('Sales & Collection'!$B$152,"#,##0.00")&" 差额过大",""))
A13: =IF('Daily Sale entry '!A13="","",'Daily Sale entry '!A13) | B13: =IF($A13="","",ROUND('Opening Balance'!$B$4+SUM('Daily Sale entry '!$K$2:K13)+SUMIFS('Daily Sale entry '!$AC$2:$AC$1501,'Daily Sale entry '!$X$2:$X$1501,"<="&$A13)-SUMIFS('Daily Sale entry '!$AD$2:$AD$1501,'Daily Sale entry '!$X$2:$X$1501,"<="&$A13)+SUMPRODUCT(('Daily Sale entry '!$Q$2:$Q$1501="Collection 收款")*('Daily Sale entry '!$R$2:$R$1501="Cheque 支票")*('Daily Sale entry '!$V$2:$V$1501<>"")*('Daily Sale entry '!$V$2:$V$1501<=$A13)*('Daily Sale entry '!$S$2:$S$1501-'Opening Balance'!$B$15*('Daily Sale entry '!$R$2:$R$1501="Cheque 支票")*('Daily Sale entry '!$S$2:$S$1501-TRUNC('Daily Sale entry '!$S$2:$S$1501))))-'Opening Balance'!$B$15*SUMPRODUCT(('Daily Sale entry '!$X$2:$X$1501<=$A13)*('Daily Sale entry '!$Z$2:$Z$1501="Online collection 网上收款")*('Daily Sale entry '!$AA$2:$AA$1501<>"")*('Daily Sale entry '!$AC$2:$AC$1501-TRUNC('Daily Sale entry '!$AC$2:$AC$1501))),2)) | C13: =IF($A13="","",'Opening Balance'!$B$5+SUM('Daily Sale entry '!$I$2:I13)-SUMIFS('Daily Sale entry '!$AB$2:$AB$1501,'Daily Sale entry '!$X$2:$X$1501,"<="&$A13,'Daily Sale entry '!$Z$2:$Z$1501,"Cheque deposit 支票存入")-COUNTIFS('Daily Sale entry '!$Q$2:$Q$1501,"Collection 收款",'Daily Sale entry '!$R$2:$R$1501,"Cheque 支票",'Daily Sale entry '!$V$2:$V$1501,"<="&$A13)) | D13: =IF($A13="","",ROUND('Opening Balance'!$B$6+SUM('Daily Sale entry '!$J$2:J13)-SUMIFS('Daily Sale entry '!$AC$2:$AC$1501,'Daily Sale entry '!$X$2:$X$1501,"<="&$A13,'Daily Sale entry '!$Z$2:$Z$1501,"Cheque deposit 支票存入")-SUMPRODUCT(('Daily Sale entry '!$Q$2:$Q$1501="Collection 收款")*('Daily Sale entry '!$R$2:$R$1501="Cheque 支票")*('Daily Sale entry '!$V$2:$V$1501<>"")*('Daily Sale entry '!$V$2:$V$1501<=$A13)*('Daily Sale entry '!$S$2:$S$1501-'Opening Balance'!$B$15*('Daily Sale entry '!$R$2:$R$1501="Cheque 支票")*('Daily Sale entry '!$S$2:$S$1501-TRUNC('Daily Sale entry '!$S$2:$S$1501)))),2)) | E13: =IF($A13="","",'Opening Balance'!$B$7) | F13: =IF($A13="","",ROUND(SUMIFS('Daily Sale entry '!$L$2:$L$367,'Daily Sale entry '!$A$2:$A$367,">="&DATE(YEAR($A13),MONTH($A13),1),'Daily Sale entry '!$A$2:$A$367,"<="&$A13)+SUMIFS('Daily Sale entry '!$M$2:$M$367,'Daily Sale entry '!$A$2:$A$367,">="&DATE(YEAR($A13),MONTH($A13),1),'Daily Sale entry '!$A$2:$A$367,"<="&$A13)+IF(AND(YEAR($A13)=YEAR('Daily Sale entry '!$A$2),MONTH($A13)=MONTH('Daily Sale entry '!$A$2)),'Opening Balance'!$B$8,0),2)) | G13: =IF($A13="","",MOD(ROUND('Opening Balance'!$B$9+SUMIFS('Sales & Collection'!$L$1:$L$157,'Sales & Collection'!$K$1:$K$157,"cash collection*"),2),'Opening Balance'!$B$11)) | H13: =IF($A13="","",ROUND('Opening Balance'!$B$10+'Opening Balance'!$B$9+SUMIFS('Sales & Collection'!$L$1:$L$157,'Sales & Collection'!$K$1:$K$157,"cash collection*")-G13-SUMIFS('Daily Sale entry '!$AC$2:$AC$1501,'Daily Sale entry '!$X$2:$X$1501,"<="&$A13,'Daily Sale entry '!$Z$2:$Z$1501,"Cash deposit 现金存入"),2)) | I13: =IF($A13="","",ROUND(B13+D13+E13+F13+G13+H13,2)) | J13: =IF($A13="","",'AR & AP'!K14) | K13: =IF($A13="","",ROUND(I13-J13-SUMIFS('Daily Sale entry '!$AC$2:$AC$1501,'Daily Sale entry '!$X$2:$X$1501,"<="&$A13,'Daily Sale entry '!$Z$2:$Z$1501,"Other deposit 其他存入")+SUMIFS('Daily Sale entry '!$AD$2:$AD$1501,'Daily Sale entry '!$X$2:$X$1501,"<="&$A13)+('Opening Balance'!$B$8+SUM('Daily Sale entry '!$L$2:M13)-F13),2)) | L13: =IF($A13="","",IF(ABS('Sales & Collection'!$B$166)>'Opening Balance'!$B$16,"ALERT 警报: Different "&TEXT('Sales & Collection'!$B$166,"#,##0.00")&" 差额过大",""))
A14: =IF('Daily Sale entry '!A14="","",'Daily Sale entry '!A14) | B14: =IF($A14="","",ROUND('Opening Balance'!$B$4+SUM('Daily Sale entry '!$K$2:K14)+SUMIFS('Daily Sale entry '!$AC$2:$AC$1501,'Daily Sale entry '!$X$2:$X$1501,"<="&$A14)-SUMIFS('Daily Sale entry '!$AD$2:$AD$1501,'Daily Sale entry '!$X$2:$X$1501,"<="&$A14)+SUMPRODUCT(('Daily Sale entry '!$Q$2:$Q$1501="Collection 收款")*('Daily Sale entry '!$R$2:$R$1501="Cheque 支票")*('Daily Sale entry '!$V$2:$V$1501<>"")*('Daily Sale entry '!$V$2:$V$1501<=$A14)*('Daily Sale entry '!$S$2:$S$1501-'Opening Balance'!$B$15*('Daily Sale entry '!$R$2:$R$1501="Cheque 支票")*('Daily Sale entry '!$S$2:$S$1501-TRUNC('Daily Sale entry '!$S$2:$S$1501))))-'Opening Balance'!$B$15*SUMPRODUCT(('Daily Sale entry '!$X$2:$X$1501<=$A14)*('Daily Sale entry '!$Z$2:$Z$1501="Online collection 网上收款")*('Daily Sale entry '!$AA$2:$AA$1501<>"")*('Daily Sale entry '!$AC$2:$AC$1501-TRUNC('Daily Sale entry '!$AC$2:$AC$1501))),2)) | C14: =IF($A14="","",'Opening Balance'!$B$5+SUM('Daily Sale entry '!$I$2:I14)-SUMIFS('Daily Sale entry '!$AB$2:$AB$1501,'Daily Sale entry '!$X$2:$X$1501,"<="&$A14,'Daily Sale entry '!$Z$2:$Z$1501,"Cheque deposit 支票存入")-COUNTIFS('Daily Sale entry '!$Q$2:$Q$1501,"Collection 收款",'Daily Sale entry '!$R$2:$R$1501,"Cheque 支票",'Daily Sale entry '!$V$2:$V$1501,"<="&$A14)) | D14: =IF($A14="","",ROUND('Opening Balance'!$B$6+SUM('Daily Sale entry '!$J$2:J14)-SUMIFS('Daily Sale entry '!$AC$2:$AC$1501,'Daily Sale entry '!$X$2:$X$1501,"<="&$A14,'Daily Sale entry '!$Z$2:$Z$1501,"Cheque deposit 支票存入")-SUMPRODUCT(('Daily Sale entry '!$Q$2:$Q$1501="Collection 收款")*('Daily Sale entry '!$R$2:$R$1501="Cheque 支票")*('Daily Sale entry '!$V$2:$V$1501<>"")*('Daily Sale entry '!$V$2:$V$1501<=$A14)*('Daily Sale entry '!$S$2:$S$1501-'Opening Balance'!$B$15*('Daily Sale entry '!$R$2:$R$1501="Cheque 支票")*('Daily Sale entry '!$S$2:$S$1501-TRUNC('Daily Sale entry '!$S$2:$S$1501)))),2)) | E14: =IF($A14="","",'Opening Balance'!$B$7) | F14: =IF($A14="","",ROUND(SUMIFS('Daily Sale entry '!$L$2:$L$367,'Daily Sale entry '!$A$2:$A$367,">="&DATE(YEAR($A14),MONTH($A14),1),'Daily Sale entry '!$A$2:$A$367,"<="&$A14)+SUMIFS('Daily Sale entry '!$M$2:$M$367,'Daily Sale entry '!$A$2:$A$367,">="&DATE(YEAR($A14),MONTH($A14),1),'Daily Sale entry '!$A$2:$A$367,"<="&$A14)+IF(AND(YEAR($A14)=YEAR('Daily Sale entry '!$A$2),MONTH($A14)=MONTH('Daily Sale entry '!$A$2)),'Opening Balance'!$B$8,0),2)) | G14: =IF($A14="","",MOD(ROUND('Opening Balance'!$B$9+SUMIFS('Sales & Collection'!$L$1:$L$171,'Sales & Collection'!$K$1:$K$171,"cash collection*"),2),'Opening Balance'!$B$11)) | H14: =IF($A14="","",ROUND('Opening Balance'!$B$10+'Opening Balance'!$B$9+SUMIFS('Sales & Collection'!$L$1:$L$171,'Sales & Collection'!$K$1:$K$171,"cash collection*")-G14-SUMIFS('Daily Sale entry '!$AC$2:$AC$1501,'Daily Sale entry '!$X$2:$X$1501,"<="&$A14,'Daily Sale entry '!$Z$2:$Z$1501,"Cash deposit 现金存入"),2)) | I14: =IF($A14="","",ROUND(B14+D14+E14+F14+G14+H14,2)) | J14: =IF($A14="","",'AR & AP'!K15) | K14: =IF($A14="","",ROUND(I14-J14-SUMIFS('Daily Sale entry '!$AC$2:$AC$1501,'Daily Sale entry '!$X$2:$X$1501,"<="&$A14,'Daily Sale entry '!$Z$2:$Z$1501,"Other deposit 其他存入")+SUMIFS('Daily Sale entry '!$AD$2:$AD$1501,'Daily Sale entry '!$X$2:$X$1501,"<="&$A14)+('Opening Balance'!$B$8+SUM('Daily Sale entry '!$L$2:M14)-F14),2)) | L14: =IF($A14="","",IF(ABS('Sales & Collection'!$B$180)>'Opening Balance'!$B$16,"ALERT 警报: Different "&TEXT('Sales & Collection'!$B$180,"#,##0.00")&" 差额过大",""))
A15: =IF('Daily Sale entry '!A15="","",'Daily Sale entry '!A15) | B15: =IF($A15="","",ROUND('Opening Balance'!$B$4+SUM('Daily Sale entry '!$K$2:K15)+SUMIFS('Daily Sale entry '!$AC$2:$AC$1501,'Daily Sale entry '!$X$2:$X$1501,"<="&$A15)-SUMIFS('Daily Sale entry '!$AD$2:$AD$1501,'Daily Sale entry '!$X$2:$X$1501,"<="&$A15)+SUMPRODUCT(('Daily Sale entry '!$Q$2:$Q$1501="Collection 收款")*('Daily Sale entry '!$R$2:$R$1501="Cheque 支票")*('Daily Sale entry '!$V$2:$V$1501<>"")*('Daily Sale entry '!$V$2:$V$1501<=$A15)*('Daily Sale entry '!$S$2:$S$1501-'Opening Balance'!$B$15*('Daily Sale entry '!$R$2:$R$1501="Cheque 支票")*('Daily Sale entry '!$S$2:$S$1501-TRUNC('Daily Sale entry '!$S$2:$S$1501))))-'Opening Balance'!$B$15*SUMPRODUCT(('Daily Sale entry '!$X$2:$X$1501<=$A15)*('Daily Sale entry '!$Z$2:$Z$1501="Online collection 网上收款")*('Daily Sale entry '!$AA$2:$AA$1501<>"")*('Daily Sale entry '!$AC$2:$AC$1501-TRUNC('Daily Sale entry '!$AC$2:$AC$1501))),2)) | C15: =IF($A15="","",'Opening Balance'!$B$5+SUM('Daily Sale entry '!$I$2:I15)-SUMIFS('Daily Sale entry '!$AB$2:$AB$1501,'Daily Sale entry '!$X$2:$X$1501,"<="&$A15,'Daily Sale entry '!$Z$2:$Z$1501,"Cheque deposit 支票存入")-COUNTIFS('Daily Sale entry '!$Q$2:$Q$1501,"Collection 收款",'Daily Sale entry '!$R$2:$R$1501,"Cheque 支票",'Daily Sale entry '!$V$2:$V$1501,"<="&$A15)) | D15: =IF($A15="","",ROUND('Opening Balance'!$B$6+SUM('Daily Sale entry '!$J$2:J15)-SUMIFS('Daily Sale entry '!$AC$2:$AC$1501,'Daily Sale entry '!$X$2:$X$1501,"<="&$A15,'Daily Sale entry '!$Z$2:$Z$1501,"Cheque deposit 支票存入")-SUMPRODUCT(('Daily Sale entry '!$Q$2:$Q$1501="Collection 收款")*('Daily Sale entry '!$R$2:$R$1501="Cheque 支票")*('Daily Sale entry '!$V$2:$V$1501<>"")*('Daily Sale entry '!$V$2:$V$1501<=$A15)*('Daily Sale entry '!$S$2:$S$1501-'Opening Balance'!$B$15*('Daily Sale entry '!$R$2:$R$1501="Cheque 支票")*('Daily Sale entry '!$S$2:$S$1501-TRUNC('Daily Sale entry '!$S$2:$S$1501)))),2)) | E15: =IF($A15="","",'Opening Balance'!$B$7) | F15: =IF($A15="","",ROUND(SUMIFS('Daily Sale entry '!$L$2:$L$367,'Daily Sale entry '!$A$2:$A$367,">="&DATE(YEAR($A15),MONTH($A15),1),'Daily Sale entry '!$A$2:$A$367,"<="&$A15)+SUMIFS('Daily Sale entry '!$M$2:$M$367,'Daily Sale entry '!$A$2:$A$367,">="&DATE(YEAR($A15),MONTH($A15),1),'Daily Sale entry '!$A$2:$A$367,"<="&$A15)+IF(AND(YEAR($A15)=YEAR('Daily Sale entry '!$A$2),MONTH($A15)=MONTH('Daily Sale entry '!$A$2)),'Opening Balance'!$B$8,0),2)) | G15: =IF($A15="","",MOD(ROUND('Opening Balance'!$B$9+SUMIFS('Sales & Collection'!$L$1:$L$185,'Sales & Collection'!$K$1:$K$185,"cash collection*"),2),'Opening Balance'!$B$11)) | H15: =IF($A15="","",ROUND('Opening Balance'!$B$10+'Opening Balance'!$B$9+SUMIFS('Sales & Collection'!$L$1:$L$185,'Sales & Collection'!$K$1:$K$185,"cash collection*")-G15-SUMIFS('Daily Sale entry '!$AC$2:$AC$1501,'Daily Sale entry '!$X$2:$X$1501,"<="&$A15,'Daily Sale entry '!$Z$2:$Z$1501,"Cash deposit 现金存入"),2)) | I15: =IF($A15="","",ROUND(B15+D15+E15+F15+G15+H15,2)) | J15: =IF($A15="","",'AR & AP'!K16) | K15: =IF($A15="","",ROUND(I15-J15-SUMIFS('Daily Sale entry '!$AC$2:$AC$1501,'Daily Sale entry '!$X$2:$X$1501,"<="&$A15,'Daily Sale entry '!$Z$2:$Z$1501,"Other deposit 其他存入")+SUMIFS('Daily Sale entry '!$AD$2:$AD$1501,'Daily Sale entry '!$X$2:$X$1501,"<="&$A15)+('Opening Balance'!$B$8+SUM('Daily Sale entry '!$L$2:M15)-F15),2)) | L15: =IF($A15="","",IF(ABS('Sales & Collection'!$B$194)>'Opening Balance'!$B$16,"ALERT 警报: Different "&TEXT('Sales & Collection'!$B$194,"#,##0.00")&" 差额过大",""))
A16: =IF('Daily Sale entry '!A16="","",'Daily Sale entry '!A16) | B16: =IF($A16="","",ROUND('Opening Balance'!$B$4+SUM('Daily Sale entry '!$K$2:K16)+SUMIFS('Daily Sale entry '!$AC$2:$AC$1501,'Daily Sale entry '!$X$2:$X$1501,"<="&$A16)-SUMIFS('Daily Sale entry '!$AD$2:$AD$1501,'Daily Sale entry '!$X$2:$X$1501,"<="&$A16)+SUMPRODUCT(('Daily Sale entry '!$Q$2:$Q$1501="Collection 收款")*('Daily Sale entry '!$R$2:$R$1501="Cheque 支票")*('Daily Sale entry '!$V$2:$V$1501<>"")*('Daily Sale entry '!$V$2:$V$1501<=$A16)*('Daily Sale entry '!$S$2:$S$1501-'Opening Balance'!$B$15*('Daily Sale entry '!$R$2:$R$1501="Cheque 支票")*('Daily Sale entry '!$S$2:$S$1501-TRUNC('Daily Sale entry '!$S$2:$S$1501))))-'Opening Balance'!$B$15*SUMPRODUCT(('Daily Sale entry '!$X$2:$X$1501<=$A16)*('Daily Sale entry '!$Z$2:$Z$1501="Online collection 网上收款")*('Daily Sale entry '!$AA$2:$AA$1501<>"")*('Daily Sale entry '!$AC$2:$AC$1501-TRUNC('Daily Sale entry '!$AC$2:$AC$1501))),2)) | C16: =IF($A16="","",'Opening Balance'!$B$5+SUM('Daily Sale entry '!$I$2:I16)-SUMIFS('Daily Sale entry '!$AB$2:$AB$1501,'Daily Sale entry '!$X$2:$X$1501,"<="&$A16,'Daily Sale entry '!$Z$2:$Z$1501,"Cheque deposit 支票存入")-COUNTIFS('Daily Sale entry '!$Q$2:$Q$1501,"Collection 收款",'Daily Sale entry '!$R$2:$R$1501,"Cheque 支票",'Daily Sale entry '!$V$2:$V$1501,"<="&$A16)) | D16: =IF($A16="","",ROUND('Opening Balance'!$B$6+SUM('Daily Sale entry '!$J$2:J16)-SUMIFS('Daily Sale entry '!$AC$2:$AC$1501,'Daily Sale entry '!$X$2:$X$1501,"<="&$A16,'Daily Sale entry '!$Z$2:$Z$1501,"Cheque deposit 支票存入")-SUMPRODUCT(('Daily Sale entry '!$Q$2:$Q$1501="Collection 收款")*('Daily Sale entry '!$R$2:$R$1501="Cheque 支票")*('Daily Sale entry '!$V$2:$V$1501<>"")*('Daily Sale entry '!$V$2:$V$1501<=$A16)*('Daily Sale entry '!$S$2:$S$1501-'Opening Balance'!$B$15*('Daily Sale entry '!$R$2:$R$1501="Cheque 支票")*('Daily Sale entry '!$S$2:$S$1501-TRUNC('Daily Sale entry '!$S$2:$S$1501)))),2)) | E16: =IF($A16="","",'Opening Balance'!$B$7) | F16: =IF($A16="","",ROUND(SUMIFS('Daily Sale entry '!$L$2:$L$367,'Daily Sale entry '!$A$2:$A$367,">="&DATE(YEAR($A16),MONTH($A16),1),'Daily Sale entry '!$A$2:$A$367,"<="&$A16)+SUMIFS('Daily Sale entry '!$M$2:$M$367,'Daily Sale entry '!$A$2:$A$367,">="&DATE(YEAR($A16),MONTH($A16),1),'Daily Sale entry '!$A$2:$A$367,"<="&$A16)+IF(AND(YEAR($A16)=YEAR('Daily Sale entry '!$A$2),MONTH($A16)=MONTH('Daily Sale entry '!$A$2)),'Opening Balance'!$B$8,0),2)) | G16: =IF($A16="","",MOD(ROUND('Opening Balance'!$B$9+SUMIFS('Sales & Collection'!$L$1:$L$199,'Sales & Collection'!$K$1:$K$199,"cash collection*"),2),'Opening Balance'!$B$11)) | H16: =IF($A16="","",ROUND('Opening Balance'!$B$10+'Opening Balance'!$B$9+SUMIFS('Sales & Collection'!$L$1:$L$199,'Sales & Collection'!$K$1:$K$199,"cash collection*")-G16-SUMIFS('Daily Sale entry '!$AC$2:$AC$1501,'Daily Sale entry '!$X$2:$X$1501,"<="&$A16,'Daily Sale entry '!$Z$2:$Z$1501,"Cash deposit 现金存入"),2)) | I16: =IF($A16="","",ROUND(B16+D16+E16+F16+G16+H16,2)) | J16: =IF($A16="","",'AR & AP'!K17) | K16: =IF($A16="","",ROUND(I16-J16-SUMIFS('Daily Sale entry '!$AC$2:$AC$1501,'Daily Sale entry '!$X$2:$X$1501,"<="&$A16,'Daily Sale entry '!$Z$2:$Z$1501,"Other deposit 其他存入")+SUMIFS('Daily Sale entry '!$AD$2:$AD$1501,'Daily Sale entry '!$X$2:$X$1501,"<="&$A16)+('Opening Balance'!$B$8+SUM('Daily Sale entry '!$L$2:M16)-F16),2)) | L16: =IF($A16="","",IF(ABS('Sales & Collection'!$B$208)>'Opening Balance'!$B$16,"ALERT 警报: Different "&TEXT('Sales & Collection'!$B$208,"#,##0.00")&" 差额过大",""))
A17: =IF('Daily Sale entry '!A17="","",'Daily Sale entry '!A17) | B17: =IF($A17="","",ROUND('Opening Balance'!$B$4+SUM('Daily Sale entry '!$K$2:K17)+SUMIFS('Daily Sale entry '!$AC$2:$AC$1501,'Daily Sale entry '!$X$2:$X$1501,"<="&$A17)-SUMIFS('Daily Sale entry '!$AD$2:$AD$1501,'Daily Sale entry '!$X$2:$X$1501,"<="&$A17)+SUMPRODUCT(('Daily Sale entry '!$Q$2:$Q$1501="Collection 收款")*('Daily Sale entry '!$R$2:$R$1501="Cheque 支票")*('Daily Sale entry '!$V$2:$V$1501<>"")*('Daily Sale entry '!$V$2:$V$1501<=$A17)*('Daily Sale entry '!$S$2:$S$1501-'Opening Balance'!$B$15*('Daily Sale entry '!$R$2:$R$1501="Cheque 支票")*('Daily Sale entry '!$S$2:$S$1501-TRUNC('Daily Sale entry '!$S$2:$S$1501))))-'Opening Balance'!$B$15*SUMPRODUCT(('Daily Sale entry '!$X$2:$X$1501<=$A17)*('Daily Sale entry '!$Z$2:$Z$1501="Online collection 网上收款")*('Daily Sale entry '!$AA$2:$AA$1501<>"")*('Daily Sale entry '!$AC$2:$AC$1501-TRUNC('Daily Sale entry '!$AC$2:$AC$1501))),2)) | C17: =IF($A17="","",'Opening Balance'!$B$5+SUM('Daily Sale entry '!$I$2:I17)-SUMIFS('Daily Sale entry '!$AB$2:$AB$1501,'Daily Sale entry '!$X$2:$X$1501,"<="&$A17,'Daily Sale entry '!$Z$2:$Z$1501,"Cheque deposit 支票存入")-COUNTIFS('Daily Sale entry '!$Q$2:$Q$1501,"Collection 收款",'Daily Sale entry '!$R$2:$R$1501,"Cheque 支票",'Daily Sale entry '!$V$2:$V$1501,"<="&$A17)) | D17: =IF($A17="","",ROUND('Opening Balance'!$B$6+SUM('Daily Sale entry '!$J$2:J17)-SUMIFS('Daily Sale entry '!$AC$2:$AC$1501,'Daily Sale entry '!$X$2:$X$1501,"<="&$A17,'Daily Sale entry '!$Z$2:$Z$1501,"Cheque deposit 支票存入")-SUMPRODUCT(('Daily Sale entry '!$Q$2:$Q$1501="Collection 收款")*('Daily Sale entry '!$R$2:$R$1501="Cheque 支票")*('Daily Sale entry '!$V$2:$V$1501<>"")*('Daily Sale entry '!$V$2:$V$1501<=$A17)*('Daily Sale entry '!$S$2:$S$1501-'Opening Balance'!$B$15*('Daily Sale entry '!$R$2:$R$1501="Cheque 支票")*('Daily Sale entry '!$S$2:$S$1501-TRUNC('Daily Sale entry '!$S$2:$S$1501)))),2)) | E17: =IF($A17="","",'Opening Balance'!$B$7) | F17: =IF($A17="","",ROUND(SUMIFS('Daily Sale entry '!$L$2:$L$367,'Daily Sale entry '!$A$2:$A$367,">="&DATE(YEAR($A17),MONTH($A17),1),'Daily Sale entry '!$A$2:$A$367,"<="&$A17)+SUMIFS('Daily Sale entry '!$M$2:$M$367,'Daily Sale entry '!$A$2:$A$367,">="&DATE(YEAR($A17),MONTH($A17),1),'Daily Sale entry '!$A$2:$A$367,"<="&$A17)+IF(AND(YEAR($A17)=YEAR('Daily Sale entry '!$A$2),MONTH($A17)=MONTH('Daily Sale entry '!$A$2)),'Opening Balance'!$B$8,0),2)) | G17: =IF($A17="","",MOD(ROUND('Opening Balance'!$B$9+SUMIFS('Sales & Collection'!$L$1:$L$213,'Sales & Collection'!$K$1:$K$213,"cash collection*"),2),'Opening Balance'!$B$11)) | H17: =IF($A17="","",ROUND('Opening Balance'!$B$10+'Opening Balance'!$B$9+SUMIFS('Sales & Collection'!$L$1:$L$213,'Sales & Collection'!$K$1:$K$213,"cash collection*")-G17-SUMIFS('Daily Sale entry '!$AC$2:$AC$1501,'Daily Sale entry '!$X$2:$X$1501,"<="&$A17,'Daily Sale entry '!$Z$2:$Z$1501,"Cash deposit 现金存入"),2)) | I17: =IF($A17="","",ROUND(B17+D17+E17+F17+G17+H17,2)) | J17: =IF($A17="","",'AR & AP'!K18) | K17: =IF($A17="","",ROUND(I17-J17-SUMIFS('Daily Sale entry '!$AC$2:$AC$1501,'Daily Sale entry '!$X$2:$X$1501,"<="&$A17,'Daily Sale entry '!$Z$2:$Z$1501,"Other deposit 其他存入")+SUMIFS('Daily Sale entry '!$AD$2:$AD$1501,'Daily Sale entry '!$X$2:$X$1501,"<="&$A17)+('Opening Balance'!$B$8+SUM('Daily Sale entry '!$L$2:M17)-F17),2)) | L17: =IF($A17="","",IF(ABS('Sales & Collection'!$B$222)>'Opening Balance'!$B$16,"ALERT 警报: Different "&TEXT('Sales & Collection'!$B$222,"#,##0.00")&" 差额过大",""))
A18: =IF('Daily Sale entry '!A18="","",'Daily Sale entry '!A18) | B18: =IF($A18="","",ROUND('Opening Balance'!$B$4+SUM('Daily Sale entry '!$K$2:K18)+SUMIFS('Daily Sale entry '!$AC$2:$AC$1501,'Daily Sale entry '!$X$2:$X$1501,"<="&$A18)-SUMIFS('Daily Sale entry '!$AD$2:$AD$1501,'Daily Sale entry '!$X$2:$X$1501,"<="&$A18)+SUMPRODUCT(('Daily Sale entry '!$Q$2:$Q$1501="Collection 收款")*('Daily Sale entry '!$R$2:$R$1501="Cheque 支票")*('Daily Sale entry '!$V$2:$V$1501<>"")*('Daily Sale entry '!$V$2:$V$1501<=$A18)*('Daily Sale entry '!$S$2:$S$1501-'Opening Balance'!$B$15*('Daily Sale entry '!$R$2:$R$1501="Cheque 支票")*('Daily Sale entry '!$S$2:$S$1501-TRUNC('Daily Sale entry '!$S$2:$S$1501))))-'Opening Balance'!$B$15*SUMPRODUCT(('Daily Sale entry '!$X$2:$X$1501<=$A18)*('Daily Sale entry '!$Z$2:$Z$1501="Online collection 网上收款")*('Daily Sale entry '!$AA$2:$AA$1501<>"")*('Daily Sale entry '!$AC$2:$AC$1501-TRUNC('Daily Sale entry '!$AC$2:$AC$1501))),2)) | C18: =IF($A18="","",'Opening Balance'!$B$5+SUM('Daily Sale entry '!$I$2:I18)-SUMIFS('Daily Sale entry '!$AB$2:$AB$1501,'Daily Sale entry '!$X$2:$X$1501,"<="&$A18,'Daily Sale entry '!$Z$2:$Z$1501,"Cheque deposit 支票存入")-COUNTIFS('Daily Sale entry '!$Q$2:$Q$1501,"Collection 收款",'Daily Sale entry '!$R$2:$R$1501,"Cheque 支票",'Daily Sale entry '!$V$2:$V$1501,"<="&$A18)) | D18: =IF($A18="","",ROUND('Opening Balance'!$B$6+SUM('Daily Sale entry '!$J$2:J18)-SUMIFS('Daily Sale entry '!$AC$2:$AC$1501,'Daily Sale entry '!$X$2:$X$1501,"<="&$A18,'Daily Sale entry '!$Z$2:$Z$1501,"Cheque deposit 支票存入")-SUMPRODUCT(('Daily Sale entry '!$Q$2:$Q$1501="Collection 收款")*('Daily Sale entry '!$R$2:$R$1501="Cheque 支票")*('Daily Sale entry '!$V$2:$V$1501<>"")*('Daily Sale entry '!$V$2:$V$1501<=$A18)*('Daily Sale entry '!$S$2:$S$1501-'Opening Balance'!$B$15*('Daily Sale entry '!$R$2:$R$1501="Cheque 支票")*('Daily Sale entry '!$S$2:$S$1501-TRUNC('Daily Sale entry '!$S$2:$S$1501)))),2)) | E18: =IF($A18="","",'Opening Balance'!$B$7) | F18: =IF($A18="","",ROUND(SUMIFS('Daily Sale entry '!$L$2:$L$367,'Daily Sale entry '!$A$2:$A$367,">="&DATE(YEAR($A18),MONTH($A18),1),'Daily Sale entry '!$A$2:$A$367,"<="&$A18)+SUMIFS('Daily Sale entry '!$M$2:$M$367,'Daily Sale entry '!$A$2:$A$367,">="&DATE(YEAR($A18),MONTH($A18),1),'Daily Sale entry '!$A$2:$A$367,"<="&$A18)+IF(AND(YEAR($A18)=YEAR('Daily Sale entry '!$A$2),MONTH($A18)=MONTH('Daily Sale entry '!$A$2)),'Opening Balance'!$B$8,0),2)) | G18: =IF($A18="","",MOD(ROUND('Opening Balance'!$B$9+SUMIFS('Sales & Collection'!$L$1:$L$227,'Sales & Collection'!$K$1:$K$227,"cash collection*"),2),'Opening Balance'!$B$11)) | H18: =IF($A18="","",ROUND('Opening Balance'!$B$10+'Opening Balance'!$B$9+SUMIFS('Sales & Collection'!$L$1:$L$227,'Sales & Collection'!$K$1:$K$227,"cash collection*")-G18-SUMIFS('Daily Sale entry '!$AC$2:$AC$1501,'Daily Sale entry '!$X$2:$X$1501,"<="&$A18,'Daily Sale entry '!$Z$2:$Z$1501,"Cash deposit 现金存入"),2)) | I18: =IF($A18="","",ROUND(B18+D18+E18+F18+G18+H18,2)) | J18: =IF($A18="","",'AR & AP'!K19) | K18: =IF($A18="","",ROUND(I18-J18-SUMIFS('Daily Sale entry '!$AC$2:$AC$1501,'Daily Sale entry '!$X$2:$X$1501,"<="&$A18,'Daily Sale entry '!$Z$2:$Z$1501,"Other deposit 其他存入")+SUMIFS('Daily Sale entry '!$AD$2:$AD$1501,'Daily Sale entry '!$X$2:$X$1501,"<="&$A18)+('Opening Balance'!$B$8+SUM('Daily Sale entry '!$L$2:M18)-F18),2)) | L18: =IF($A18="","",IF(ABS('Sales & Collection'!$B$236)>'Opening Balance'!$B$16,"ALERT 警报: Different "&TEXT('Sales & Collection'!$B$236,"#,##0.00")&" 差额过大",""))
A19: =IF('Daily Sale entry '!A19="","",'Daily Sale entry '!A19) | B19: =IF($A19="","",ROUND('Opening Balance'!$B$4+SUM('Daily Sale entry '!$K$2:K19)+SUMIFS('Daily Sale entry '!$AC$2:$AC$1501,'Daily Sale entry '!$X$2:$X$1501,"<="&$A19)-SUMIFS('Daily Sale entry '!$AD$2:$AD$1501,'Daily Sale entry '!$X$2:$X$1501,"<="&$A19)+SUMPRODUCT(('Daily Sale entry '!$Q$2:$Q$1501="Collection 收款")*('Daily Sale entry '!$R$2:$R$1501="Cheque 支票")*('Daily Sale entry '!$V$2:$V$1501<>"")*('Daily Sale entry '!$V$2:$V$1501<=$A19)*('Daily Sale entry '!$S$2:$S$1501-'Opening Balance'!$B$15*('Daily Sale entry '!$R$2:$R$1501="Cheque 支票")*('Daily Sale entry '!$S$2:$S$1501-TRUNC('Daily Sale entry '!$S$2:$S$1501))))-'Opening Balance'!$B$15*SUMPRODUCT(('Daily Sale entry '!$X$2:$X$1501<=$A19)*('Daily Sale entry '!$Z$2:$Z$1501="Online collection 网上收款")*('Daily Sale entry '!$AA$2:$AA$1501<>"")*('Daily Sale entry '!$AC$2:$AC$1501-TRUNC('Daily Sale entry '!$AC$2:$AC$1501))),2)) | C19: =IF($A19="","",'Opening Balance'!$B$5+SUM('Daily Sale entry '!$I$2:I19)-SUMIFS('Daily Sale entry '!$AB$2:$AB$1501,'Daily Sale entry '!$X$2:$X$1501,"<="&$A19,'Daily Sale entry '!$Z$2:$Z$1501,"Cheque deposit 支票存入")-COUNTIFS('Daily Sale entry '!$Q$2:$Q$1501,"Collection 收款",'Daily Sale entry '!$R$2:$R$1501,"Cheque 支票",'Daily Sale entry '!$V$2:$V$1501,"<="&$A19)) | D19: =IF($A19="","",ROUND('Opening Balance'!$B$6+SUM('Daily Sale entry '!$J$2:J19)-SUMIFS('Daily Sale entry '!$AC$2:$AC$1501,'Daily Sale entry '!$X$2:$X$1501,"<="&$A19,'Daily Sale entry '!$Z$2:$Z$1501,"Cheque deposit 支票存入")-SUMPRODUCT(('Daily Sale entry '!$Q$2:$Q$1501="Collection 收款")*('Daily Sale entry '!$R$2:$R$1501="Cheque 支票")*('Daily Sale entry '!$V$2:$V$1501<>"")*('Daily Sale entry '!$V$2:$V$1501<=$A19)*('Daily Sale entry '!$S$2:$S$1501-'Opening Balance'!$B$15*('Daily Sale entry '!$R$2:$R$1501="Cheque 支票")*('Daily Sale entry '!$S$2:$S$1501-TRUNC('Daily Sale entry '!$S$2:$S$1501)))),2)) | E19: =IF($A19="","",'Opening Balance'!$B$7) | F19: =IF($A19="","",ROUND(SUMIFS('Daily Sale entry '!$L$2:$L$367,'Daily Sale entry '!$A$2:$A$367,">="&DATE(YEAR($A19),MONTH($A19),1),'Daily Sale entry '!$A$2:$A$367,"<="&$A19)+SUMIFS('Daily Sale entry '!$M$2:$M$367,'Daily Sale entry '!$A$2:$A$367,">="&DATE(YEAR($A19),MONTH($A19),1),'Daily Sale entry '!$A$2:$A$367,"<="&$A19)+IF(AND(YEAR($A19)=YEAR('Daily Sale entry '!$A$2),MONTH($A19)=MONTH('Daily Sale entry '!$A$2)),'Opening Balance'!$B$8,0),2)) | G19: =IF($A19="","",MOD(ROUND('Opening Balance'!$B$9+SUMIFS('Sales & Collection'!$L$1:$L$241,'Sales & Collection'!$K$1:$K$241,"cash collection*"),2),'Opening Balance'!$B$11)) | H19: =IF($A19="","",ROUND('Opening Balance'!$B$10+'Opening Balance'!$B$9+SUMIFS('Sales & Collection'!$L$1:$L$241,'Sales & Collection'!$K$1:$K$241,"cash collection*")-G19-SUMIFS('Daily Sale entry '!$AC$2:$AC$1501,'Daily Sale entry '!$X$2:$X$1501,"<="&$A19,'Daily Sale entry '!$Z$2:$Z$1501,"Cash deposit 现金存入"),2)) | I19: =IF($A19="","",ROUND(B19+D19+E19+F19+G19+H19,2)) | J19: =IF($A19="","",'AR & AP'!K20) | K19: =IF($A19="","",ROUND(I19-J19-SUMIFS('Daily Sale entry '!$AC$2:$AC$1501,'Daily Sale entry '!$X$2:$X$1501,"<="&$A19,'Daily Sale entry '!$Z$2:$Z$1501,"Other deposit 其他存入")+SUMIFS('Daily Sale entry '!$AD$2:$AD$1501,'Daily Sale entry '!$X$2:$X$1501,"<="&$A19)+('Opening Balance'!$B$8+SUM('Daily Sale entry '!$L$2:M19)-F19),2)) | L19: =IF($A19="","",IF(ABS('Sales & Collection'!$B$250)>'Opening Balance'!$B$16,"ALERT 警报: Different "&TEXT('Sales & Collection'!$B$250,"#,##0.00")&" 差额过大",""))
A20: =IF('Daily Sale entry '!A20="","",'Daily Sale entry '!A20) | B20: =IF($A20="","",ROUND('Opening Balance'!$B$4+SUM('Daily Sale entry '!$K$2:K20)+SUMIFS('Daily Sale entry '!$AC$2:$AC$1501,'Daily Sale entry '!$X$2:$X$1501,"<="&$A20)-SUMIFS('Daily Sale entry '!$AD$2:$AD$1501,'Daily Sale entry '!$X$2:$X$1501,"<="&$A20)+SUMPRODUCT(('Daily Sale entry '!$Q$2:$Q$1501="Collection 收款")*('Daily Sale entry '!$R$2:$R$1501="Cheque 支票")*('Daily Sale entry '!$V$2:$V$1501<>"")*('Daily Sale entry '!$V$2:$V$1501<=$A20)*('Daily Sale entry '!$S$2:$S$1501-'Opening Balance'!$B$15*('Daily Sale entry '!$R$2:$R$1501="Cheque 支票")*('Daily Sale entry '!$S$2:$S$1501-TRUNC('Daily Sale entry '!$S$2:$S$1501))))-'Opening Balance'!$B$15*SUMPRODUCT(('Daily Sale entry '!$X$2:$X$1501<=$A20)*('Daily Sale entry '!$Z$2:$Z$1501="Online collection 网上收款")*('Daily Sale entry '!$AA$2:$AA$1501<>"")*('Daily Sale entry '!$AC$2:$AC$1501-TRUNC('Daily Sale entry '!$AC$2:$AC$1501))),2)) | C20: =IF($A20="","",'Opening Balance'!$B$5+SUM('Daily Sale entry '!$I$2:I20)-SUMIFS('Daily Sale entry '!$AB$2:$AB$1501,'Daily Sale entry '!$X$2:$X$1501,"<="&$A20,'Daily Sale entry '!$Z$2:$Z$1501,"Cheque deposit 支票存入")-COUNTIFS('Daily Sale entry '!$Q$2:$Q$1501,"Collection 收款",'Daily Sale entry '!$R$2:$R$1501,"Cheque 支票",'Daily Sale entry '!$V$2:$V$1501,"<="&$A20)) | D20: =IF($A20="","",ROUND('Opening Balance'!$B$6+SUM('Daily Sale entry '!$J$2:J20)-SUMIFS('Daily Sale entry '!$AC$2:$AC$1501,'Daily Sale entry '!$X$2:$X$1501,"<="&$A20,'Daily Sale entry '!$Z$2:$Z$1501,"Cheque deposit 支票存入")-SUMPRODUCT(('Daily Sale entry '!$Q$2:$Q$1501="Collection 收款")*('Daily Sale entry '!$R$2:$R$1501="Cheque 支票")*('Daily Sale entry '!$V$2:$V$1501<>"")*('Daily Sale entry '!$V$2:$V$1501<=$A20)*('Daily Sale entry '!$S$2:$S$1501-'Opening Balance'!$B$15*('Daily Sale entry '!$R$2:$R$1501="Cheque 支票")*('Daily Sale entry '!$S$2:$S$1501-TRUNC('Daily Sale entry '!$S$2:$S$1501)))),2)) | E20: =IF($A20="","",'Opening Balance'!$B$7) | F20: =IF($A20="","",ROUND(SUMIFS('Daily Sale entry '!$L$2:$L$367,'Daily Sale entry '!$A$2:$A$367,">="&DATE(YEAR($A20),MONTH($A20),1),'Daily Sale entry '!$A$2:$A$367,"<="&$A20)+SUMIFS('Daily Sale entry '!$M$2:$M$367,'Daily Sale entry '!$A$2:$A$367,">="&DATE(YEAR($A20),MONTH($A20),1),'Daily Sale entry '!$A$2:$A$367,"<="&$A20)+IF(AND(YEAR($A20)=YEAR('Daily Sale entry '!$A$2),MONTH($A20)=MONTH('Daily Sale entry '!$A$2)),'Opening Balance'!$B$8,0),2)) | G20: =IF($A20="","",MOD(ROUND('Opening Balance'!$B$9+SUMIFS('Sales & Collection'!$L$1:$L$255,'Sales & Collection'!$K$1:$K$255,"cash collection*"),2),'Opening Balance'!$B$11)) | H20: =IF($A20="","",ROUND('Opening Balance'!$B$10+'Opening Balance'!$B$9+SUMIFS('Sales & Collection'!$L$1:$L$255,'Sales & Collection'!$K$1:$K$255,"cash collection*")-G20-SUMIFS('Daily Sale entry '!$AC$2:$AC$1501,'Daily Sale entry '!$X$2:$X$1501,"<="&$A20,'Daily Sale entry '!$Z$2:$Z$1501,"Cash deposit 现金存入"),2)) | I20: =IF($A20="","",ROUND(B20+D20+E20+F20+G20+H20,2)) | J20: =IF($A20="","",'AR & AP'!K21) | K20: =IF($A20="","",ROUND(I20-J20-SUMIFS('Daily Sale entry '!$AC$2:$AC$1501,'Daily Sale entry '!$X$2:$X$1501,"<="&$A20,'Daily Sale entry '!$Z$2:$Z$1501,"Other deposit 其他存入")+SUMIFS('Daily Sale entry '!$AD$2:$AD$1501,'Daily Sale entry '!$X$2:$X$1501,"<="&$A20)+('Opening Balance'!$B$8+SUM('Daily Sale entry '!$L$2:M20)-F20),2)) | L20: =IF($A20="","",IF(ABS('Sales & Collection'!$B$264)>'Opening Balance'!$B$16,"ALERT 警报: Different "&TEXT('Sales & Collection'!$B$264,"#,##0.00")&" 差额过大",""))
A21: =IF('Daily Sale entry '!A21="","",'Daily Sale entry '!A21) | B21: =IF($A21="","",ROUND('Opening Balance'!$B$4+SUM('Daily Sale entry '!$K$2:K21)+SUMIFS('Daily Sale entry '!$AC$2:$AC$1501,'Daily Sale entry '!$X$2:$X$1501,"<="&$A21)-SUMIFS('Daily Sale entry '!$AD$2:$AD$1501,'Daily Sale entry '!$X$2:$X$1501,"<="&$A21)+SUMPRODUCT(('Daily Sale entry '!$Q$2:$Q$1501="Collection 收款")*('Daily Sale entry '!$R$2:$R$1501="Cheque 支票")*('Daily Sale entry '!$V$2:$V$1501<>"")*('Daily Sale entry '!$V$2:$V$1501<=$A21)*('Daily Sale entry '!$S$2:$S$1501-'Opening Balance'!$B$15*('Daily Sale entry '!$R$2:$R$1501="Cheque 支票")*('Daily Sale entry '!$S$2:$S$1501-TRUNC('Daily Sale entry '!$S$2:$S$1501))))-'Opening Balance'!$B$15*SUMPRODUCT(('Daily Sale entry '!$X$2:$X$1501<=$A21)*('Daily Sale entry '!$Z$2:$Z$1501="Online collection 网上收款")*('Daily Sale entry '!$AA$2:$AA$1501<>"")*('Daily Sale entry '!$AC$2:$AC$1501-TRUNC('Daily Sale entry '!$AC$2:$AC$1501))),2)) | C21: =IF($A21="","",'Opening Balance'!$B$5+SUM('Daily Sale entry '!$I$2:I21)-SUMIFS('Daily Sale entry '!$AB$2:$AB$1501,'Daily Sale entry '!$X$2:$X$1501,"<="&$A21,'Daily Sale entry '!$Z$2:$Z$1501,"Cheque deposit 支票存入")-COUNTIFS('Daily Sale entry '!$Q$2:$Q$1501,"Collection 收款",'Daily Sale entry '!$R$2:$R$1501,"Cheque 支票",'Daily Sale entry '!$V$2:$V$1501,"<="&$A21)) | D21: =IF($A21="","",ROUND('Opening Balance'!$B$6+SUM('Daily Sale entry '!$J$2:J21)-SUMIFS('Daily Sale entry '!$AC$2:$AC$1501,'Daily Sale entry '!$X$2:$X$1501,"<="&$A21,'Daily Sale entry '!$Z$2:$Z$1501,"Cheque deposit 支票存入")-SUMPRODUCT(('Daily Sale entry '!$Q$2:$Q$1501="Collection 收款")*('Daily Sale entry '!$R$2:$R$1501="Cheque 支票")*('Daily Sale entry '!$V$2:$V$1501<>"")*('Daily Sale entry '!$V$2:$V$1501<=$A21)*('Daily Sale entry '!$S$2:$S$1501-'Opening Balance'!$B$15*('Daily Sale entry '!$R$2:$R$1501="Cheque 支票")*('Daily Sale entry '!$S$2:$S$1501-TRUNC('Daily Sale entry '!$S$2:$S$1501)))),2)) | E21: =IF($A21="","",'Opening Balance'!$B$7) | F21: =IF($A21="","",ROUND(SUMIFS('Daily Sale entry '!$L$2:$L$367,'Daily Sale entry '!$A$2:$A$367,">="&DATE(YEAR($A21),MONTH($A21),1),'Daily Sale entry '!$A$2:$A$367,"<="&$A21)+SUMIFS('Daily Sale entry '!$M$2:$M$367,'Daily Sale entry '!$A$2:$A$367,">="&DATE(YEAR($A21),MONTH($A21),1),'Daily Sale entry '!$A$2:$A$367,"<="&$A21)+IF(AND(YEAR($A21)=YEAR('Daily Sale entry '!$A$2),MONTH($A21)=MONTH('Daily Sale entry '!$A$2)),'Opening Balance'!$B$8,0),2)) | G21: =IF($A21="","",MOD(ROUND('Opening Balance'!$B$9+SUMIFS('Sales & Collection'!$L$1:$L$269,'Sales & Collection'!$K$1:$K$269,"cash collection*"),2),'Opening Balance'!$B$11)) | H21: =IF($A21="","",ROUND('Opening Balance'!$B$10+'Opening Balance'!$B$9+SUMIFS('Sales & Collection'!$L$1:$L$269,'Sales & Collection'!$K$1:$K$269,"cash collection*")-G21-SUMIFS('Daily Sale entry '!$AC$2:$AC$1501,'Daily Sale entry '!$X$2:$X$1501,"<="&$A21,'Daily Sale entry '!$Z$2:$Z$1501,"Cash deposit 现金存入"),2)) | I21: =IF($A21="","",ROUND(B21+D21+E21+F21+G21+H21,2)) | J21: =IF($A21="","",'AR & AP'!K22) | K21: =IF($A21="","",ROUND(I21-J21-SUMIFS('Daily Sale entry '!$AC$2:$AC$1501,'Daily Sale entry '!$X$2:$X$1501,"<="&$A21,'Daily Sale entry '!$Z$2:$Z$1501,"Other deposit 其他存入")+SUMIFS('Daily Sale entry '!$AD$2:$AD$1501,'Daily Sale entry '!$X$2:$X$1501,"<="&$A21)+('Opening Balance'!$B$8+SUM('Daily Sale entry '!$L$2:M21)-F21),2)) | L21: =IF($A21="","",IF(ABS('Sales & Collection'!$B$278)>'Opening Balance'!$B$16,"ALERT 警报: Different "&TEXT('Sales & Collection'!$B$278,"#,##0.00")&" 差额过大",""))
A22: =IF('Daily Sale entry '!A22="","",'Daily Sale entry '!A22) | B22: =IF($A22="","",ROUND('Opening Balance'!$B$4+SUM('Daily Sale entry '!$K$2:K22)+SUMIFS('Daily Sale entry '!$AC$2:$AC$1501,'Daily Sale entry '!$X$2:$X$1501,"<="&$A22)-SUMIFS('Daily Sale entry '!$AD$2:$AD$1501,'Daily Sale entry '!$X$2:$X$1501,"<="&$A22)+SUMPRODUCT(('Daily Sale entry '!$Q$2:$Q$1501="Collection 收款")*('Daily Sale entry '!$R$2:$R$1501="Cheque 支票")*('Daily Sale entry '!$V$2:$V$1501<>"")*('Daily Sale entry '!$V$2:$V$1501<=$A22)*('Daily Sale entry '!$S$2:$S$1501-'Opening Balance'!$B$15*('Daily Sale entry '!$R$2:$R$1501="Cheque 支票")*('Daily Sale entry '!$S$2:$S$1501-TRUNC('Daily Sale entry '!$S$2:$S$1501))))-'Opening Balance'!$B$15*SUMPRODUCT(('Daily Sale entry '!$X$2:$X$1501<=$A22)*('Daily Sale entry '!$Z$2:$Z$1501="Online collection 网上收款")*('Daily Sale entry '!$AA$2:$AA$1501<>"")*('Daily Sale entry '!$AC$2:$AC$1501-TRUNC('Daily Sale entry '!$AC$2:$AC$1501))),2)) | C22: =IF($A22="","",'Opening Balance'!$B$5+SUM('Daily Sale entry '!$I$2:I22)-SUMIFS('Daily Sale entry '!$AB$2:$AB$1501,'Daily Sale entry '!$X$2:$X$1501,"<="&$A22,'Daily Sale entry '!$Z$2:$Z$1501,"Cheque deposit 支票存入")-COUNTIFS('Daily Sale entry '!$Q$2:$Q$1501,"Collection 收款",'Daily Sale entry '!$R$2:$R$1501,"Cheque 支票",'Daily Sale entry '!$V$2:$V$1501,"<="&$A22)) | D22: =IF($A22="","",ROUND('Opening Balance'!$B$6+SUM('Daily Sale entry '!$J$2:J22)-SUMIFS('Daily Sale entry '!$AC$2:$AC$1501,'Daily Sale entry '!$X$2:$X$1501,"<="&$A22,'Daily Sale entry '!$Z$2:$Z$1501,"Cheque deposit 支票存入")-SUMPRODUCT(('Daily Sale entry '!$Q$2:$Q$1501="Collection 收款")*('Daily Sale entry '!$R$2:$R$1501="Cheque 支票")*('Daily Sale entry '!$V$2:$V$1501<>"")*('Daily Sale entry '!$V$2:$V$1501<=$A22)*('Daily Sale entry '!$S$2:$S$1501-'Opening Balance'!$B$15*('Daily Sale entry '!$R$2:$R$1501="Cheque 支票")*('Daily Sale entry '!$S$2:$S$1501-TRUNC('Daily Sale entry '!$S$2:$S$1501)))),2)) | E22: =IF($A22="","",'Opening Balance'!$B$7) | F22: =IF($A22="","",ROUND(SUMIFS('Daily Sale entry '!$L$2:$L$367,'Daily Sale entry '!$A$2:$A$367,">="&DATE(YEAR($A22),MONTH($A22),1),'Daily Sale entry '!$A$2:$A$367,"<="&$A22)+SUMIFS('Daily Sale entry '!$M$2:$M$367,'Daily Sale entry '!$A$2:$A$367,">="&DATE(YEAR($A22),MONTH($A22),1),'Daily Sale entry '!$A$2:$A$367,"<="&$A22)+IF(AND(YEAR($A22)=YEAR('Daily Sale entry '!$A$2),MONTH($A22)=MONTH('Daily Sale entry '!$A$2)),'Opening Balance'!$B$8,0),2)) | G22: =IF($A22="","",MOD(ROUND('Opening Balance'!$B$9+SUMIFS('Sales & Collection'!$L$1:$L$283,'Sales & Collection'!$K$1:$K$283,"cash collection*"),2),'Opening Balance'!$B$11)) | H22: =IF($A22="","",ROUND('Opening Balance'!$B$10+'Opening Balance'!$B$9+SUMIFS('Sales & Collection'!$L$1:$L$283,'Sales & Collection'!$K$1:$K$283,"cash collection*")-G22-SUMIFS('Daily Sale entry '!$AC$2:$AC$1501,'Daily Sale entry '!$X$2:$X$1501,"<="&$A22,'Daily Sale entry '!$Z$2:$Z$1501,"Cash deposit 现金存入"),2)) | I22: =IF($A22="","",ROUND(B22+D22+E22+F22+G22+H22,2)) | J22: =IF($A22="","",'AR & AP'!K23) | K22: =IF($A22="","",ROUND(I22-J22-SUMIFS('Daily Sale entry '!$AC$2:$AC$1501,'Daily Sale entry '!$X$2:$X$1501,"<="&$A22,'Daily Sale entry '!$Z$2:$Z$1501,"Other deposit 其他存入")+SUMIFS('Daily Sale entry '!$AD$2:$AD$1501,'Daily Sale entry '!$X$2:$X$1501,"<="&$A22)+('Opening Balance'!$B$8+SUM('Daily Sale entry '!$L$2:M22)-F22),2)) | L22: =IF($A22="","",IF(ABS('Sales & Collection'!$B$292)>'Opening Balance'!$B$16,"ALERT 警报: Different "&TEXT('Sales & Collection'!$B$292,"#,##0.00")&" 差额过大",""))
A23: =IF('Daily Sale entry '!A23="","",'Daily Sale entry '!A23) | B23: =IF($A23="","",ROUND('Opening Balance'!$B$4+SUM('Daily Sale entry '!$K$2:K23)+SUMIFS('Daily Sale entry '!$AC$2:$AC$1501,'Daily Sale entry '!$X$2:$X$1501,"<="&$A23)-SUMIFS('Daily Sale entry '!$AD$2:$AD$1501,'Daily Sale entry '!$X$2:$X$1501,"<="&$A23)+SUMPRODUCT(('Daily Sale entry '!$Q$2:$Q$1501="Collection 收款")*('Daily Sale entry '!$R$2:$R$1501="Cheque 支票")*('Daily Sale entry '!$V$2:$V$1501<>"")*('Daily Sale entry '!$V$2:$V$1501<=$A23)*('Daily Sale entry '!$S$2:$S$1501-'Opening Balance'!$B$15*('Daily Sale entry '!$R$2:$R$1501="Cheque 支票")*('Daily Sale entry '!$S$2:$S$1501-TRUNC('Daily Sale entry '!$S$2:$S$1501))))-'Opening Balance'!$B$15*SUMPRODUCT(('Daily Sale entry '!$X$2:$X$1501<=$A23)*('Daily Sale entry '!$Z$2:$Z$1501="Online collection 网上收款")*('Daily Sale entry '!$AA$2:$AA$1501<>"")*('Daily Sale entry '!$AC$2:$AC$1501-TRUNC('Daily Sale entry '!$AC$2:$AC$1501))),2)) | C23: =IF($A23="","",'Opening Balance'!$B$5+SUM('Daily Sale entry '!$I$2:I23)-SUMIFS('Daily Sale entry '!$AB$2:$AB$1501,'Daily Sale entry '!$X$2:$X$1501,"<="&$A23,'Daily Sale entry '!$Z$2:$Z$1501,"Cheque deposit 支票存入")-COUNTIFS('Daily Sale entry '!$Q$2:$Q$1501,"Collection 收款",'Daily Sale entry '!$R$2:$R$1501,"Cheque 支票",'Daily Sale entry '!$V$2:$V$1501,"<="&$A23)) | D23: =IF($A23="","",ROUND('Opening Balance'!$B$6+SUM('Daily Sale entry '!$J$2:J23)-SUMIFS('Daily Sale entry '!$AC$2:$AC$1501,'Daily Sale entry '!$X$2:$X$1501,"<="&$A23,'Daily Sale entry '!$Z$2:$Z$1501,"Cheque deposit 支票存入")-SUMPRODUCT(('Daily Sale entry '!$Q$2:$Q$1501="Collection 收款")*('Daily Sale entry '!$R$2:$R$1501="Cheque 支票")*('Daily Sale entry '!$V$2:$V$1501<>"")*('Daily Sale entry '!$V$2:$V$1501<=$A23)*('Daily Sale entry '!$S$2:$S$1501-'Opening Balance'!$B$15*('Daily Sale entry '!$R$2:$R$1501="Cheque 支票")*('Daily Sale entry '!$S$2:$S$1501-TRUNC('Daily Sale entry '!$S$2:$S$1501)))),2)) | E23: =IF($A23="","",'Opening Balance'!$B$7) | F23: =IF($A23="","",ROUND(SUMIFS('Daily Sale entry '!$L$2:$L$367,'Daily Sale entry '!$A$2:$A$367,">="&DATE(YEAR($A23),MONTH($A23),1),'Daily Sale entry '!$A$2:$A$367,"<="&$A23)+SUMIFS('Daily Sale entry '!$M$2:$M$367,'Daily Sale entry '!$A$2:$A$367,">="&DATE(YEAR($A23),MONTH($A23),1),'Daily Sale entry '!$A$2:$A$367,"<="&$A23)+IF(AND(YEAR($A23)=YEAR('Daily Sale entry '!$A$2),MONTH($A23)=MONTH('Daily Sale entry '!$A$2)),'Opening Balance'!$B$8,0),2)) | G23: =IF($A23="","",MOD(ROUND('Opening Balance'!$B$9+SUMIFS('Sales & Collection'!$L$1:$L$297,'Sales & Collection'!$K$1:$K$297,"cash collection*"),2),'Opening Balance'!$B$11)) | H23: =IF($A23="","",ROUND('Opening Balance'!$B$10+'Opening Balance'!$B$9+SUMIFS('Sales & Collection'!$L$1:$L$297,'Sales & Collection'!$K$1:$K$297,"cash collection*")-G23-SUMIFS('Daily Sale entry '!$AC$2:$AC$1501,'Daily Sale entry '!$X$2:$X$1501,"<="&$A23,'Daily Sale entry '!$Z$2:$Z$1501,"Cash deposit 现金存入"),2)) | I23: =IF($A23="","",ROUND(B23+D23+E23+F23+G23+H23,2)) | J23: =IF($A23="","",'AR & AP'!K24) | K23: =IF($A23="","",ROUND(I23-J23-SUMIFS('Daily Sale entry '!$AC$2:$AC$1501,'Daily Sale entry '!$X$2:$X$1501,"<="&$A23,'Daily Sale entry '!$Z$2:$Z$1501,"Other deposit 其他存入")+SUMIFS('Daily Sale entry '!$AD$2:$AD$1501,'Daily Sale entry '!$X$2:$X$1501,"<="&$A23)+('Opening Balance'!$B$8+SUM('Daily Sale entry '!$L$2:M23)-F23),2)) | L23: =IF($A23="","",IF(ABS('Sales & Collection'!$B$306)>'Opening Balance'!$B$16,"ALERT 警报: Different "&TEXT('Sales & Collection'!$B$306,"#,##0.00")&" 差额过大",""))
A24: =IF('Daily Sale entry '!A24="","",'Daily Sale entry '!A24) | B24: =IF($A24="","",ROUND('Opening Balance'!$B$4+SUM('Daily Sale entry '!$K$2:K24)+SUMIFS('Daily Sale entry '!$AC$2:$AC$1501,'Daily Sale entry '!$X$2:$X$1501,"<="&$A24)-SUMIFS('Daily Sale entry '!$AD$2:$AD$1501,'Daily Sale entry '!$X$2:$X$1501,"<="&$A24)+SUMPRODUCT(('Daily Sale entry '!$Q$2:$Q$1501="Collection 收款")*('Daily Sale entry '!$R$2:$R$1501="Cheque 支票")*('Daily Sale entry '!$V$2:$V$1501<>"")*('Daily Sale entry '!$V$2:$V$1501<=$A24)*('Daily Sale entry '!$S$2:$S$1501-'Opening Balance'!$B$15*('Daily Sale entry '!$R$2:$R$1501="Cheque 支票")*('Daily Sale entry '!$S$2:$S$1501-TRUNC('Daily Sale entry '!$S$2:$S$1501))))-'Opening Balance'!$B$15*SUMPRODUCT(('Daily Sale entry '!$X$2:$X$1501<=$A24)*('Daily Sale entry '!$Z$2:$Z$1501="Online collection 网上收款")*('Daily Sale entry '!$AA$2:$AA$1501<>"")*('Daily Sale entry '!$AC$2:$AC$1501-TRUNC('Daily Sale entry '!$AC$2:$AC$1501))),2)) | C24: =IF($A24="","",'Opening Balance'!$B$5+SUM('Daily Sale entry '!$I$2:I24)-SUMIFS('Daily Sale entry '!$AB$2:$AB$1501,'Daily Sale entry '!$X$2:$X$1501,"<="&$A24,'Daily Sale entry '!$Z$2:$Z$1501,"Cheque deposit 支票存入")-COUNTIFS('Daily Sale entry '!$Q$2:$Q$1501,"Collection 收款",'Daily Sale entry '!$R$2:$R$1501,"Cheque 支票",'Daily Sale entry '!$V$2:$V$1501,"<="&$A24)) | D24: =IF($A24="","",ROUND('Opening Balance'!$B$6+SUM('Daily Sale entry '!$J$2:J24)-SUMIFS('Daily Sale entry '!$AC$2:$AC$1501,'Daily Sale entry '!$X$2:$X$1501,"<="&$A24,'Daily Sale entry '!$Z$2:$Z$1501,"Cheque deposit 支票存入")-SUMPRODUCT(('Daily Sale entry '!$Q$2:$Q$1501="Collection 收款")*('Daily Sale entry '!$R$2:$R$1501="Cheque 支票")*('Daily Sale entry '!$V$2:$V$1501<>"")*('Daily Sale entry '!$V$2:$V$1501<=$A24)*('Daily Sale entry '!$S$2:$S$1501-'Opening Balance'!$B$15*('Daily Sale entry '!$R$2:$R$1501="Cheque 支票")*('Daily Sale entry '!$S$2:$S$1501-TRUNC('Daily Sale entry '!$S$2:$S$1501)))),2)) | E24: =IF($A24="","",'Opening Balance'!$B$7) | F24: =IF($A24="","",ROUND(SUMIFS('Daily Sale entry '!$L$2:$L$367,'Daily Sale entry '!$A$2:$A$367,">="&DATE(YEAR($A24),MONTH($A24),1),'Daily Sale entry '!$A$2:$A$367,"<="&$A24)+SUMIFS('Daily Sale entry '!$M$2:$M$367,'Daily Sale entry '!$A$2:$A$367,">="&DATE(YEAR($A24),MONTH($A24),1),'Daily Sale entry '!$A$2:$A$367,"<="&$A24)+IF(AND(YEAR($A24)=YEAR('Daily Sale entry '!$A$2),MONTH($A24)=MONTH('Daily Sale entry '!$A$2)),'Opening Balance'!$B$8,0),2)) | G24: =IF($A24="","",MOD(ROUND('Opening Balance'!$B$9+SUMIFS('Sales & Collection'!$L$1:$L$311,'Sales & Collection'!$K$1:$K$311,"cash collection*"),2),'Opening Balance'!$B$11)) | H24: =IF($A24="","",ROUND('Opening Balance'!$B$10+'Opening Balance'!$B$9+SUMIFS('Sales & Collection'!$L$1:$L$311,'Sales & Collection'!$K$1:$K$311,"cash collection*")-G24-SUMIFS('Daily Sale entry '!$AC$2:$AC$1501,'Daily Sale entry '!$X$2:$X$1501,"<="&$A24,'Daily Sale entry '!$Z$2:$Z$1501,"Cash deposit 现金存入"),2)) | I24: =IF($A24="","",ROUND(B24+D24+E24+F24+G24+H24,2)) | J24: =IF($A24="","",'AR & AP'!K25) | K24: =IF($A24="","",ROUND(I24-J24-SUMIFS('Daily Sale entry '!$AC$2:$AC$1501,'Daily Sale entry '!$X$2:$X$1501,"<="&$A24,'Daily Sale entry '!$Z$2:$Z$1501,"Other deposit 其他存入")+SUMIFS('Daily Sale entry '!$AD$2:$AD$1501,'Daily Sale entry '!$X$2:$X$1501,"<="&$A24)+('Opening Balance'!$B$8+SUM('Daily Sale entry '!$L$2:M24)-F24),2)) | L24: =IF($A24="","",IF(ABS('Sales & Collection'!$B$320)>'Opening Balance'!$B$16,"ALERT 警报: Different "&TEXT('Sales & Collection'!$B$320,"#,##0.00")&" 差额过大",""))
A25: =IF('Daily Sale entry '!A25="","",'Daily Sale entry '!A25) | B25: =IF($A25="","",ROUND('Opening Balance'!$B$4+SUM('Daily Sale entry '!$K$2:K25)+SUMIFS('Daily Sale entry '!$AC$2:$AC$1501,'Daily Sale entry '!$X$2:$X$1501,"<="&$A25)-SUMIFS('Daily Sale entry '!$AD$2:$AD$1501,'Daily Sale entry '!$X$2:$X$1501,"<="&$A25)+SUMPRODUCT(('Daily Sale entry '!$Q$2:$Q$1501="Collection 收款")*('Daily Sale entry '!$R$2:$R$1501="Cheque 支票")*('Daily Sale entry '!$V$2:$V$1501<>"")*('Daily Sale entry '!$V$2:$V$1501<=$A25)*('Daily Sale entry '!$S$2:$S$1501-'Opening Balance'!$B$15*('Daily Sale entry '!$R$2:$R$1501="Cheque 支票")*('Daily Sale entry '!$S$2:$S$1501-TRUNC('Daily Sale entry '!$S$2:$S$1501))))-'Opening Balance'!$B$15*SUMPRODUCT(('Daily Sale entry '!$X$2:$X$1501<=$A25)*('Daily Sale entry '!$Z$2:$Z$1501="Online collection 网上收款")*('Daily Sale entry '!$AA$2:$AA$1501<>"")*('Daily Sale entry '!$AC$2:$AC$1501-TRUNC('Daily Sale entry '!$AC$2:$AC$1501))),2)) | C25: =IF($A25="","",'Opening Balance'!$B$5+SUM('Daily Sale entry '!$I$2:I25)-SUMIFS('Daily Sale entry '!$AB$2:$AB$1501,'Daily Sale entry '!$X$2:$X$1501,"<="&$A25,'Daily Sale entry '!$Z$2:$Z$1501,"Cheque deposit 支票存入")-COUNTIFS('Daily Sale entry '!$Q$2:$Q$1501,"Collection 收款",'Daily Sale entry '!$R$2:$R$1501,"Cheque 支票",'Daily Sale entry '!$V$2:$V$1501,"<="&$A25)) | D25: =IF($A25="","",ROUND('Opening Balance'!$B$6+SUM('Daily Sale entry '!$J$2:J25)-SUMIFS('Daily Sale entry '!$AC$2:$AC$1501,'Daily Sale entry '!$X$2:$X$1501,"<="&$A25,'Daily Sale entry '!$Z$2:$Z$1501,"Cheque deposit 支票存入")-SUMPRODUCT(('Daily Sale entry '!$Q$2:$Q$1501="Collection 收款")*('Daily Sale entry '!$R$2:$R$1501="Cheque 支票")*('Daily Sale entry '!$V$2:$V$1501<>"")*('Daily Sale entry '!$V$2:$V$1501<=$A25)*('Daily Sale entry '!$S$2:$S$1501-'Opening Balance'!$B$15*('Daily Sale entry '!$R$2:$R$1501="Cheque 支票")*('Daily Sale entry '!$S$2:$S$1501-TRUNC('Daily Sale entry '!$S$2:$S$1501)))),2)) | E25: =IF($A25="","",'Opening Balance'!$B$7) | F25: =IF($A25="","",ROUND(SUMIFS('Daily Sale entry '!$L$2:$L$367,'Daily Sale entry '!$A$2:$A$367,">="&DATE(YEAR($A25),MONTH($A25),1),'Daily Sale entry '!$A$2:$A$367,"<="&$A25)+SUMIFS('Daily Sale entry '!$M$2:$M$367,'Daily Sale entry '!$A$2:$A$367,">="&DATE(YEAR($A25),MONTH($A25),1),'Daily Sale entry '!$A$2:$A$367,"<="&$A25)+IF(AND(YEAR($A25)=YEAR('Daily Sale entry '!$A$2),MONTH($A25)=MONTH('Daily Sale entry '!$A$2)),'Opening Balance'!$B$8,0),2)) | G25: =IF($A25="","",MOD(ROUND('Opening Balance'!$B$9+SUMIFS('Sales & Collection'!$L$1:$L$325,'Sales & Collection'!$K$1:$K$325,"cash collection*"),2),'Opening Balance'!$B$11)) | H25: =IF($A25="","",ROUND('Opening Balance'!$B$10+'Opening Balance'!$B$9+SUMIFS('Sales & Collection'!$L$1:$L$325,'Sales & Collection'!$K$1:$K$325,"cash collection*")-G25-SUMIFS('Daily Sale entry '!$AC$2:$AC$1501,'Daily Sale entry '!$X$2:$X$1501,"<="&$A25,'Daily Sale entry '!$Z$2:$Z$1501,"Cash deposit 现金存入"),2)) | I25: =IF($A25="","",ROUND(B25+D25+E25+F25+G25+H25,2)) | J25: =IF($A25="","",'AR & AP'!K26) | K25: =IF($A25="","",ROUND(I25-J25-SUMIFS('Daily Sale entry '!$AC$2:$AC$1501,'Daily Sale entry '!$X$2:$X$1501,"<="&$A25,'Daily Sale entry '!$Z$2:$Z$1501,"Other deposit 其他存入")+SUMIFS('Daily Sale entry '!$AD$2:$AD$1501,'Daily Sale entry '!$X$2:$X$1501,"<="&$A25)+('Opening Balance'!$B$8+SUM('Daily Sale entry '!$L$2:M25)-F25),2)) | L25: =IF($A25="","",IF(ABS('Sales & Collection'!$B$334)>'Opening Balance'!$B$16,"ALERT 警报: Different "&TEXT('Sales & Collection'!$B$334,"#,##0.00")&" 差额过大",""))
A26: =IF('Daily Sale entry '!A26="","",'Daily Sale entry '!A26) | B26: =IF($A26="","",ROUND('Opening Balance'!$B$4+SUM('Daily Sale entry '!$K$2:K26)+SUMIFS('Daily Sale entry '!$AC$2:$AC$1501,'Daily Sale entry '!$X$2:$X$1501,"<="&$A26)-SUMIFS('Daily Sale entry '!$AD$2:$AD$1501,'Daily Sale entry '!$X$2:$X$1501,"<="&$A26)+SUMPRODUCT(('Daily Sale entry '!$Q$2:$Q$1501="Collection 收款")*('Daily Sale entry '!$R$2:$R$1501="Cheque 支票")*('Daily Sale entry '!$V$2:$V$1501<>"")*('Daily Sale entry '!$V$2:$V$1501<=$A26)*('Daily Sale entry '!$S$2:$S$1501-'Opening Balance'!$B$15*('Daily Sale entry '!$R$2:$R$1501="Cheque 支票")*('Daily Sale entry '!$S$2:$S$1501-TRUNC('Daily Sale entry '!$S$2:$S$1501))))-'Opening Balance'!$B$15*SUMPRODUCT(('Daily Sale entry '!$X$2:$X$1501<=$A26)*('Daily Sale entry '!$Z$2:$Z$1501="Online collection 网上收款")*('Daily Sale entry '!$AA$2:$AA$1501<>"")*('Daily Sale entry '!$AC$2:$AC$1501-TRUNC('Daily Sale entry '!$AC$2:$AC$1501))),2)) | C26: =IF($A26="","",'Opening Balance'!$B$5+SUM('Daily Sale entry '!$I$2:I26)-SUMIFS('Daily Sale entry '!$AB$2:$AB$1501,'Daily Sale entry '!$X$2:$X$1501,"<="&$A26,'Daily Sale entry '!$Z$2:$Z$1501,"Cheque deposit 支票存入")-COUNTIFS('Daily Sale entry '!$Q$2:$Q$1501,"Collection 收款",'Daily Sale entry '!$R$2:$R$1501,"Cheque 支票",'Daily Sale entry '!$V$2:$V$1501,"<="&$A26)) | D26: =IF($A26="","",ROUND('Opening Balance'!$B$6+SUM('Daily Sale entry '!$J$2:J26)-SUMIFS('Daily Sale entry '!$AC$2:$AC$1501,'Daily Sale entry '!$X$2:$X$1501,"<="&$A26,'Daily Sale entry '!$Z$2:$Z$1501,"Cheque deposit 支票存入")-SUMPRODUCT(('Daily Sale entry '!$Q$2:$Q$1501="Collection 收款")*('Daily Sale entry '!$R$2:$R$1501="Cheque 支票")*('Daily Sale entry '!$V$2:$V$1501<>"")*('Daily Sale entry '!$V$2:$V$1501<=$A26)*('Daily Sale entry '!$S$2:$S$1501-'Opening Balance'!$B$15*('Daily Sale entry '!$R$2:$R$1501="Cheque 支票")*('Daily Sale entry '!$S$2:$S$1501-TRUNC('Daily Sale entry '!$S$2:$S$1501)))),2)) | E26: =IF($A26="","",'Opening Balance'!$B$7) | F26: =IF($A26="","",ROUND(SUMIFS('Daily Sale entry '!$L$2:$L$367,'Daily Sale entry '!$A$2:$A$367,">="&DATE(YEAR($A26),MONTH($A26),1),'Daily Sale entry '!$A$2:$A$367,"<="&$A26)+SUMIFS('Daily Sale entry '!$M$2:$M$367,'Daily Sale entry '!$A$2:$A$367,">="&DATE(YEAR($A26),MONTH($A26),1),'Daily Sale entry '!$A$2:$A$367,"<="&$A26)+IF(AND(YEAR($A26)=YEAR('Daily Sale entry '!$A$2),MONTH($A26)=MONTH('Daily Sale entry '!$A$2)),'Opening Balance'!$B$8,0),2)) | G26: =IF($A26="","",MOD(ROUND('Opening Balance'!$B$9+SUMIFS('Sales & Collection'!$L$1:$L$339,'Sales & Collection'!$K$1:$K$339,"cash collection*"),2),'Opening Balance'!$B$11)) | H26: =IF($A26="","",ROUND('Opening Balance'!$B$10+'Opening Balance'!$B$9+SUMIFS('Sales & Collection'!$L$1:$L$339,'Sales & Collection'!$K$1:$K$339,"cash collection*")-G26-SUMIFS('Daily Sale entry '!$AC$2:$AC$1501,'Daily Sale entry '!$X$2:$X$1501,"<="&$A26,'Daily Sale entry '!$Z$2:$Z$1501,"Cash deposit 现金存入"),2)) | I26: =IF($A26="","",ROUND(B26+D26+E26+F26+G26+H26,2)) | J26: =IF($A26="","",'AR & AP'!K27) | K26: =IF($A26="","",ROUND(I26-J26-SUMIFS('Daily Sale entry '!$AC$2:$AC$1501,'Daily Sale entry '!$X$2:$X$1501,"<="&$A26,'Daily Sale entry '!$Z$2:$Z$1501,"Other deposit 其他存入")+SUMIFS('Daily Sale entry '!$AD$2:$AD$1501,'Daily Sale entry '!$X$2:$X$1501,"<="&$A26)+('Opening Balance'!$B$8+SUM('Daily Sale entry '!$L$2:M26)-F26),2)) | L26: =IF($A26="","",IF(ABS('Sales & Collection'!$B$348)>'Opening Balance'!$B$16,"ALERT 警报: Different "&TEXT('Sales & Collection'!$B$348,"#,##0.00")&" 差额过大",""))
A27: =IF('Daily Sale entry '!A27="","",'Daily Sale entry '!A27) | B27: =IF($A27="","",ROUND('Opening Balance'!$B$4+SUM('Daily Sale entry '!$K$2:K27)+SUMIFS('Daily Sale entry '!$AC$2:$AC$1501,'Daily Sale entry '!$X$2:$X$1501,"<="&$A27)-SUMIFS('Daily Sale entry '!$AD$2:$AD$1501,'Daily Sale entry '!$X$2:$X$1501,"<="&$A27)+SUMPRODUCT(('Daily Sale entry '!$Q$2:$Q$1501="Collection 收款")*('Daily Sale entry '!$R$2:$R$1501="Cheque 支票")*('Daily Sale entry '!$V$2:$V$1501<>"")*('Daily Sale entry '!$V$2:$V$1501<=$A27)*('Daily Sale entry '!$S$2:$S$1501-'Opening Balance'!$B$15*('Daily Sale entry '!$R$2:$R$1501="Cheque 支票")*('Daily Sale entry '!$S$2:$S$1501-TRUNC('Daily Sale entry '!$S$2:$S$1501))))-'Opening Balance'!$B$15*SUMPRODUCT(('Daily Sale entry '!$X$2:$X$1501<=$A27)*('Daily Sale entry '!$Z$2:$Z$1501="Online collection 网上收款")*('Daily Sale entry '!$AA$2:$AA$1501<>"")*('Daily Sale entry '!$AC$2:$AC$1501-TRUNC('Daily Sale entry '!$AC$2:$AC$1501))),2)) | C27: =IF($A27="","",'Opening Balance'!$B$5+SUM('Daily Sale entry '!$I$2:I27)-SUMIFS('Daily Sale entry '!$AB$2:$AB$1501,'Daily Sale entry '!$X$2:$X$1501,"<="&$A27,'Daily Sale entry '!$Z$2:$Z$1501,"Cheque deposit 支票存入")-COUNTIFS('Daily Sale entry '!$Q$2:$Q$1501,"Collection 收款",'Daily Sale entry '!$R$2:$R$1501,"Cheque 支票",'Daily Sale entry '!$V$2:$V$1501,"<="&$A27)) | D27: =IF($A27="","",ROUND('Opening Balance'!$B$6+SUM('Daily Sale entry '!$J$2:J27)-SUMIFS('Daily Sale entry '!$AC$2:$AC$1501,'Daily Sale entry '!$X$2:$X$1501,"<="&$A27,'Daily Sale entry '!$Z$2:$Z$1501,"Cheque deposit 支票存入")-SUMPRODUCT(('Daily Sale entry '!$Q$2:$Q$1501="Collection 收款")*('Daily Sale entry '!$R$2:$R$1501="Cheque 支票")*('Daily Sale entry '!$V$2:$V$1501<>"")*('Daily Sale entry '!$V$2:$V$1501<=$A27)*('Daily Sale entry '!$S$2:$S$1501-'Opening Balance'!$B$15*('Daily Sale entry '!$R$2:$R$1501="Cheque 支票")*('Daily Sale entry '!$S$2:$S$1501-TRUNC('Daily Sale entry '!$S$2:$S$1501)))),2)) | E27: =IF($A27="","",'Opening Balance'!$B$7) | F27: =IF($A27="","",ROUND(SUMIFS('Daily Sale entry '!$L$2:$L$367,'Daily Sale entry '!$A$2:$A$367,">="&DATE(YEAR($A27),MONTH($A27),1),'Daily Sale entry '!$A$2:$A$367,"<="&$A27)+SUMIFS('Daily Sale entry '!$M$2:$M$367,'Daily Sale entry '!$A$2:$A$367,">="&DATE(YEAR($A27),MONTH($A27),1),'Daily Sale entry '!$A$2:$A$367,"<="&$A27)+IF(AND(YEAR($A27)=YEAR('Daily Sale entry '!$A$2),MONTH($A27)=MONTH('Daily Sale entry '!$A$2)),'Opening Balance'!$B$8,0),2)) | G27: =IF($A27="","",MOD(ROUND('Opening Balance'!$B$9+SUMIFS('Sales & Collection'!$L$1:$L$353,'Sales & Collection'!$K$1:$K$353,"cash collection*"),2),'Opening Balance'!$B$11)) | H27: =IF($A27="","",ROUND('Opening Balance'!$B$10+'Opening Balance'!$B$9+SUMIFS('Sales & Collection'!$L$1:$L$353,'Sales & Collection'!$K$1:$K$353,"cash collection*")-G27-SUMIFS('Daily Sale entry '!$AC$2:$AC$1501,'Daily Sale entry '!$X$2:$X$1501,"<="&$A27,'Daily Sale entry '!$Z$2:$Z$1501,"Cash deposit 现金存入"),2)) | I27: =IF($A27="","",ROUND(B27+D27+E27+F27+G27+H27,2)) | J27: =IF($A27="","",'AR & AP'!K28) | K27: =IF($A27="","",ROUND(I27-J27-SUMIFS('Daily Sale entry '!$AC$2:$AC$1501,'Daily Sale entry '!$X$2:$X$1501,"<="&$A27,'Daily Sale entry '!$Z$2:$Z$1501,"Other deposit 其他存入")+SUMIFS('Daily Sale entry '!$AD$2:$AD$1501,'Daily Sale entry '!$X$2:$X$1501,"<="&$A27)+('Opening Balance'!$B$8+SUM('Daily Sale entry '!$L$2:M27)-F27),2)) | L27: =IF($A27="","",IF(ABS('Sales & Collection'!$B$362)>'Opening Balance'!$B$16,"ALERT 警报: Different "&TEXT('Sales & Collection'!$B$362,"#,##0.00")&" 差额过大",""))
A28: =IF('Daily Sale entry '!A28="","",'Daily Sale entry '!A28) | B28: =IF($A28="","",ROUND('Opening Balance'!$B$4+SUM('Daily Sale entry '!$K$2:K28)+SUMIFS('Daily Sale entry '!$AC$2:$AC$1501,'Daily Sale entry '!$X$2:$X$1501,"<="&$A28)-SUMIFS('Daily Sale entry '!$AD$2:$AD$1501,'Daily Sale entry '!$X$2:$X$1501,"<="&$A28)+SUMPRODUCT(('Daily Sale entry '!$Q$2:$Q$1501="Collection 收款")*('Daily Sale entry '!$R$2:$R$1501="Cheque 支票")*('Daily Sale entry '!$V$2:$V$1501<>"")*('Daily Sale entry '!$V$2:$V$1501<=$A28)*('Daily Sale entry '!$S$2:$S$1501-'Opening Balance'!$B$15*('Daily Sale entry '!$R$2:$R$1501="Cheque 支票")*('Daily Sale entry '!$S$2:$S$1501-TRUNC('Daily Sale entry '!$S$2:$S$1501))))-'Opening Balance'!$B$15*SUMPRODUCT(('Daily Sale entry '!$X$2:$X$1501<=$A28)*('Daily Sale entry '!$Z$2:$Z$1501="Online collection 网上收款")*('Daily Sale entry '!$AA$2:$AA$1501<>"")*('Daily Sale entry '!$AC$2:$AC$1501-TRUNC('Daily Sale entry '!$AC$2:$AC$1501))),2)) | C28: =IF($A28="","",'Opening Balance'!$B$5+SUM('Daily Sale entry '!$I$2:I28)-SUMIFS('Daily Sale entry '!$AB$2:$AB$1501,'Daily Sale entry '!$X$2:$X$1501,"<="&$A28,'Daily Sale entry '!$Z$2:$Z$1501,"Cheque deposit 支票存入")-COUNTIFS('Daily Sale entry '!$Q$2:$Q$1501,"Collection 收款",'Daily Sale entry '!$R$2:$R$1501,"Cheque 支票",'Daily Sale entry '!$V$2:$V$1501,"<="&$A28)) | D28: =IF($A28="","",ROUND('Opening Balance'!$B$6+SUM('Daily Sale entry '!$J$2:J28)-SUMIFS('Daily Sale entry '!$AC$2:$AC$1501,'Daily Sale entry '!$X$2:$X$1501,"<="&$A28,'Daily Sale entry '!$Z$2:$Z$1501,"Cheque deposit 支票存入")-SUMPRODUCT(('Daily Sale entry '!$Q$2:$Q$1501="Collection 收款")*('Daily Sale entry '!$R$2:$R$1501="Cheque 支票")*('Daily Sale entry '!$V$2:$V$1501<>"")*('Daily Sale entry '!$V$2:$V$1501<=$A28)*('Daily Sale entry '!$S$2:$S$1501-'Opening Balance'!$B$15*('Daily Sale entry '!$R$2:$R$1501="Cheque 支票")*('Daily Sale entry '!$S$2:$S$1501-TRUNC('Daily Sale entry '!$S$2:$S$1501)))),2)) | E28: =IF($A28="","",'Opening Balance'!$B$7) | F28: =IF($A28="","",ROUND(SUMIFS('Daily Sale entry '!$L$2:$L$367,'Daily Sale entry '!$A$2:$A$367,">="&DATE(YEAR($A28),MONTH($A28),1),'Daily Sale entry '!$A$2:$A$367,"<="&$A28)+SUMIFS('Daily Sale entry '!$M$2:$M$367,'Daily Sale entry '!$A$2:$A$367,">="&DATE(YEAR($A28),MONTH($A28),1),'Daily Sale entry '!$A$2:$A$367,"<="&$A28)+IF(AND(YEAR($A28)=YEAR('Daily Sale entry '!$A$2),MONTH($A28)=MONTH('Daily Sale entry '!$A$2)),'Opening Balance'!$B$8,0),2)) | G28: =IF($A28="","",MOD(ROUND('Opening Balance'!$B$9+SUMIFS('Sales & Collection'!$L$1:$L$367,'Sales & Collection'!$K$1:$K$367,"cash collection*"),2),'Opening Balance'!$B$11)) | H28: =IF($A28="","",ROUND('Opening Balance'!$B$10+'Opening Balance'!$B$9+SUMIFS('Sales & Collection'!$L$1:$L$367,'Sales & Collection'!$K$1:$K$367,"cash collection*")-G28-SUMIFS('Daily Sale entry '!$AC$2:$AC$1501,'Daily Sale entry '!$X$2:$X$1501,"<="&$A28,'Daily Sale entry '!$Z$2:$Z$1501,"Cash deposit 现金存入"),2)) | I28: =IF($A28="","",ROUND(B28+D28+E28+F28+G28+H28,2)) | J28: =IF($A28="","",'AR & AP'!K29) | K28: =IF($A28="","",ROUND(I28-J28-SUMIFS('Daily Sale entry '!$AC$2:$AC$1501,'Daily Sale entry '!$X$2:$X$1501,"<="&$A28,'Daily Sale entry '!$Z$2:$Z$1501,"Other deposit 其他存入")+SUMIFS('Daily Sale entry '!$AD$2:$AD$1501,'Daily Sale entry '!$X$2:$X$1501,"<="&$A28)+('Opening Balance'!$B$8+SUM('Daily Sale entry '!$L$2:M28)-F28),2)) | L28: =IF($A28="","",IF(ABS('Sales & Collection'!$B$376)>'Opening Balance'!$B$16,"ALERT 警报: Different "&TEXT('Sales & Collection'!$B$376,"#,##0.00")&" 差额过大",""))
A29: =IF('Daily Sale entry '!A29="","",'Daily Sale entry '!A29) | B29: =IF($A29="","",ROUND('Opening Balance'!$B$4+SUM('Daily Sale entry '!$K$2:K29)+SUMIFS('Daily Sale entry '!$AC$2:$AC$1501,'Daily Sale entry '!$X$2:$X$1501,"<="&$A29)-SUMIFS('Daily Sale entry '!$AD$2:$AD$1501,'Daily Sale entry '!$X$2:$X$1501,"<="&$A29)+SUMPRODUCT(('Daily Sale entry '!$Q$2:$Q$1501="Collection 收款")*('Daily Sale entry '!$R$2:$R$1501="Cheque 支票")*('Daily Sale entry '!$V$2:$V$1501<>"")*('Daily Sale entry '!$V$2:$V$1501<=$A29)*('Daily Sale entry '!$S$2:$S$1501-'Opening Balance'!$B$15*('Daily Sale entry '!$R$2:$R$1501="Cheque 支票")*('Daily Sale entry '!$S$2:$S$1501-TRUNC('Daily Sale entry '!$S$2:$S$1501))))-'Opening Balance'!$B$15*SUMPRODUCT(('Daily Sale entry '!$X$2:$X$1501<=$A29)*('Daily Sale entry '!$Z$2:$Z$1501="Online collection 网上收款")*('Daily Sale entry '!$AA$2:$AA$1501<>"")*('Daily Sale entry '!$AC$2:$AC$1501-TRUNC('Daily Sale entry '!$AC$2:$AC$1501))),2)) | C29: =IF($A29="","",'Opening Balance'!$B$5+SUM('Daily Sale entry '!$I$2:I29)-SUMIFS('Daily Sale entry '!$AB$2:$AB$1501,'Daily Sale entry '!$X$2:$X$1501,"<="&$A29,'Daily Sale entry '!$Z$2:$Z$1501,"Cheque deposit 支票存入")-COUNTIFS('Daily Sale entry '!$Q$2:$Q$1501,"Collection 收款",'Daily Sale entry '!$R$2:$R$1501,"Cheque 支票",'Daily Sale entry '!$V$2:$V$1501,"<="&$A29)) | D29: =IF($A29="","",ROUND('Opening Balance'!$B$6+SUM('Daily Sale entry '!$J$2:J29)-SUMIFS('Daily Sale entry '!$AC$2:$AC$1501,'Daily Sale entry '!$X$2:$X$1501,"<="&$A29,'Daily Sale entry '!$Z$2:$Z$1501,"Cheque deposit 支票存入")-SUMPRODUCT(('Daily Sale entry '!$Q$2:$Q$1501="Collection 收款")*('Daily Sale entry '!$R$2:$R$1501="Cheque 支票")*('Daily Sale entry '!$V$2:$V$1501<>"")*('Daily Sale entry '!$V$2:$V$1501<=$A29)*('Daily Sale entry '!$S$2:$S$1501-'Opening Balance'!$B$15*('Daily Sale entry '!$R$2:$R$1501="Cheque 支票")*('Daily Sale entry '!$S$2:$S$1501-TRUNC('Daily Sale entry '!$S$2:$S$1501)))),2)) | E29: =IF($A29="","",'Opening Balance'!$B$7) | F29: =IF($A29="","",ROUND(SUMIFS('Daily Sale entry '!$L$2:$L$367,'Daily Sale entry '!$A$2:$A$367,">="&DATE(YEAR($A29),MONTH($A29),1),'Daily Sale entry '!$A$2:$A$367,"<="&$A29)+SUMIFS('Daily Sale entry '!$M$2:$M$367,'Daily Sale entry '!$A$2:$A$367,">="&DATE(YEAR($A29),MONTH($A29),1),'Daily Sale entry '!$A$2:$A$367,"<="&$A29)+IF(AND(YEAR($A29)=YEAR('Daily Sale entry '!$A$2),MONTH($A29)=MONTH('Daily Sale entry '!$A$2)),'Opening Balance'!$B$8,0),2)) | G29: =IF($A29="","",MOD(ROUND('Opening Balance'!$B$9+SUMIFS('Sales & Collection'!$L$1:$L$381,'Sales & Collection'!$K$1:$K$381,"cash collection*"),2),'Opening Balance'!$B$11)) | H29: =IF($A29="","",ROUND('Opening Balance'!$B$10+'Opening Balance'!$B$9+SUMIFS('Sales & Collection'!$L$1:$L$381,'Sales & Collection'!$K$1:$K$381,"cash collection*")-G29-SUMIFS('Daily Sale entry '!$AC$2:$AC$1501,'Daily Sale entry '!$X$2:$X$1501,"<="&$A29,'Daily Sale entry '!$Z$2:$Z$1501,"Cash deposit 现金存入"),2)) | I29: =IF($A29="","",ROUND(B29+D29+E29+F29+G29+H29,2)) | J29: =IF($A29="","",'AR & AP'!K30) | K29: =IF($A29="","",ROUND(I29-J29-SUMIFS('Daily Sale entry '!$AC$2:$AC$1501,'Daily Sale entry '!$X$2:$X$1501,"<="&$A29,'Daily Sale entry '!$Z$2:$Z$1501,"Other deposit 其他存入")+SUMIFS('Daily Sale entry '!$AD$2:$AD$1501,'Daily Sale entry '!$X$2:$X$1501,"<="&$A29)+('Opening Balance'!$B$8+SUM('Daily Sale entry '!$L$2:M29)-F29),2)) | L29: =IF($A29="","",IF(ABS('Sales & Collection'!$B$390)>'Opening Balance'!$B$16,"ALERT 警报: Different "&TEXT('Sales & Collection'!$B$390,"#,##0.00")&" 差额过大",""))
A30: =IF('Daily Sale entry '!A30="","",'Daily Sale entry '!A30) | B30: =IF($A30="","",ROUND('Opening Balance'!$B$4+SUM('Daily Sale entry '!$K$2:K30)+SUMIFS('Daily Sale entry '!$AC$2:$AC$1501,'Daily Sale entry '!$X$2:$X$1501,"<="&$A30)-SUMIFS('Daily Sale entry '!$AD$2:$AD$1501,'Daily Sale entry '!$X$2:$X$1501,"<="&$A30)+SUMPRODUCT(('Daily Sale entry '!$Q$2:$Q$1501="Collection 收款")*('Daily Sale entry '!$R$2:$R$1501="Cheque 支票")*('Daily Sale entry '!$V$2:$V$1501<>"")*('Daily Sale entry '!$V$2:$V$1501<=$A30)*('Daily Sale entry '!$S$2:$S$1501-'Opening Balance'!$B$15*('Daily Sale entry '!$R$2:$R$1501="Cheque 支票")*('Daily Sale entry '!$S$2:$S$1501-TRUNC('Daily Sale entry '!$S$2:$S$1501))))-'Opening Balance'!$B$15*SUMPRODUCT(('Daily Sale entry '!$X$2:$X$1501<=$A30)*('Daily Sale entry '!$Z$2:$Z$1501="Online collection 网上收款")*('Daily Sale entry '!$AA$2:$AA$1501<>"")*('Daily Sale entry '!$AC$2:$AC$1501-TRUNC('Daily Sale entry '!$AC$2:$AC$1501))),2)) | C30: =IF($A30="","",'Opening Balance'!$B$5+SUM('Daily Sale entry '!$I$2:I30)-SUMIFS('Daily Sale entry '!$AB$2:$AB$1501,'Daily Sale entry '!$X$2:$X$1501,"<="&$A30,'Daily Sale entry '!$Z$2:$Z$1501,"Cheque deposit 支票存入")-COUNTIFS('Daily Sale entry '!$Q$2:$Q$1501,"Collection 收款",'Daily Sale entry '!$R$2:$R$1501,"Cheque 支票",'Daily Sale entry '!$V$2:$V$1501,"<="&$A30)) | D30: =IF($A30="","",ROUND('Opening Balance'!$B$6+SUM('Daily Sale entry '!$J$2:J30)-SUMIFS('Daily Sale entry '!$AC$2:$AC$1501,'Daily Sale entry '!$X$2:$X$1501,"<="&$A30,'Daily Sale entry '!$Z$2:$Z$1501,"Cheque deposit 支票存入")-SUMPRODUCT(('Daily Sale entry '!$Q$2:$Q$1501="Collection 收款")*('Daily Sale entry '!$R$2:$R$1501="Cheque 支票")*('Daily Sale entry '!$V$2:$V$1501<>"")*('Daily Sale entry '!$V$2:$V$1501<=$A30)*('Daily Sale entry '!$S$2:$S$1501-'Opening Balance'!$B$15*('Daily Sale entry '!$R$2:$R$1501="Cheque 支票")*('Daily Sale entry '!$S$2:$S$1501-TRUNC('Daily Sale entry '!$S$2:$S$1501)))),2)) | E30: =IF($A30="","",'Opening Balance'!$B$7) | F30: =IF($A30="","",ROUND(SUMIFS('Daily Sale entry '!$L$2:$L$367,'Daily Sale entry '!$A$2:$A$367,">="&DATE(YEAR($A30),MONTH($A30),1),'Daily Sale entry '!$A$2:$A$367,"<="&$A30)+SUMIFS('Daily Sale entry '!$M$2:$M$367,'Daily Sale entry '!$A$2:$A$367,">="&DATE(YEAR($A30),MONTH($A30),1),'Daily Sale entry '!$A$2:$A$367,"<="&$A30)+IF(AND(YEAR($A30)=YEAR('Daily Sale entry '!$A$2),MONTH($A30)=MONTH('Daily Sale entry '!$A$2)),'Opening Balance'!$B$8,0),2)) | G30: =IF($A30="","",MOD(ROUND('Opening Balance'!$B$9+SUMIFS('Sales & Collection'!$L$1:$L$395,'Sales & Collection'!$K$1:$K$395,"cash collection*"),2),'Opening Balance'!$B$11)) | H30: =IF($A30="","",ROUND('Opening Balance'!$B$10+'Opening Balance'!$B$9+SUMIFS('Sales & Collection'!$L$1:$L$395,'Sales & Collection'!$K$1:$K$395,"cash collection*")-G30-SUMIFS('Daily Sale entry '!$AC$2:$AC$1501,'Daily Sale entry '!$X$2:$X$1501,"<="&$A30,'Daily Sale entry '!$Z$2:$Z$1501,"Cash deposit 现金存入"),2)) | I30: =IF($A30="","",ROUND(B30+D30+E30+F30+G30+H30,2)) | J30: =IF($A30="","",'AR & AP'!K31) | K30: =IF($A30="","",ROUND(I30-J30-SUMIFS('Daily Sale entry '!$AC$2:$AC$1501,'Daily Sale entry '!$X$2:$X$1501,"<="&$A30,'Daily Sale entry '!$Z$2:$Z$1501,"Other deposit 其他存入")+SUMIFS('Daily Sale entry '!$AD$2:$AD$1501,'Daily Sale entry '!$X$2:$X$1501,"<="&$A30)+('Opening Balance'!$B$8+SUM('Daily Sale entry '!$L$2:M30)-F30),2)) | L30: =IF($A30="","",IF(ABS('Sales & Collection'!$B$404)>'Opening Balance'!$B$16,"ALERT 警报: Different "&TEXT('Sales & Collection'!$B$404,"#,##0.00")&" 差额过大",""))
A31: =IF('Daily Sale entry '!A31="","",'Daily Sale entry '!A31) | B31: =IF($A31="","",ROUND('Opening Balance'!$B$4+SUM('Daily Sale entry '!$K$2:K31)+SUMIFS('Daily Sale entry '!$AC$2:$AC$1501,'Daily Sale entry '!$X$2:$X$1501,"<="&$A31)-SUMIFS('Daily Sale entry '!$AD$2:$AD$1501,'Daily Sale entry '!$X$2:$X$1501,"<="&$A31)+SUMPRODUCT(('Daily Sale entry '!$Q$2:$Q$1501="Collection 收款")*('Daily Sale entry '!$R$2:$R$1501="Cheque 支票")*('Daily Sale entry '!$V$2:$V$1501<>"")*('Daily Sale entry '!$V$2:$V$1501<=$A31)*('Daily Sale entry '!$S$2:$S$1501-'Opening Balance'!$B$15*('Daily Sale entry '!$R$2:$R$1501="Cheque 支票")*('Daily Sale entry '!$S$2:$S$1501-TRUNC('Daily Sale entry '!$S$2:$S$1501))))-'Opening Balance'!$B$15*SUMPRODUCT(('Daily Sale entry '!$X$2:$X$1501<=$A31)*('Daily Sale entry '!$Z$2:$Z$1501="Online collection 网上收款")*('Daily Sale entry '!$AA$2:$AA$1501<>"")*('Daily Sale entry '!$AC$2:$AC$1501-TRUNC('Daily Sale entry '!$AC$2:$AC$1501))),2)) | C31: =IF($A31="","",'Opening Balance'!$B$5+SUM('Daily Sale entry '!$I$2:I31)-SUMIFS('Daily Sale entry '!$AB$2:$AB$1501,'Daily Sale entry '!$X$2:$X$1501,"<="&$A31,'Daily Sale entry '!$Z$2:$Z$1501,"Cheque deposit 支票存入")-COUNTIFS('Daily Sale entry '!$Q$2:$Q$1501,"Collection 收款",'Daily Sale entry '!$R$2:$R$1501,"Cheque 支票",'Daily Sale entry '!$V$2:$V$1501,"<="&$A31)) | D31: =IF($A31="","",ROUND('Opening Balance'!$B$6+SUM('Daily Sale entry '!$J$2:J31)-SUMIFS('Daily Sale entry '!$AC$2:$AC$1501,'Daily Sale entry '!$X$2:$X$1501,"<="&$A31,'Daily Sale entry '!$Z$2:$Z$1501,"Cheque deposit 支票存入")-SUMPRODUCT(('Daily Sale entry '!$Q$2:$Q$1501="Collection 收款")*('Daily Sale entry '!$R$2:$R$1501="Cheque 支票")*('Daily Sale entry '!$V$2:$V$1501<>"")*('Daily Sale entry '!$V$2:$V$1501<=$A31)*('Daily Sale entry '!$S$2:$S$1501-'Opening Balance'!$B$15*('Daily Sale entry '!$R$2:$R$1501="Cheque 支票")*('Daily Sale entry '!$S$2:$S$1501-TRUNC('Daily Sale entry '!$S$2:$S$1501)))),2)) | E31: =IF($A31="","",'Opening Balance'!$B$7) | F31: =IF($A31="","",ROUND(SUMIFS('Daily Sale entry '!$L$2:$L$367,'Daily Sale entry '!$A$2:$A$367,">="&DATE(YEAR($A31),MONTH($A31),1),'Daily Sale entry '!$A$2:$A$367,"<="&$A31)+SUMIFS('Daily Sale entry '!$M$2:$M$367,'Daily Sale entry '!$A$2:$A$367,">="&DATE(YEAR($A31),MONTH($A31),1),'Daily Sale entry '!$A$2:$A$367,"<="&$A31)+IF(AND(YEAR($A31)=YEAR('Daily Sale entry '!$A$2),MONTH($A31)=MONTH('Daily Sale entry '!$A$2)),'Opening Balance'!$B$8,0),2)) | G31: =IF($A31="","",MOD(ROUND('Opening Balance'!$B$9+SUMIFS('Sales & Collection'!$L$1:$L$409,'Sales & Collection'!$K$1:$K$409,"cash collection*"),2),'Opening Balance'!$B$11)) | H31: =IF($A31="","",ROUND('Opening Balance'!$B$10+'Opening Balance'!$B$9+SUMIFS('Sales & Collection'!$L$1:$L$409,'Sales & Collection'!$K$1:$K$409,"cash collection*")-G31-SUMIFS('Daily Sale entry '!$AC$2:$AC$1501,'Daily Sale entry '!$X$2:$X$1501,"<="&$A31,'Daily Sale entry '!$Z$2:$Z$1501,"Cash deposit 现金存入"),2)) | I31: =IF($A31="","",ROUND(B31+D31+E31+F31+G31+H31,2)) | J31: =IF($A31="","",'AR & AP'!K32) | K31: =IF($A31="","",ROUND(I31-J31-SUMIFS('Daily Sale entry '!$AC$2:$AC$1501,'Daily Sale entry '!$X$2:$X$1501,"<="&$A31,'Daily Sale entry '!$Z$2:$Z$1501,"Other deposit 其他存入")+SUMIFS('Daily Sale entry '!$AD$2:$AD$1501,'Daily Sale entry '!$X$2:$X$1501,"<="&$A31)+('Opening Balance'!$B$8+SUM('Daily Sale entry '!$L$2:M31)-F31),2)) | L31: =IF($A31="","",IF(ABS('Sales & Collection'!$B$418)>'Opening Balance'!$B$16,"ALERT 警报: Different "&TEXT('Sales & Collection'!$B$418,"#,##0.00")&" 差额过大",""))
A32: =IF('Daily Sale entry '!A32="","",'Daily Sale entry '!A32) | B32: =IF($A32="","",ROUND('Opening Balance'!$B$4+SUM('Daily Sale entry '!$K$2:K32)+SUMIFS('Daily Sale entry '!$AC$2:$AC$1501,'Daily Sale entry '!$X$2:$X$1501,"<="&$A32)-SUMIFS('Daily Sale entry '!$AD$2:$AD$1501,'Daily Sale entry '!$X$2:$X$1501,"<="&$A32)+SUMPRODUCT(('Daily Sale entry '!$Q$2:$Q$1501="Collection 收款")*('Daily Sale entry '!$R$2:$R$1501="Cheque 支票")*('Daily Sale entry '!$V$2:$V$1501<>"")*('Daily Sale entry '!$V$2:$V$1501<=$A32)*('Daily Sale entry '!$S$2:$S$1501-'Opening Balance'!$B$15*('Daily Sale entry '!$R$2:$R$1501="Cheque 支票")*('Daily Sale entry '!$S$2:$S$1501-TRUNC('Daily Sale entry '!$S$2:$S$1501))))-'Opening Balance'!$B$15*SUMPRODUCT(('Daily Sale entry '!$X$2:$X$1501<=$A32)*('Daily Sale entry '!$Z$2:$Z$1501="Online collection 网上收款")*('Daily Sale entry '!$AA$2:$AA$1501<>"")*('Daily Sale entry '!$AC$2:$AC$1501-TRUNC('Daily Sale entry '!$AC$2:$AC$1501))),2)) | C32: =IF($A32="","",'Opening Balance'!$B$5+SUM('Daily Sale entry '!$I$2:I32)-SUMIFS('Daily Sale entry '!$AB$2:$AB$1501,'Daily Sale entry '!$X$2:$X$1501,"<="&$A32,'Daily Sale entry '!$Z$2:$Z$1501,"Cheque deposit 支票存入")-COUNTIFS('Daily Sale entry '!$Q$2:$Q$1501,"Collection 收款",'Daily Sale entry '!$R$2:$R$1501,"Cheque 支票",'Daily Sale entry '!$V$2:$V$1501,"<="&$A32)) | D32: =IF($A32="","",ROUND('Opening Balance'!$B$6+SUM('Daily Sale entry '!$J$2:J32)-SUMIFS('Daily Sale entry '!$AC$2:$AC$1501,'Daily Sale entry '!$X$2:$X$1501,"<="&$A32,'Daily Sale entry '!$Z$2:$Z$1501,"Cheque deposit 支票存入")-SUMPRODUCT(('Daily Sale entry '!$Q$2:$Q$1501="Collection 收款")*('Daily Sale entry '!$R$2:$R$1501="Cheque 支票")*('Daily Sale entry '!$V$2:$V$1501<>"")*('Daily Sale entry '!$V$2:$V$1501<=$A32)*('Daily Sale entry '!$S$2:$S$1501-'Opening Balance'!$B$15*('Daily Sale entry '!$R$2:$R$1501="Cheque 支票")*('Daily Sale entry '!$S$2:$S$1501-TRUNC('Daily Sale entry '!$S$2:$S$1501)))),2)) | E32: =IF($A32="","",'Opening Balance'!$B$7) | F32: =IF($A32="","",ROUND(SUMIFS('Daily Sale entry '!$L$2:$L$367,'Daily Sale entry '!$A$2:$A$367,">="&DATE(YEAR($A32),MONTH($A32),1),'Daily Sale entry '!$A$2:$A$367,"<="&$A32)+SUMIFS('Daily Sale entry '!$M$2:$M$367,'Daily Sale entry '!$A$2:$A$367,">="&DATE(YEAR($A32),MONTH($A32),1),'Daily Sale entry '!$A$2:$A$367,"<="&$A32)+IF(AND(YEAR($A32)=YEAR('Daily Sale entry '!$A$2),MONTH($A32)=MONTH('Daily Sale entry '!$A$2)),'Opening Balance'!$B$8,0),2)) | G32: =IF($A32="","",MOD(ROUND('Opening Balance'!$B$9+SUMIFS('Sales & Collection'!$L$1:$L$423,'Sales & Collection'!$K$1:$K$423,"cash collection*"),2),'Opening Balance'!$B$11)) | H32: =IF($A32="","",ROUND('Opening Balance'!$B$10+'Opening Balance'!$B$9+SUMIFS('Sales & Collection'!$L$1:$L$423,'Sales & Collection'!$K$1:$K$423,"cash collection*")-G32-SUMIFS('Daily Sale entry '!$AC$2:$AC$1501,'Daily Sale entry '!$X$2:$X$1501,"<="&$A32,'Daily Sale entry '!$Z$2:$Z$1501,"Cash deposit 现金存入"),2)) | I32: =IF($A32="","",ROUND(B32+D32+E32+F32+G32+H32,2)) | J32: =IF($A32="","",'AR & AP'!K33) | K32: =IF($A32="","",ROUND(I32-J32-SUMIFS('Daily Sale entry '!$AC$2:$AC$1501,'Daily Sale entry '!$X$2:$X$1501,"<="&$A32,'Daily Sale entry '!$Z$2:$Z$1501,"Other deposit 其他存入")+SUMIFS('Daily Sale entry '!$AD$2:$AD$1501,'Daily Sale entry '!$X$2:$X$1501,"<="&$A32)+('Opening Balance'!$B$8+SUM('Daily Sale entry '!$L$2:M32)-F32),2)) | L32: =IF($A32="","",IF(ABS('Sales & Collection'!$B$432)>'Opening Balance'!$B$16,"ALERT 警报: Different "&TEXT('Sales & Collection'!$B$432,"#,##0.00")&" 差额过大",""))
A33: =IF('Daily Sale entry '!A33="","",'Daily Sale entry '!A33) | B33: =IF($A33="","",ROUND('Opening Balance'!$B$4+SUM('Daily Sale entry '!$K$2:K33)+SUMIFS('Daily Sale entry '!$AC$2:$AC$1501,'Daily Sale entry '!$X$2:$X$1501,"<="&$A33)-SUMIFS('Daily Sale entry '!$AD$2:$AD$1501,'Daily Sale entry '!$X$2:$X$1501,"<="&$A33)+SUMPRODUCT(('Daily Sale entry '!$Q$2:$Q$1501="Collection 收款")*('Daily Sale entry '!$R$2:$R$1501="Cheque 支票")*('Daily Sale entry '!$V$2:$V$1501<>"")*('Daily Sale entry '!$V$2:$V$1501<=$A33)*('Daily Sale entry '!$S$2:$S$1501-'Opening Balance'!$B$15*('Daily Sale entry '!$R$2:$R$1501="Cheque 支票")*('Daily Sale entry '!$S$2:$S$1501-TRUNC('Daily Sale entry '!$S$2:$S$1501))))-'Opening Balance'!$B$15*SUMPRODUCT(('Daily Sale entry '!$X$2:$X$1501<=$A33)*('Daily Sale entry '!$Z$2:$Z$1501="Online collection 网上收款")*('Daily Sale entry '!$AA$2:$AA$1501<>"")*('Daily Sale entry '!$AC$2:$AC$1501-TRUNC('Daily Sale entry '!$AC$2:$AC$1501))),2)) | C33: =IF($A33="","",'Opening Balance'!$B$5+SUM('Daily Sale entry '!$I$2:I33)-SUMIFS('Daily Sale entry '!$AB$2:$AB$1501,'Daily Sale entry '!$X$2:$X$1501,"<="&$A33,'Daily Sale entry '!$Z$2:$Z$1501,"Cheque deposit 支票存入")-COUNTIFS('Daily Sale entry '!$Q$2:$Q$1501,"Collection 收款",'Daily Sale entry '!$R$2:$R$1501,"Cheque 支票",'Daily Sale entry '!$V$2:$V$1501,"<="&$A33)) | D33: =IF($A33="","",ROUND('Opening Balance'!$B$6+SUM('Daily Sale entry '!$J$2:J33)-SUMIFS('Daily Sale entry '!$AC$2:$AC$1501,'Daily Sale entry '!$X$2:$X$1501,"<="&$A33,'Daily Sale entry '!$Z$2:$Z$1501,"Cheque deposit 支票存入")-SUMPRODUCT(('Daily Sale entry '!$Q$2:$Q$1501="Collection 收款")*('Daily Sale entry '!$R$2:$R$1501="Cheque 支票")*('Daily Sale entry '!$V$2:$V$1501<>"")*('Daily Sale entry '!$V$2:$V$1501<=$A33)*('Daily Sale entry '!$S$2:$S$1501-'Opening Balance'!$B$15*('Daily Sale entry '!$R$2:$R$1501="Cheque 支票")*('Daily Sale entry '!$S$2:$S$1501-TRUNC('Daily Sale entry '!$S$2:$S$1501)))),2)) | E33: =IF($A33="","",'Opening Balance'!$B$7) | F33: =IF($A33="","",ROUND(SUMIFS('Daily Sale entry '!$L$2:$L$367,'Daily Sale entry '!$A$2:$A$367,">="&DATE(YEAR($A33),MONTH($A33),1),'Daily Sale entry '!$A$2:$A$367,"<="&$A33)+SUMIFS('Daily Sale entry '!$M$2:$M$367,'Daily Sale entry '!$A$2:$A$367,">="&DATE(YEAR($A33),MONTH($A33),1),'Daily Sale entry '!$A$2:$A$367,"<="&$A33)+IF(AND(YEAR($A33)=YEAR('Daily Sale entry '!$A$2),MONTH($A33)=MONTH('Daily Sale entry '!$A$2)),'Opening Balance'!$B$8,0),2)) | G33: =IF($A33="","",MOD(ROUND('Opening Balance'!$B$9+SUMIFS('Sales & Collection'!$L$1:$L$437,'Sales & Collection'!$K$1:$K$437,"cash collection*"),2),'Opening Balance'!$B$11)) | H33: =IF($A33="","",ROUND('Opening Balance'!$B$10+'Opening Balance'!$B$9+SUMIFS('Sales & Collection'!$L$1:$L$437,'Sales & Collection'!$K$1:$K$437,"cash collection*")-G33-SUMIFS('Daily Sale entry '!$AC$2:$AC$1501,'Daily Sale entry '!$X$2:$X$1501,"<="&$A33,'Daily Sale entry '!$Z$2:$Z$1501,"Cash deposit 现金存入"),2)) | I33: =IF($A33="","",ROUND(B33+D33+E33+F33+G33+H33,2)) | J33: =IF($A33="","",'AR & AP'!K34) | K33: =IF($A33="","",ROUND(I33-J33-SUMIFS('Daily Sale entry '!$AC$2:$AC$1501,'Daily Sale entry '!$X$2:$X$1501,"<="&$A33,'Daily Sale entry '!$Z$2:$Z$1501,"Other deposit 其他存入")+SUMIFS('Daily Sale entry '!$AD$2:$AD$1501,'Daily Sale entry '!$X$2:$X$1501,"<="&$A33)+('Opening Balance'!$B$8+SUM('Daily Sale entry '!$L$2:M33)-F33),2)) | L33: =IF($A33="","",IF(ABS('Sales & Collection'!$B$446)>'Opening Balance'!$B$16,"ALERT 警报: Different "&TEXT('Sales & Collection'!$B$446,"#,##0.00")&" 差额过大",""))
A34: =IF('Daily Sale entry '!A34="","",'Daily Sale entry '!A34) | B34: =IF($A34="","",ROUND('Opening Balance'!$B$4+SUM('Daily Sale entry '!$K$2:K34)+SUMIFS('Daily Sale entry '!$AC$2:$AC$1501,'Daily Sale entry '!$X$2:$X$1501,"<="&$A34)-SUMIFS('Daily Sale entry '!$AD$2:$AD$1501,'Daily Sale entry '!$X$2:$X$1501,"<="&$A34)+SUMPRODUCT(('Daily Sale entry '!$Q$2:$Q$1501="Collection 收款")*('Daily Sale entry '!$R$2:$R$1501="Cheque 支票")*('Daily Sale entry '!$V$2:$V$1501<>"")*('Daily Sale entry '!$V$2:$V$1501<=$A34)*('Daily Sale entry '!$S$2:$S$1501-'Opening Balance'!$B$15*('Daily Sale entry '!$R$2:$R$1501="Cheque 支票")*('Daily Sale entry '!$S$2:$S$1501-TRUNC('Daily Sale entry '!$S$2:$S$1501))))-'Opening Balance'!$B$15*SUMPRODUCT(('Daily Sale entry '!$X$2:$X$1501<=$A34)*('Daily Sale entry '!$Z$2:$Z$1501="Online collection 网上收款")*('Daily Sale entry '!$AA$2:$AA$1501<>"")*('Daily Sale entry '!$AC$2:$AC$1501-TRUNC('Daily Sale entry '!$AC$2:$AC$1501))),2)) | C34: =IF($A34="","",'Opening Balance'!$B$5+SUM('Daily Sale entry '!$I$2:I34)-SUMIFS('Daily Sale entry '!$AB$2:$AB$1501,'Daily Sale entry '!$X$2:$X$1501,"<="&$A34,'Daily Sale entry '!$Z$2:$Z$1501,"Cheque deposit 支票存入")-COUNTIFS('Daily Sale entry '!$Q$2:$Q$1501,"Collection 收款",'Daily Sale entry '!$R$2:$R$1501,"Cheque 支票",'Daily Sale entry '!$V$2:$V$1501,"<="&$A34)) | D34: =IF($A34="","",ROUND('Opening Balance'!$B$6+SUM('Daily Sale entry '!$J$2:J34)-SUMIFS('Daily Sale entry '!$AC$2:$AC$1501,'Daily Sale entry '!$X$2:$X$1501,"<="&$A34,'Daily Sale entry '!$Z$2:$Z$1501,"Cheque deposit 支票存入")-SUMPRODUCT(('Daily Sale entry '!$Q$2:$Q$1501="Collection 收款")*('Daily Sale entry '!$R$2:$R$1501="Cheque 支票")*('Daily Sale entry '!$V$2:$V$1501<>"")*('Daily Sale entry '!$V$2:$V$1501<=$A34)*('Daily Sale entry '!$S$2:$S$1501-'Opening Balance'!$B$15*('Daily Sale entry '!$R$2:$R$1501="Cheque 支票")*('Daily Sale entry '!$S$2:$S$1501-TRUNC('Daily Sale entry '!$S$2:$S$1501)))),2)) | E34: =IF($A34="","",'Opening Balance'!$B$7) | F34: =IF($A34="","",ROUND(SUMIFS('Daily Sale entry '!$L$2:$L$367,'Daily Sale entry '!$A$2:$A$367,">="&DATE(YEAR($A34),MONTH($A34),1),'Daily Sale entry '!$A$2:$A$367,"<="&$A34)+SUMIFS('Daily Sale entry '!$M$2:$M$367,'Daily Sale entry '!$A$2:$A$367,">="&DATE(YEAR($A34),MONTH($A34),1),'Daily Sale entry '!$A$2:$A$367,"<="&$A34)+IF(AND(YEAR($A34)=YEAR('Daily Sale entry '!$A$2),MONTH($A34)=MONTH('Daily Sale entry '!$A$2)),'Opening Balance'!$B$8,0),2)) | G34: =IF($A34="","",MOD(ROUND('Opening Balance'!$B$9+SUMIFS('Sales & Collection'!$L$1:$L$451,'Sales & Collection'!$K$1:$K$451,"cash collection*"),2),'Opening Balance'!$B$11)) | H34: =IF($A34="","",ROUND('Opening Balance'!$B$10+'Opening Balance'!$B$9+SUMIFS('Sales & Collection'!$L$1:$L$451,'Sales & Collection'!$K$1:$K$451,"cash collection*")-G34-SUMIFS('Daily Sale entry '!$AC$2:$AC$1501,'Daily Sale entry '!$X$2:$X$1501,"<="&$A34,'Daily Sale entry '!$Z$2:$Z$1501,"Cash deposit 现金存入"),2)) | I34: =IF($A34="","",ROUND(B34+D34+E34+F34+G34+H34,2)) | J34: =IF($A34="","",'AR & AP'!K35) | K34: =IF($A34="","",ROUND(I34-J34-SUMIFS('Daily Sale entry '!$AC$2:$AC$1501,'Daily Sale entry '!$X$2:$X$1501,"<="&$A34,'Daily Sale entry '!$Z$2:$Z$1501,"Other deposit 其他存入")+SUMIFS('Daily Sale entry '!$AD$2:$AD$1501,'Daily Sale entry '!$X$2:$X$1501,"<="&$A34)+('Opening Balance'!$B$8+SUM('Daily Sale entry '!$L$2:M34)-F34),2)) | L34: =IF($A34="","",IF(ABS('Sales & Collection'!$B$460)>'Opening Balance'!$B$16,"ALERT 警报: Different "&TEXT('Sales & Collection'!$B$460,"#,##0.00")&" 差额过大",""))
A35: =IF('Daily Sale entry '!A35="","",'Daily Sale entry '!A35) | B35: =IF($A35="","",ROUND('Opening Balance'!$B$4+SUM('Daily Sale entry '!$K$2:K35)+SUMIFS('Daily Sale entry '!$AC$2:$AC$1501,'Daily Sale entry '!$X$2:$X$1501,"<="&$A35)-SUMIFS('Daily Sale entry '!$AD$2:$AD$1501,'Daily Sale entry '!$X$2:$X$1501,"<="&$A35)+SUMPRODUCT(('Daily Sale entry '!$Q$2:$Q$1501="Collection 收款")*('Daily Sale entry '!$R$2:$R$1501="Cheque 支票")*('Daily Sale entry '!$V$2:$V$1501<>"")*('Daily Sale entry '!$V$2:$V$1501<=$A35)*('Daily Sale entry '!$S$2:$S$1501-'Opening Balance'!$B$15*('Daily Sale entry '!$R$2:$R$1501="Cheque 支票")*('Daily Sale entry '!$S$2:$S$1501-TRUNC('Daily Sale entry '!$S$2:$S$1501))))-'Opening Balance'!$B$15*SUMPRODUCT(('Daily Sale entry '!$X$2:$X$1501<=$A35)*('Daily Sale entry '!$Z$2:$Z$1501="Online collection 网上收款")*('Daily Sale entry '!$AA$2:$AA$1501<>"")*('Daily Sale entry '!$AC$2:$AC$1501-TRUNC('Daily Sale entry '!$AC$2:$AC$1501))),2)) | C35: =IF($A35="","",'Opening Balance'!$B$5+SUM('Daily Sale entry '!$I$2:I35)-SUMIFS('Daily Sale entry '!$AB$2:$AB$1501,'Daily Sale entry '!$X$2:$X$1501,"<="&$A35,'Daily Sale entry '!$Z$2:$Z$1501,"Cheque deposit 支票存入")-COUNTIFS('Daily Sale entry '!$Q$2:$Q$1501,"Collection 收款",'Daily Sale entry '!$R$2:$R$1501,"Cheque 支票",'Daily Sale entry '!$V$2:$V$1501,"<="&$A35)) | D35: =IF($A35="","",ROUND('Opening Balance'!$B$6+SUM('Daily Sale entry '!$J$2:J35)-SUMIFS('Daily Sale entry '!$AC$2:$AC$1501,'Daily Sale entry '!$X$2:$X$1501,"<="&$A35,'Daily Sale entry '!$Z$2:$Z$1501,"Cheque deposit 支票存入")-SUMPRODUCT(('Daily Sale entry '!$Q$2:$Q$1501="Collection 收款")*('Daily Sale entry '!$R$2:$R$1501="Cheque 支票")*('Daily Sale entry '!$V$2:$V$1501<>"")*('Daily Sale entry '!$V$2:$V$1501<=$A35)*('Daily Sale entry '!$S$2:$S$1501-'Opening Balance'!$B$15*('Daily Sale entry '!$R$2:$R$1501="Cheque 支票")*('Daily Sale entry '!$S$2:$S$1501-TRUNC('Daily Sale entry '!$S$2:$S$1501)))),2)) | E35: =IF($A35="","",'Opening Balance'!$B$7) | F35: =IF($A35="","",ROUND(SUMIFS('Daily Sale entry '!$L$2:$L$367,'Daily Sale entry '!$A$2:$A$367,">="&DATE(YEAR($A35),MONTH($A35),1),'Daily Sale entry '!$A$2:$A$367,"<="&$A35)+SUMIFS('Daily Sale entry '!$M$2:$M$367,'Daily Sale entry '!$A$2:$A$367,">="&DATE(YEAR($A35),MONTH($A35),1),'Daily Sale entry '!$A$2:$A$367,"<="&$A35)+IF(AND(YEAR($A35)=YEAR('Daily Sale entry '!$A$2),MONTH($A35)=MONTH('Daily Sale entry '!$A$2)),'Opening Balance'!$B$8,0),2)) | G35: =IF($A35="","",MOD(ROUND('Opening Balance'!$B$9+SUMIFS('Sales & Collection'!$L$1:$L$465,'Sales & Collection'!$K$1:$K$465,"cash collection*"),2),'Opening Balance'!$B$11)) | H35: =IF($A35="","",ROUND('Opening Balance'!$B$10+'Opening Balance'!$B$9+SUMIFS('Sales & Collection'!$L$1:$L$465,'Sales & Collection'!$K$1:$K$465,"cash collection*")-G35-SUMIFS('Daily Sale entry '!$AC$2:$AC$1501,'Daily Sale entry '!$X$2:$X$1501,"<="&$A35,'Daily Sale entry '!$Z$2:$Z$1501,"Cash deposit 现金存入"),2)) | I35: =IF($A35="","",ROUND(B35+D35+E35+F35+G35+H35,2)) | J35: =IF($A35="","",'AR & AP'!K36) | K35: =IF($A35="","",ROUND(I35-J35-SUMIFS('Daily Sale entry '!$AC$2:$AC$1501,'Daily Sale entry '!$X$2:$X$1501,"<="&$A35,'Daily Sale entry '!$Z$2:$Z$1501,"Other deposit 其他存入")+SUMIFS('Daily Sale entry '!$AD$2:$AD$1501,'Daily Sale entry '!$X$2:$X$1501,"<="&$A35)+('Opening Balance'!$B$8+SUM('Daily Sale entry '!$L$2:M35)-F35),2)) | L35: =IF($A35="","",IF(ABS('Sales & Collection'!$B$474)>'Opening Balance'!$B$16,"ALERT 警报: Different "&TEXT('Sales & Collection'!$B$474,"#,##0.00")&" 差额过大",""))
A36: =IF('Daily Sale entry '!A36="","",'Daily Sale entry '!A36) | B36: =IF($A36="","",ROUND('Opening Balance'!$B$4+SUM('Daily Sale entry '!$K$2:K36)+SUMIFS('Daily Sale entry '!$AC$2:$AC$1501,'Daily Sale entry '!$X$2:$X$1501,"<="&$A36)-SUMIFS('Daily Sale entry '!$AD$2:$AD$1501,'Daily Sale entry '!$X$2:$X$1501,"<="&$A36)+SUMPRODUCT(('Daily Sale entry '!$Q$2:$Q$1501="Collection 收款")*('Daily Sale entry '!$R$2:$R$1501="Cheque 支票")*('Daily Sale entry '!$V$2:$V$1501<>"")*('Daily Sale entry '!$V$2:$V$1501<=$A36)*('Daily Sale entry '!$S$2:$S$1501-'Opening Balance'!$B$15*('Daily Sale entry '!$R$2:$R$1501="Cheque 支票")*('Daily Sale entry '!$S$2:$S$1501-TRUNC('Daily Sale entry '!$S$2:$S$1501))))-'Opening Balance'!$B$15*SUMPRODUCT(('Daily Sale entry '!$X$2:$X$1501<=$A36)*('Daily Sale entry '!$Z$2:$Z$1501="Online collection 网上收款")*('Daily Sale entry '!$AA$2:$AA$1501<>"")*('Daily Sale entry '!$AC$2:$AC$1501-TRUNC('Daily Sale entry '!$AC$2:$AC$1501))),2)) | C36: =IF($A36="","",'Opening Balance'!$B$5+SUM('Daily Sale entry '!$I$2:I36)-SUMIFS('Daily Sale entry '!$AB$2:$AB$1501,'Daily Sale entry '!$X$2:$X$1501,"<="&$A36,'Daily Sale entry '!$Z$2:$Z$1501,"Cheque deposit 支票存入")-COUNTIFS('Daily Sale entry '!$Q$2:$Q$1501,"Collection 收款",'Daily Sale entry '!$R$2:$R$1501,"Cheque 支票",'Daily Sale entry '!$V$2:$V$1501,"<="&$A36)) | D36: =IF($A36="","",ROUND('Opening Balance'!$B$6+SUM('Daily Sale entry '!$J$2:J36)-SUMIFS('Daily Sale entry '!$AC$2:$AC$1501,'Daily Sale entry '!$X$2:$X$1501,"<="&$A36,'Daily Sale entry '!$Z$2:$Z$1501,"Cheque deposit 支票存入")-SUMPRODUCT(('Daily Sale entry '!$Q$2:$Q$1501="Collection 收款")*('Daily Sale entry '!$R$2:$R$1501="Cheque 支票")*('Daily Sale entry '!$V$2:$V$1501<>"")*('Daily Sale entry '!$V$2:$V$1501<=$A36)*('Daily Sale entry '!$S$2:$S$1501-'Opening Balance'!$B$15*('Daily Sale entry '!$R$2:$R$1501="Cheque 支票")*('Daily Sale entry '!$S$2:$S$1501-TRUNC('Daily Sale entry '!$S$2:$S$1501)))),2)) | E36: =IF($A36="","",'Opening Balance'!$B$7) | F36: =IF($A36="","",ROUND(SUMIFS('Daily Sale entry '!$L$2:$L$367,'Daily Sale entry '!$A$2:$A$367,">="&DATE(YEAR($A36),MONTH($A36),1),'Daily Sale entry '!$A$2:$A$367,"<="&$A36)+SUMIFS('Daily Sale entry '!$M$2:$M$367,'Daily Sale entry '!$A$2:$A$367,">="&DATE(YEAR($A36),MONTH($A36),1),'Daily Sale entry '!$A$2:$A$367,"<="&$A36)+IF(AND(YEAR($A36)=YEAR('Daily Sale entry '!$A$2),MONTH($A36)=MONTH('Daily Sale entry '!$A$2)),'Opening Balance'!$B$8,0),2)) | G36: =IF($A36="","",MOD(ROUND('Opening Balance'!$B$9+SUMIFS('Sales & Collection'!$L$1:$L$479,'Sales & Collection'!$K$1:$K$479,"cash collection*"),2),'Opening Balance'!$B$11)) | H36: =IF($A36="","",ROUND('Opening Balance'!$B$10+'Opening Balance'!$B$9+SUMIFS('Sales & Collection'!$L$1:$L$479,'Sales & Collection'!$K$1:$K$479,"cash collection*")-G36-SUMIFS('Daily Sale entry '!$AC$2:$AC$1501,'Daily Sale entry '!$X$2:$X$1501,"<="&$A36,'Daily Sale entry '!$Z$2:$Z$1501,"Cash deposit 现金存入"),2)) | I36: =IF($A36="","",ROUND(B36+D36+E36+F36+G36+H36,2)) | J36: =IF($A36="","",'AR & AP'!K37) | K36: =IF($A36="","",ROUND(I36-J36-SUMIFS('Daily Sale entry '!$AC$2:$AC$1501,'Daily Sale entry '!$X$2:$X$1501,"<="&$A36,'Daily Sale entry '!$Z$2:$Z$1501,"Other deposit 其他存入")+SUMIFS('Daily Sale entry '!$AD$2:$AD$1501,'Daily Sale entry '!$X$2:$X$1501,"<="&$A36)+('Opening Balance'!$B$8+SUM('Daily Sale entry '!$L$2:M36)-F36),2)) | L36: =IF($A36="","",IF(ABS('Sales & Collection'!$B$488)>'Opening Balance'!$B$16,"ALERT 警报: Different "&TEXT('Sales & Collection'!$B$488,"#,##0.00")&" 差额过大",""))
A37: =IF('Daily Sale entry '!A37="","",'Daily Sale entry '!A37) | B37: =IF($A37="","",ROUND('Opening Balance'!$B$4+SUM('Daily Sale entry '!$K$2:K37)+SUMIFS('Daily Sale entry '!$AC$2:$AC$1501,'Daily Sale entry '!$X$2:$X$1501,"<="&$A37)-SUMIFS('Daily Sale entry '!$AD$2:$AD$1501,'Daily Sale entry '!$X$2:$X$1501,"<="&$A37)+SUMPRODUCT(('Daily Sale entry '!$Q$2:$Q$1501="Collection 收款")*('Daily Sale entry '!$R$2:$R$1501="Cheque 支票")*('Daily Sale entry '!$V$2:$V$1501<>"")*('Daily Sale entry '!$V$2:$V$1501<=$A37)*('Daily Sale entry '!$S$2:$S$1501-'Opening Balance'!$B$15*('Daily Sale entry '!$R$2:$R$1501="Cheque 支票")*('Daily Sale entry '!$S$2:$S$1501-TRUNC('Daily Sale entry '!$S$2:$S$1501))))-'Opening Balance'!$B$15*SUMPRODUCT(('Daily Sale entry '!$X$2:$X$1501<=$A37)*('Daily Sale entry '!$Z$2:$Z$1501="Online collection 网上收款")*('Daily Sale entry '!$AA$2:$AA$1501<>"")*('Daily Sale entry '!$AC$2:$AC$1501-TRUNC('Daily Sale entry '!$AC$2:$AC$1501))),2)) | C37: =IF($A37="","",'Opening Balance'!$B$5+SUM('Daily Sale entry '!$I$2:I37)-SUMIFS('Daily Sale entry '!$AB$2:$AB$1501,'Daily Sale entry '!$X$2:$X$1501,"<="&$A37,'Daily Sale entry '!$Z$2:$Z$1501,"Cheque deposit 支票存入")-COUNTIFS('Daily Sale entry '!$Q$2:$Q$1501,"Collection 收款",'Daily Sale entry '!$R$2:$R$1501,"Cheque 支票",'Daily Sale entry '!$V$2:$V$1501,"<="&$A37)) | D37: =IF($A37="","",ROUND('Opening Balance'!$B$6+SUM('Daily Sale entry '!$J$2:J37)-SUMIFS('Daily Sale entry '!$AC$2:$AC$1501,'Daily Sale entry '!$X$2:$X$1501,"<="&$A37,'Daily Sale entry '!$Z$2:$Z$1501,"Cheque deposit 支票存入")-SUMPRODUCT(('Daily Sale entry '!$Q$2:$Q$1501="Collection 收款")*('Daily Sale entry '!$R$2:$R$1501="Cheque 支票")*('Daily Sale entry '!$V$2:$V$1501<>"")*('Daily Sale entry '!$V$2:$V$1501<=$A37)*('Daily Sale entry '!$S$2:$S$1501-'Opening Balance'!$B$15*('Daily Sale entry '!$R$2:$R$1501="Cheque 支票")*('Daily Sale entry '!$S$2:$S$1501-TRUNC('Daily Sale entry '!$S$2:$S$1501)))),2)) | E37: =IF($A37="","",'Opening Balance'!$B$7) | F37: =IF($A37="","",ROUND(SUMIFS('Daily Sale entry '!$L$2:$L$367,'Daily Sale entry '!$A$2:$A$367,">="&DATE(YEAR($A37),MONTH($A37),1),'Daily Sale entry '!$A$2:$A$367,"<="&$A37)+SUMIFS('Daily Sale entry '!$M$2:$M$367,'Daily Sale entry '!$A$2:$A$367,">="&DATE(YEAR($A37),MONTH($A37),1),'Daily Sale entry '!$A$2:$A$367,"<="&$A37)+IF(AND(YEAR($A37)=YEAR('Daily Sale entry '!$A$2),MONTH($A37)=MONTH('Daily Sale entry '!$A$2)),'Opening Balance'!$B$8,0),2)) | G37: =IF($A37="","",MOD(ROUND('Opening Balance'!$B$9+SUMIFS('Sales & Collection'!$L$1:$L$493,'Sales & Collection'!$K$1:$K$493,"cash collection*"),2),'Opening Balance'!$B$11)) | H37: =IF($A37="","",ROUND('Opening Balance'!$B$10+'Opening Balance'!$B$9+SUMIFS('Sales & Collection'!$L$1:$L$493,'Sales & Collection'!$K$1:$K$493,"cash collection*")-G37-SUMIFS('Daily Sale entry '!$AC$2:$AC$1501,'Daily Sale entry '!$X$2:$X$1501,"<="&$A37,'Daily Sale entry '!$Z$2:$Z$1501,"Cash deposit 现金存入"),2)) | I37: =IF($A37="","",ROUND(B37+D37+E37+F37+G37+H37,2)) | J37: =IF($A37="","",'AR & AP'!K38) | K37: =IF($A37="","",ROUND(I37-J37-SUMIFS('Daily Sale entry '!$AC$2:$AC$1501,'Daily Sale entry '!$X$2:$X$1501,"<="&$A37,'Daily Sale entry '!$Z$2:$Z$1501,"Other deposit 其他存入")+SUMIFS('Daily Sale entry '!$AD$2:$AD$1501,'Daily Sale entry '!$X$2:$X$1501,"<="&$A37)+('Opening Balance'!$B$8+SUM('Daily Sale entry '!$L$2:M37)-F37),2)) | L37: =IF($A37="","",IF(ABS('Sales & Collection'!$B$502)>'Opening Balance'!$B$16,"ALERT 警报: Different "&TEXT('Sales & Collection'!$B$502,"#,##0.00")&" 差额过大",""))
A38: =IF('Daily Sale entry '!A38="","",'Daily Sale entry '!A38) | B38: =IF($A38="","",ROUND('Opening Balance'!$B$4+SUM('Daily Sale entry '!$K$2:K38)+SUMIFS('Daily Sale entry '!$AC$2:$AC$1501,'Daily Sale entry '!$X$2:$X$1501,"<="&$A38)-SUMIFS('Daily Sale entry '!$AD$2:$AD$1501,'Daily Sale entry '!$X$2:$X$1501,"<="&$A38)+SUMPRODUCT(('Daily Sale entry '!$Q$2:$Q$1501="Collection 收款")*('Daily Sale entry '!$R$2:$R$1501="Cheque 支票")*('Daily Sale entry '!$V$2:$V$1501<>"")*('Daily Sale entry '!$V$2:$V$1501<=$A38)*('Daily Sale entry '!$S$2:$S$1501-'Opening Balance'!$B$15*('Daily Sale entry '!$R$2:$R$1501="Cheque 支票")*('Daily Sale entry '!$S$2:$S$1501-TRUNC('Daily Sale entry '!$S$2:$S$1501))))-'Opening Balance'!$B$15*SUMPRODUCT(('Daily Sale entry '!$X$2:$X$1501<=$A38)*('Daily Sale entry '!$Z$2:$Z$1501="Online collection 网上收款")*('Daily Sale entry '!$AA$2:$AA$1501<>"")*('Daily Sale entry '!$AC$2:$AC$1501-TRUNC('Daily Sale entry '!$AC$2:$AC$1501))),2)) | C38: =IF($A38="","",'Opening Balance'!$B$5+SUM('Daily Sale entry '!$I$2:I38)-SUMIFS('Daily Sale entry '!$AB$2:$AB$1501,'Daily Sale entry '!$X$2:$X$1501,"<="&$A38,'Daily Sale entry '!$Z$2:$Z$1501,"Cheque deposit 支票存入")-COUNTIFS('Daily Sale entry '!$Q$2:$Q$1501,"Collection 收款",'Daily Sale entry '!$R$2:$R$1501,"Cheque 支票",'Daily Sale entry '!$V$2:$V$1501,"<="&$A38)) | D38: =IF($A38="","",ROUND('Opening Balance'!$B$6+SUM('Daily Sale entry '!$J$2:J38)-SUMIFS('Daily Sale entry '!$AC$2:$AC$1501,'Daily Sale entry '!$X$2:$X$1501,"<="&$A38,'Daily Sale entry '!$Z$2:$Z$1501,"Cheque deposit 支票存入")-SUMPRODUCT(('Daily Sale entry '!$Q$2:$Q$1501="Collection 收款")*('Daily Sale entry '!$R$2:$R$1501="Cheque 支票")*('Daily Sale entry '!$V$2:$V$1501<>"")*('Daily Sale entry '!$V$2:$V$1501<=$A38)*('Daily Sale entry '!$S$2:$S$1501-'Opening Balance'!$B$15*('Daily Sale entry '!$R$2:$R$1501="Cheque 支票")*('Daily Sale entry '!$S$2:$S$1501-TRUNC('Daily Sale entry '!$S$2:$S$1501)))),2)) | E38: =IF($A38="","",'Opening Balance'!$B$7) | F38: =IF($A38="","",ROUND(SUMIFS('Daily Sale entry '!$L$2:$L$367,'Daily Sale entry '!$A$2:$A$367,">="&DATE(YEAR($A38),MONTH($A38),1),'Daily Sale entry '!$A$2:$A$367,"<="&$A38)+SUMIFS('Daily Sale entry '!$M$2:$M$367,'Daily Sale entry '!$A$2:$A$367,">="&DATE(YEAR($A38),MONTH($A38),1),'Daily Sale entry '!$A$2:$A$367,"<="&$A38)+IF(AND(YEAR($A38)=YEAR('Daily Sale entry '!$A$2),MONTH($A38)=MONTH('Daily Sale entry '!$A$2)),'Opening Balance'!$B$8,0),2)) | G38: =IF($A38="","",MOD(ROUND('Opening Balance'!$B$9+SUMIFS('Sales & Collection'!$L$1:$L$507,'Sales & Collection'!$K$1:$K$507,"cash collection*"),2),'Opening Balance'!$B$11)) | H38: =IF($A38="","",ROUND('Opening Balance'!$B$10+'Opening Balance'!$B$9+SUMIFS('Sales & Collection'!$L$1:$L$507,'Sales & Collection'!$K$1:$K$507,"cash collection*")-G38-SUMIFS('Daily Sale entry '!$AC$2:$AC$1501,'Daily Sale entry '!$X$2:$X$1501,"<="&$A38,'Daily Sale entry '!$Z$2:$Z$1501,"Cash deposit 现金存入"),2)) | I38: =IF($A38="","",ROUND(B38+D38+E38+F38+G38+H38,2)) | J38: =IF($A38="","",'AR & AP'!K39) | K38: =IF($A38="","",ROUND(I38-J38-SUMIFS('Daily Sale entry '!$AC$2:$AC$1501,'Daily Sale entry '!$X$2:$X$1501,"<="&$A38,'Daily Sale entry '!$Z$2:$Z$1501,"Other deposit 其他存入")+SUMIFS('Daily Sale entry '!$AD$2:$AD$1501,'Daily Sale entry '!$X$2:$X$1501,"<="&$A38)+('Opening Balance'!$B$8+SUM('Daily Sale entry '!$L$2:M38)-F38),2)) | L38: =IF($A38="","",IF(ABS('Sales & Collection'!$B$516)>'Opening Balance'!$B$16,"ALERT 警报: Different "&TEXT('Sales & Collection'!$B$516,"#,##0.00")&" 差额过大",""))
A39: =IF('Daily Sale entry '!A39="","",'Daily Sale entry '!A39) | B39: =IF($A39="","",ROUND('Opening Balance'!$B$4+SUM('Daily Sale entry '!$K$2:K39)+SUMIFS('Daily Sale entry '!$AC$2:$AC$1501,'Daily Sale entry '!$X$2:$X$1501,"<="&$A39)-SUMIFS('Daily Sale entry '!$AD$2:$AD$1501,'Daily Sale entry '!$X$2:$X$1501,"<="&$A39)+SUMPRODUCT(('Daily Sale entry '!$Q$2:$Q$1501="Collection 收款")*('Daily Sale entry '!$R$2:$R$1501="Cheque 支票")*('Daily Sale entry '!$V$2:$V$1501<>"")*('Daily Sale entry '!$V$2:$V$1501<=$A39)*('Daily Sale entry '!$S$2:$S$1501-'Opening Balance'!$B$15*('Daily Sale entry '!$R$2:$R$1501="Cheque 支票")*('Daily Sale entry '!$S$2:$S$1501-TRUNC('Daily Sale entry '!$S$2:$S$1501))))-'Opening Balance'!$B$15*SUMPRODUCT(('Daily Sale entry '!$X$2:$X$1501<=$A39)*('Daily Sale entry '!$Z$2:$Z$1501="Online collection 网上收款")*('Daily Sale entry '!$AA$2:$AA$1501<>"")*('Daily Sale entry '!$AC$2:$AC$1501-TRUNC('Daily Sale entry '!$AC$2:$AC$1501))),2)) | C39: =IF($A39="","",'Opening Balance'!$B$5+SUM('Daily Sale entry '!$I$2:I39)-SUMIFS('Daily Sale entry '!$AB$2:$AB$1501,'Daily Sale entry '!$X$2:$X$1501,"<="&$A39,'Daily Sale entry '!$Z$2:$Z$1501,"Cheque deposit 支票存入")-COUNTIFS('Daily Sale entry '!$Q$2:$Q$1501,"Collection 收款",'Daily Sale entry '!$R$2:$R$1501,"Cheque 支票",'Daily Sale entry '!$V$2:$V$1501,"<="&$A39)) | D39: =IF($A39="","",ROUND('Opening Balance'!$B$6+SUM('Daily Sale entry '!$J$2:J39)-SUMIFS('Daily Sale entry '!$AC$2:$AC$1501,'Daily Sale entry '!$X$2:$X$1501,"<="&$A39,'Daily Sale entry '!$Z$2:$Z$1501,"Cheque deposit 支票存入")-SUMPRODUCT(('Daily Sale entry '!$Q$2:$Q$1501="Collection 收款")*('Daily Sale entry '!$R$2:$R$1501="Cheque 支票")*('Daily Sale entry '!$V$2:$V$1501<>"")*('Daily Sale entry '!$V$2:$V$1501<=$A39)*('Daily Sale entry '!$S$2:$S$1501-'Opening Balance'!$B$15*('Daily Sale entry '!$R$2:$R$1501="Cheque 支票")*('Daily Sale entry '!$S$2:$S$1501-TRUNC('Daily Sale entry '!$S$2:$S$1501)))),2)) | E39: =IF($A39="","",'Opening Balance'!$B$7) | F39: =IF($A39="","",ROUND(SUMIFS('Daily Sale entry '!$L$2:$L$367,'Daily Sale entry '!$A$2:$A$367,">="&DATE(YEAR($A39),MONTH($A39),1),'Daily Sale entry '!$A$2:$A$367,"<="&$A39)+SUMIFS('Daily Sale entry '!$M$2:$M$367,'Daily Sale entry '!$A$2:$A$367,">="&DATE(YEAR($A39),MONTH($A39),1),'Daily Sale entry '!$A$2:$A$367,"<="&$A39)+IF(AND(YEAR($A39)=YEAR('Daily Sale entry '!$A$2),MONTH($A39)=MONTH('Daily Sale entry '!$A$2)),'Opening Balance'!$B$8,0),2)) | G39: =IF($A39="","",MOD(ROUND('Opening Balance'!$B$9+SUMIFS('Sales & Collection'!$L$1:$L$521,'Sales & Collection'!$K$1:$K$521,"cash collection*"),2),'Opening Balance'!$B$11)) | H39: =IF($A39="","",ROUND('Opening Balance'!$B$10+'Opening Balance'!$B$9+SUMIFS('Sales & Collection'!$L$1:$L$521,'Sales & Collection'!$K$1:$K$521,"cash collection*")-G39-SUMIFS('Daily Sale entry '!$AC$2:$AC$1501,'Daily Sale entry '!$X$2:$X$1501,"<="&$A39,'Daily Sale entry '!$Z$2:$Z$1501,"Cash deposit 现金存入"),2)) | I39: =IF($A39="","",ROUND(B39+D39+E39+F39+G39+H39,2)) | J39: =IF($A39="","",'AR & AP'!K40) | K39: =IF($A39="","",ROUND(I39-J39-SUMIFS('Daily Sale entry '!$AC$2:$AC$1501,'Daily Sale entry '!$X$2:$X$1501,"<="&$A39,'Daily Sale entry '!$Z$2:$Z$1501,"Other deposit 其他存入")+SUMIFS('Daily Sale entry '!$AD$2:$AD$1501,'Daily Sale entry '!$X$2:$X$1501,"<="&$A39)+('Opening Balance'!$B$8+SUM('Daily Sale entry '!$L$2:M39)-F39),2)) | L39: =IF($A39="","",IF(ABS('Sales & Collection'!$B$530)>'Opening Balance'!$B$16,"ALERT 警报: Different "&TEXT('Sales & Collection'!$B$530,"#,##0.00")&" 差额过大",""))
A40: =IF('Daily Sale entry '!A40="","",'Daily Sale entry '!A40) | B40: =IF($A40="","",ROUND('Opening Balance'!$B$4+SUM('Daily Sale entry '!$K$2:K40)+SUMIFS('Daily Sale entry '!$AC$2:$AC$1501,'Daily Sale entry '!$X$2:$X$1501,"<="&$A40)-SUMIFS('Daily Sale entry '!$AD$2:$AD$1501,'Daily Sale entry '!$X$2:$X$1501,"<="&$A40)+SUMPRODUCT(('Daily Sale entry '!$Q$2:$Q$1501="Collection 收款")*('Daily Sale entry '!$R$2:$R$1501="Cheque 支票")*('Daily Sale entry '!$V$2:$V$1501<>"")*('Daily Sale entry '!$V$2:$V$1501<=$A40)*('Daily Sale entry '!$S$2:$S$1501-'Opening Balance'!$B$15*('Daily Sale entry '!$R$2:$R$1501="Cheque 支票")*('Daily Sale entry '!$S$2:$S$1501-TRUNC('Daily Sale entry '!$S$2:$S$1501))))-'Opening Balance'!$B$15*SUMPRODUCT(('Daily Sale entry '!$X$2:$X$1501<=$A40)*('Daily Sale entry '!$Z$2:$Z$1501="Online collection 网上收款")*('Daily Sale entry '!$AA$2:$AA$1501<>"")*('Daily Sale entry '!$AC$2:$AC$1501-TRUNC('Daily Sale entry '!$AC$2:$AC$1501))),2)) | C40: =IF($A40="","",'Opening Balance'!$B$5+SUM('Daily Sale entry '!$I$2:I40)-SUMIFS('Daily Sale entry '!$AB$2:$AB$1501,'Daily Sale entry '!$X$2:$X$1501,"<="&$A40,'Daily Sale entry '!$Z$2:$Z$1501,"Cheque deposit 支票存入")-COUNTIFS('Daily Sale entry '!$Q$2:$Q$1501,"Collection 收款",'Daily Sale entry '!$R$2:$R$1501,"Cheque 支票",'Daily Sale entry '!$V$2:$V$1501,"<="&$A40)) | D40: =IF($A40="","",ROUND('Opening Balance'!$B$6+SUM('Daily Sale entry '!$J$2:J40)-SUMIFS('Daily Sale entry '!$AC$2:$AC$1501,'Daily Sale entry '!$X$2:$X$1501,"<="&$A40,'Daily Sale entry '!$Z$2:$Z$1501,"Cheque deposit 支票存入")-SUMPRODUCT(('Daily Sale entry '!$Q$2:$Q$1501="Collection 收款")*('Daily Sale entry '!$R$2:$R$1501="Cheque 支票")*('Daily Sale entry '!$V$2:$V$1501<>"")*('Daily Sale entry '!$V$2:$V$1501<=$A40)*('Daily Sale entry '!$S$2:$S$1501-'Opening Balance'!$B$15*('Daily Sale entry '!$R$2:$R$1501="Cheque 支票")*('Daily Sale entry '!$S$2:$S$1501-TRUNC('Daily Sale entry '!$S$2:$S$1501)))),2)) | E40: =IF($A40="","",'Opening Balance'!$B$7) | F40: =IF($A40="","",ROUND(SUMIFS('Daily Sale entry '!$L$2:$L$367,'Daily Sale entry '!$A$2:$A$367,">="&DATE(YEAR($A40),MONTH($A40),1),'Daily Sale entry '!$A$2:$A$367,"<="&$A40)+SUMIFS('Daily Sale entry '!$M$2:$M$367,'Daily Sale entry '!$A$2:$A$367,">="&DATE(YEAR($A40),MONTH($A40),1),'Daily Sale entry '!$A$2:$A$367,"<="&$A40)+IF(AND(YEAR($A40)=YEAR('Daily Sale entry '!$A$2),MONTH($A40)=MONTH('Daily Sale entry '!$A$2)),'Opening Balance'!$B$8,0),2)) | G40: =IF($A40="","",MOD(ROUND('Opening Balance'!$B$9+SUMIFS('Sales & Collection'!$L$1:$L$535,'Sales & Collection'!$K$1:$K$535,"cash collection*"),2),'Opening Balance'!$B$11)) | H40: =IF($A40="","",ROUND('Opening Balance'!$B$10+'Opening Balance'!$B$9+SUMIFS('Sales & Collection'!$L$1:$L$535,'Sales & Collection'!$K$1:$K$535,"cash collection*")-G40-SUMIFS('Daily Sale entry '!$AC$2:$AC$1501,'Daily Sale entry '!$X$2:$X$1501,"<="&$A40,'Daily Sale entry '!$Z$2:$Z$1501,"Cash deposit 现金存入"),2)) | I40: =IF($A40="","",ROUND(B40+D40+E40+F40+G40+H40,2)) | J40: =IF($A40="","",'AR & AP'!K41) | K40: =IF($A40="","",ROUND(I40-J40-SUMIFS('Daily Sale entry '!$AC$2:$AC$1501,'Daily Sale entry '!$X$2:$X$1501,"<="&$A40,'Daily Sale entry '!$Z$2:$Z$1501,"Other deposit 其他存入")+SUMIFS('Daily Sale entry '!$AD$2:$AD$1501,'Daily Sale entry '!$X$2:$X$1501,"<="&$A40)+('Opening Balance'!$B$8+SUM('Daily Sale entry '!$L$2:M40)-F40),2)) | L40: =IF($A40="","",IF(ABS('Sales & Collection'!$B$544)>'Opening Balance'!$B$16,"ALERT 警报: Different "&TEXT('Sales & Collection'!$B$544,"#,##0.00")&" 差额过大",""))
A41: =IF('Daily Sale entry '!A41="","",'Daily Sale entry '!A41) | B41: =IF($A41="","",ROUND('Opening Balance'!$B$4+SUM('Daily Sale entry '!$K$2:K41)+SUMIFS('Daily Sale entry '!$AC$2:$AC$1501,'Daily Sale entry '!$X$2:$X$1501,"<="&$A41)-SUMIFS('Daily Sale entry '!$AD$2:$AD$1501,'Daily Sale entry '!$X$2:$X$1501,"<="&$A41)+SUMPRODUCT(('Daily Sale entry '!$Q$2:$Q$1501="Collection 收款")*('Daily Sale entry '!$R$2:$R$1501="Cheque 支票")*('Daily Sale entry '!$V$2:$V$1501<>"")*('Daily Sale entry '!$V$2:$V$1501<=$A41)*('Daily Sale entry '!$S$2:$S$1501-'Opening Balance'!$B$15*('Daily Sale entry '!$R$2:$R$1501="Cheque 支票")*('Daily Sale entry '!$S$2:$S$1501-TRUNC('Daily Sale entry '!$S$2:$S$1501))))-'Opening Balance'!$B$15*SUMPRODUCT(('Daily Sale entry '!$X$2:$X$1501<=$A41)*('Daily Sale entry '!$Z$2:$Z$1501="Online collection 网上收款")*('Daily Sale entry '!$AA$2:$AA$1501<>"")*('Daily Sale entry '!$AC$2:$AC$1501-TRUNC('Daily Sale entry '!$AC$2:$AC$1501))),2)) | C41: =IF($A41="","",'Opening Balance'!$B$5+SUM('Daily Sale entry '!$I$2:I41)-SUMIFS('Daily Sale entry '!$AB$2:$AB$1501,'Daily Sale entry '!$X$2:$X$1501,"<="&$A41,'Daily Sale entry '!$Z$2:$Z$1501,"Cheque deposit 支票存入")-COUNTIFS('Daily Sale entry '!$Q$2:$Q$1501,"Collection 收款",'Daily Sale entry '!$R$2:$R$1501,"Cheque 支票",'Daily Sale entry '!$V$2:$V$1501,"<="&$A41)) | D41: =IF($A41="","",ROUND('Opening Balance'!$B$6+SUM('Daily Sale entry '!$J$2:J41)-SUMIFS('Daily Sale entry '!$AC$2:$AC$1501,'Daily Sale entry '!$X$2:$X$1501,"<="&$A41,'Daily Sale entry '!$Z$2:$Z$1501,"Cheque deposit 支票存入")-SUMPRODUCT(('Daily Sale entry '!$Q$2:$Q$1501="Collection 收款")*('Daily Sale entry '!$R$2:$R$1501="Cheque 支票")*('Daily Sale entry '!$V$2:$V$1501<>"")*('Daily Sale entry '!$V$2:$V$1501<=$A41)*('Daily Sale entry '!$S$2:$S$1501-'Opening Balance'!$B$15*('Daily Sale entry '!$R$2:$R$1501="Cheque 支票")*('Daily Sale entry '!$S$2:$S$1501-TRUNC('Daily Sale entry '!$S$2:$S$1501)))),2)) | E41: =IF($A41="","",'Opening Balance'!$B$7) | F41: =IF($A41="","",ROUND(SUMIFS('Daily Sale entry '!$L$2:$L$367,'Daily Sale entry '!$A$2:$A$367,">="&DATE(YEAR($A41),MONTH($A41),1),'Daily Sale entry '!$A$2:$A$367,"<="&$A41)+SUMIFS('Daily Sale entry '!$M$2:$M$367,'Daily Sale entry '!$A$2:$A$367,">="&DATE(YEAR($A41),MONTH($A41),1),'Daily Sale entry '!$A$2:$A$367,"<="&$A41)+IF(AND(YEAR($A41)=YEAR('Daily Sale entry '!$A$2),MONTH($A41)=MONTH('Daily Sale entry '!$A$2)),'Opening Balance'!$B$8,0),2)) | G41: =IF($A41="","",MOD(ROUND('Opening Balance'!$B$9+SUMIFS('Sales & Collection'!$L$1:$L$549,'Sales & Collection'!$K$1:$K$549,"cash collection*"),2),'Opening Balance'!$B$11)) | H41: =IF($A41="","",ROUND('Opening Balance'!$B$10+'Opening Balance'!$B$9+SUMIFS('Sales & Collection'!$L$1:$L$549,'Sales & Collection'!$K$1:$K$549,"cash collection*")-G41-SUMIFS('Daily Sale entry '!$AC$2:$AC$1501,'Daily Sale entry '!$X$2:$X$1501,"<="&$A41,'Daily Sale entry '!$Z$2:$Z$1501,"Cash deposit 现金存入"),2)) | I41: =IF($A41="","",ROUND(B41+D41+E41+F41+G41+H41,2)) | J41: =IF($A41="","",'AR & AP'!K42) | K41: =IF($A41="","",ROUND(I41-J41-SUMIFS('Daily Sale entry '!$AC$2:$AC$1501,'Daily Sale entry '!$X$2:$X$1501,"<="&$A41,'Daily Sale entry '!$Z$2:$Z$1501,"Other deposit 其他存入")+SUMIFS('Daily Sale entry '!$AD$2:$AD$1501,'Daily Sale entry '!$X$2:$X$1501,"<="&$A41)+('Opening Balance'!$B$8+SUM('Daily Sale entry '!$L$2:M41)-F41),2)) | L41: =IF($A41="","",IF(ABS('Sales & Collection'!$B$558)>'Opening Balance'!$B$16,"ALERT 警报: Different "&TEXT('Sales & Collection'!$B$558,"#,##0.00")&" 差额过大",""))
A42: =IF('Daily Sale entry '!A42="","",'Daily Sale entry '!A42) | B42: =IF($A42="","",ROUND('Opening Balance'!$B$4+SUM('Daily Sale entry '!$K$2:K42)+SUMIFS('Daily Sale entry '!$AC$2:$AC$1501,'Daily Sale entry '!$X$2:$X$1501,"<="&$A42)-SUMIFS('Daily Sale entry '!$AD$2:$AD$1501,'Daily Sale entry '!$X$2:$X$1501,"<="&$A42)+SUMPRODUCT(('Daily Sale entry '!$Q$2:$Q$1501="Collection 收款")*('Daily Sale entry '!$R$2:$R$1501="Cheque 支票")*('Daily Sale entry '!$V$2:$V$1501<>"")*('Daily Sale entry '!$V$2:$V$1501<=$A42)*('Daily Sale entry '!$S$2:$S$1501-'Opening Balance'!$B$15*('Daily Sale entry '!$R$2:$R$1501="Cheque 支票")*('Daily Sale entry '!$S$2:$S$1501-TRUNC('Daily Sale entry '!$S$2:$S$1501))))-'Opening Balance'!$B$15*SUMPRODUCT(('Daily Sale entry '!$X$2:$X$1501<=$A42)*('Daily Sale entry '!$Z$2:$Z$1501="Online collection 网上收款")*('Daily Sale entry '!$AA$2:$AA$1501<>"")*('Daily Sale entry '!$AC$2:$AC$1501-TRUNC('Daily Sale entry '!$AC$2:$AC$1501))),2)) | C42: =IF($A42="","",'Opening Balance'!$B$5+SUM('Daily Sale entry '!$I$2:I42)-SUMIFS('Daily Sale entry '!$AB$2:$AB$1501,'Daily Sale entry '!$X$2:$X$1501,"<="&$A42,'Daily Sale entry '!$Z$2:$Z$1501,"Cheque deposit 支票存入")-COUNTIFS('Daily Sale entry '!$Q$2:$Q$1501,"Collection 收款",'Daily Sale entry '!$R$2:$R$1501,"Cheque 支票",'Daily Sale entry '!$V$2:$V$1501,"<="&$A42)) | D42: =IF($A42="","",ROUND('Opening Balance'!$B$6+SUM('Daily Sale entry '!$J$2:J42)-SUMIFS('Daily Sale entry '!$AC$2:$AC$1501,'Daily Sale entry '!$X$2:$X$1501,"<="&$A42,'Daily Sale entry '!$Z$2:$Z$1501,"Cheque deposit 支票存入")-SUMPRODUCT(('Daily Sale entry '!$Q$2:$Q$1501="Collection 收款")*('Daily Sale entry '!$R$2:$R$1501="Cheque 支票")*('Daily Sale entry '!$V$2:$V$1501<>"")*('Daily Sale entry '!$V$2:$V$1501<=$A42)*('Daily Sale entry '!$S$2:$S$1501-'Opening Balance'!$B$15*('Daily Sale entry '!$R$2:$R$1501="Cheque 支票")*('Daily Sale entry '!$S$2:$S$1501-TRUNC('Daily Sale entry '!$S$2:$S$1501)))),2)) | E42: =IF($A42="","",'Opening Balance'!$B$7) | F42: =IF($A42="","",ROUND(SUMIFS('Daily Sale entry '!$L$2:$L$367,'Daily Sale entry '!$A$2:$A$367,">="&DATE(YEAR($A42),MONTH($A42),1),'Daily Sale entry '!$A$2:$A$367,"<="&$A42)+SUMIFS('Daily Sale entry '!$M$2:$M$367,'Daily Sale entry '!$A$2:$A$367,">="&DATE(YEAR($A42),MONTH($A42),1),'Daily Sale entry '!$A$2:$A$367,"<="&$A42)+IF(AND(YEAR($A42)=YEAR('Daily Sale entry '!$A$2),MONTH($A42)=MONTH('Daily Sale entry '!$A$2)),'Opening Balance'!$B$8,0),2)) | G42: =IF($A42="","",MOD(ROUND('Opening Balance'!$B$9+SUMIFS('Sales & Collection'!$L$1:$L$563,'Sales & Collection'!$K$1:$K$563,"cash collection*"),2),'Opening Balance'!$B$11)) | H42: =IF($A42="","",ROUND('Opening Balance'!$B$10+'Opening Balance'!$B$9+SUMIFS('Sales & Collection'!$L$1:$L$563,'Sales & Collection'!$K$1:$K$563,"cash collection*")-G42-SUMIFS('Daily Sale entry '!$AC$2:$AC$1501,'Daily Sale entry '!$X$2:$X$1501,"<="&$A42,'Daily Sale entry '!$Z$2:$Z$1501,"Cash deposit 现金存入"),2)) | I42: =IF($A42="","",ROUND(B42+D42+E42+F42+G42+H42,2)) | J42: =IF($A42="","",'AR & AP'!K43) | K42: =IF($A42="","",ROUND(I42-J42-SUMIFS('Daily Sale entry '!$AC$2:$AC$1501,'Daily Sale entry '!$X$2:$X$1501,"<="&$A42,'Daily Sale entry '!$Z$2:$Z$1501,"Other deposit 其他存入")+SUMIFS('Daily Sale entry '!$AD$2:$AD$1501,'Daily Sale entry '!$X$2:$X$1501,"<="&$A42)+('Opening Balance'!$B$8+SUM('Daily Sale entry '!$L$2:M42)-F42),2)) | L42: =IF($A42="","",IF(ABS('Sales & Collection'!$B$572)>'Opening Balance'!$B$16,"ALERT 警报: Different "&TEXT('Sales & Collection'!$B$572,"#,##0.00")&" 差额过大",""))
A43: =IF('Daily Sale entry '!A43="","",'Daily Sale entry '!A43) | B43: =IF($A43="","",ROUND('Opening Balance'!$B$4+SUM('Daily Sale entry '!$K$2:K43)+SUMIFS('Daily Sale entry '!$AC$2:$AC$1501,'Daily Sale entry '!$X$2:$X$1501,"<="&$A43)-SUMIFS('Daily Sale entry '!$AD$2:$AD$1501,'Daily Sale entry '!$X$2:$X$1501,"<="&$A43)+SUMPRODUCT(('Daily Sale entry '!$Q$2:$Q$1501="Collection 收款")*('Daily Sale entry '!$R$2:$R$1501="Cheque 支票")*('Daily Sale entry '!$V$2:$V$1501<>"")*('Daily Sale entry '!$V$2:$V$1501<=$A43)*('Daily Sale entry '!$S$2:$S$1501-'Opening Balance'!$B$15*('Daily Sale entry '!$R$2:$R$1501="Cheque 支票")*('Daily Sale entry '!$S$2:$S$1501-TRUNC('Daily Sale entry '!$S$2:$S$1501))))-'Opening Balance'!$B$15*SUMPRODUCT(('Daily Sale entry '!$X$2:$X$1501<=$A43)*('Daily Sale entry '!$Z$2:$Z$1501="Online collection 网上收款")*('Daily Sale entry '!$AA$2:$AA$1501<>"")*('Daily Sale entry '!$AC$2:$AC$1501-TRUNC('Daily Sale entry '!$AC$2:$AC$1501))),2)) | C43: =IF($A43="","",'Opening Balance'!$B$5+SUM('Daily Sale entry '!$I$2:I43)-SUMIFS('Daily Sale entry '!$AB$2:$AB$1501,'Daily Sale entry '!$X$2:$X$1501,"<="&$A43,'Daily Sale entry '!$Z$2:$Z$1501,"Cheque deposit 支票存入")-COUNTIFS('Daily Sale entry '!$Q$2:$Q$1501,"Collection 收款",'Daily Sale entry '!$R$2:$R$1501,"Cheque 支票",'Daily Sale entry '!$V$2:$V$1501,"<="&$A43)) | D43: =IF($A43="","",ROUND('Opening Balance'!$B$6+SUM('Daily Sale entry '!$J$2:J43)-SUMIFS('Daily Sale entry '!$AC$2:$AC$1501,'Daily Sale entry '!$X$2:$X$1501,"<="&$A43,'Daily Sale entry '!$Z$2:$Z$1501,"Cheque deposit 支票存入")-SUMPRODUCT(('Daily Sale entry '!$Q$2:$Q$1501="Collection 收款")*('Daily Sale entry '!$R$2:$R$1501="Cheque 支票")*('Daily Sale entry '!$V$2:$V$1501<>"")*('Daily Sale entry '!$V$2:$V$1501<=$A43)*('Daily Sale entry '!$S$2:$S$1501-'Opening Balance'!$B$15*('Daily Sale entry '!$R$2:$R$1501="Cheque 支票")*('Daily Sale entry '!$S$2:$S$1501-TRUNC('Daily Sale entry '!$S$2:$S$1501)))),2)) | E43: =IF($A43="","",'Opening Balance'!$B$7) | F43: =IF($A43="","",ROUND(SUMIFS('Daily Sale entry '!$L$2:$L$367,'Daily Sale entry '!$A$2:$A$367,">="&DATE(YEAR($A43),MONTH($A43),1),'Daily Sale entry '!$A$2:$A$367,"<="&$A43)+SUMIFS('Daily Sale entry '!$M$2:$M$367,'Daily Sale entry '!$A$2:$A$367,">="&DATE(YEAR($A43),MONTH($A43),1),'Daily Sale entry '!$A$2:$A$367,"<="&$A43)+IF(AND(YEAR($A43)=YEAR('Daily Sale entry '!$A$2),MONTH($A43)=MONTH('Daily Sale entry '!$A$2)),'Opening Balance'!$B$8,0),2)) | G43: =IF($A43="","",MOD(ROUND('Opening Balance'!$B$9+SUMIFS('Sales & Collection'!$L$1:$L$577,'Sales & Collection'!$K$1:$K$577,"cash collection*"),2),'Opening Balance'!$B$11)) | H43: =IF($A43="","",ROUND('Opening Balance'!$B$10+'Opening Balance'!$B$9+SUMIFS('Sales & Collection'!$L$1:$L$577,'Sales & Collection'!$K$1:$K$577,"cash collection*")-G43-SUMIFS('Daily Sale entry '!$AC$2:$AC$1501,'Daily Sale entry '!$X$2:$X$1501,"<="&$A43,'Daily Sale entry '!$Z$2:$Z$1501,"Cash deposit 现金存入"),2)) | I43: =IF($A43="","",ROUND(B43+D43+E43+F43+G43+H43,2)) | J43: =IF($A43="","",'AR & AP'!K44) | K43: =IF($A43="","",ROUND(I43-J43-SUMIFS('Daily Sale entry '!$AC$2:$AC$1501,'Daily Sale entry '!$X$2:$X$1501,"<="&$A43,'Daily Sale entry '!$Z$2:$Z$1501,"Other deposit 其他存入")+SUMIFS('Daily Sale entry '!$AD$2:$AD$1501,'Daily Sale entry '!$X$2:$X$1501,"<="&$A43)+('Opening Balance'!$B$8+SUM('Daily Sale entry '!$L$2:M43)-F43),2)) | L43: =IF($A43="","",IF(ABS('Sales & Collection'!$B$586)>'Opening Balance'!$B$16,"ALERT 警报: Different "&TEXT('Sales & Collection'!$B$586,"#,##0.00")&" 差额过大",""))
A44: =IF('Daily Sale entry '!A44="","",'Daily Sale entry '!A44) | B44: =IF($A44="","",ROUND('Opening Balance'!$B$4+SUM('Daily Sale entry '!$K$2:K44)+SUMIFS('Daily Sale entry '!$AC$2:$AC$1501,'Daily Sale entry '!$X$2:$X$1501,"<="&$A44)-SUMIFS('Daily Sale entry '!$AD$2:$AD$1501,'Daily Sale entry '!$X$2:$X$1501,"<="&$A44)+SUMPRODUCT(('Daily Sale entry '!$Q$2:$Q$1501="Collection 收款")*('Daily Sale entry '!$R$2:$R$1501="Cheque 支票")*('Daily Sale entry '!$V$2:$V$1501<>"")*('Daily Sale entry '!$V$2:$V$1501<=$A44)*('Daily Sale entry '!$S$2:$S$1501-'Opening Balance'!$B$15*('Daily Sale entry '!$R$2:$R$1501="Cheque 支票")*('Daily Sale entry '!$S$2:$S$1501-TRUNC('Daily Sale entry '!$S$2:$S$1501))))-'Opening Balance'!$B$15*SUMPRODUCT(('Daily Sale entry '!$X$2:$X$1501<=$A44)*('Daily Sale entry '!$Z$2:$Z$1501="Online collection 网上收款")*('Daily Sale entry '!$AA$2:$AA$1501<>"")*('Daily Sale entry '!$AC$2:$AC$1501-TRUNC('Daily Sale entry '!$AC$2:$AC$1501))),2)) | C44: =IF($A44="","",'Opening Balance'!$B$5+SUM('Daily Sale entry '!$I$2:I44)-SUMIFS('Daily Sale entry '!$AB$2:$AB$1501,'Daily Sale entry '!$X$2:$X$1501,"<="&$A44,'Daily Sale entry '!$Z$2:$Z$1501,"Cheque deposit 支票存入")-COUNTIFS('Daily Sale entry '!$Q$2:$Q$1501,"Collection 收款",'Daily Sale entry '!$R$2:$R$1501,"Cheque 支票",'Daily Sale entry '!$V$2:$V$1501,"<="&$A44)) | D44: =IF($A44="","",ROUND('Opening Balance'!$B$6+SUM('Daily Sale entry '!$J$2:J44)-SUMIFS('Daily Sale entry '!$AC$2:$AC$1501,'Daily Sale entry '!$X$2:$X$1501,"<="&$A44,'Daily Sale entry '!$Z$2:$Z$1501,"Cheque deposit 支票存入")-SUMPRODUCT(('Daily Sale entry '!$Q$2:$Q$1501="Collection 收款")*('Daily Sale entry '!$R$2:$R$1501="Cheque 支票")*('Daily Sale entry '!$V$2:$V$1501<>"")*('Daily Sale entry '!$V$2:$V$1501<=$A44)*('Daily Sale entry '!$S$2:$S$1501-'Opening Balance'!$B$15*('Daily Sale entry '!$R$2:$R$1501="Cheque 支票")*('Daily Sale entry '!$S$2:$S$1501-TRUNC('Daily Sale entry '!$S$2:$S$1501)))),2)) | E44: =IF($A44="","",'Opening Balance'!$B$7) | F44: =IF($A44="","",ROUND(SUMIFS('Daily Sale entry '!$L$2:$L$367,'Daily Sale entry '!$A$2:$A$367,">="&DATE(YEAR($A44),MONTH($A44),1),'Daily Sale entry '!$A$2:$A$367,"<="&$A44)+SUMIFS('Daily Sale entry '!$M$2:$M$367,'Daily Sale entry '!$A$2:$A$367,">="&DATE(YEAR($A44),MONTH($A44),1),'Daily Sale entry '!$A$2:$A$367,"<="&$A44)+IF(AND(YEAR($A44)=YEAR('Daily Sale entry '!$A$2),MONTH($A44)=MONTH('Daily Sale entry '!$A$2)),'Opening Balance'!$B$8,0),2)) | G44: =IF($A44="","",MOD(ROUND('Opening Balance'!$B$9+SUMIFS('Sales & Collection'!$L$1:$L$591,'Sales & Collection'!$K$1:$K$591,"cash collection*"),2),'Opening Balance'!$B$11)) | H44: =IF($A44="","",ROUND('Opening Balance'!$B$10+'Opening Balance'!$B$9+SUMIFS('Sales & Collection'!$L$1:$L$591,'Sales & Collection'!$K$1:$K$591,"cash collection*")-G44-SUMIFS('Daily Sale entry '!$AC$2:$AC$1501,'Daily Sale entry '!$X$2:$X$1501,"<="&$A44,'Daily Sale entry '!$Z$2:$Z$1501,"Cash deposit 现金存入"),2)) | I44: =IF($A44="","",ROUND(B44+D44+E44+F44+G44+H44,2)) | J44: =IF($A44="","",'AR & AP'!K45) | K44: =IF($A44="","",ROUND(I44-J44-SUMIFS('Daily Sale entry '!$AC$2:$AC$1501,'Daily Sale entry '!$X$2:$X$1501,"<="&$A44,'Daily Sale entry '!$Z$2:$Z$1501,"Other deposit 其他存入")+SUMIFS('Daily Sale entry '!$AD$2:$AD$1501,'Daily Sale entry '!$X$2:$X$1501,"<="&$A44)+('Opening Balance'!$B$8+SUM('Daily Sale entry '!$L$2:M44)-F44),2)) | L44: =IF($A44="","",IF(ABS('Sales & Collection'!$B$600)>'Opening Balance'!$B$16,"ALERT 警报: Different "&TEXT('Sales & Collection'!$B$600,"#,##0.00")&" 差额过大",""))
A45: =IF('Daily Sale entry '!A45="","",'Daily Sale entry '!A45) | B45: =IF($A45="","",ROUND('Opening Balance'!$B$4+SUM('Daily Sale entry '!$K$2:K45)+SUMIFS('Daily Sale entry '!$AC$2:$AC$1501,'Daily Sale entry '!$X$2:$X$1501,"<="&$A45)-SUMIFS('Daily Sale entry '!$AD$2:$AD$1501,'Daily Sale entry '!$X$2:$X$1501,"<="&$A45)+SUMPRODUCT(('Daily Sale entry '!$Q$2:$Q$1501="Collection 收款")*('Daily Sale entry '!$R$2:$R$1501="Cheque 支票")*('Daily Sale entry '!$V$2:$V$1501<>"")*('Daily Sale entry '!$V$2:$V$1501<=$A45)*('Daily Sale entry '!$S$2:$S$1501-'Opening Balance'!$B$15*('Daily Sale entry '!$R$2:$R$1501="Cheque 支票")*('Daily Sale entry '!$S$2:$S$1501-TRUNC('Daily Sale entry '!$S$2:$S$1501))))-'Opening Balance'!$B$15*SUMPRODUCT(('Daily Sale entry '!$X$2:$X$1501<=$A45)*('Daily Sale entry '!$Z$2:$Z$1501="Online collection 网上收款")*('Daily Sale entry '!$AA$2:$AA$1501<>"")*('Daily Sale entry '!$AC$2:$AC$1501-TRUNC('Daily Sale entry '!$AC$2:$AC$1501))),2)) | C45: =IF($A45="","",'Opening Balance'!$B$5+SUM('Daily Sale entry '!$I$2:I45)-SUMIFS('Daily Sale entry '!$AB$2:$AB$1501,'Daily Sale entry '!$X$2:$X$1501,"<="&$A45,'Daily Sale entry '!$Z$2:$Z$1501,"Cheque deposit 支票存入")-COUNTIFS('Daily Sale entry '!$Q$2:$Q$1501,"Collection 收款",'Daily Sale entry '!$R$2:$R$1501,"Cheque 支票",'Daily Sale entry '!$V$2:$V$1501,"<="&$A45)) | D45: =IF($A45="","",ROUND('Opening Balance'!$B$6+SUM('Daily Sale entry '!$J$2:J45)-SUMIFS('Daily Sale entry '!$AC$2:$AC$1501,'Daily Sale entry '!$X$2:$X$1501,"<="&$A45,'Daily Sale entry '!$Z$2:$Z$1501,"Cheque deposit 支票存入")-SUMPRODUCT(('Daily Sale entry '!$Q$2:$Q$1501="Collection 收款")*('Daily Sale entry '!$R$2:$R$1501="Cheque 支票")*('Daily Sale entry '!$V$2:$V$1501<>"")*('Daily Sale entry '!$V$2:$V$1501<=$A45)*('Daily Sale entry '!$S$2:$S$1501-'Opening Balance'!$B$15*('Daily Sale entry '!$R$2:$R$1501="Cheque 支票")*('Daily Sale entry '!$S$2:$S$1501-TRUNC('Daily Sale entry '!$S$2:$S$1501)))),2)) | E45: =IF($A45="","",'Opening Balance'!$B$7) | F45: =IF($A45="","",ROUND(SUMIFS('Daily Sale entry '!$L$2:$L$367,'Daily Sale entry '!$A$2:$A$367,">="&DATE(YEAR($A45),MONTH($A45),1),'Daily Sale entry '!$A$2:$A$367,"<="&$A45)+SUMIFS('Daily Sale entry '!$M$2:$M$367,'Daily Sale entry '!$A$2:$A$367,">="&DATE(YEAR($A45),MONTH($A45),1),'Daily Sale entry '!$A$2:$A$367,"<="&$A45)+IF(AND(YEAR($A45)=YEAR('Daily Sale entry '!$A$2),MONTH($A45)=MONTH('Daily Sale entry '!$A$2)),'Opening Balance'!$B$8,0),2)) | G45: =IF($A45="","",MOD(ROUND('Opening Balance'!$B$9+SUMIFS('Sales & Collection'!$L$1:$L$605,'Sales & Collection'!$K$1:$K$605,"cash collection*"),2),'Opening Balance'!$B$11)) | H45: =IF($A45="","",ROUND('Opening Balance'!$B$10+'Opening Balance'!$B$9+SUMIFS('Sales & Collection'!$L$1:$L$605,'Sales & Collection'!$K$1:$K$605,"cash collection*")-G45-SUMIFS('Daily Sale entry '!$AC$2:$AC$1501,'Daily Sale entry '!$X$2:$X$1501,"<="&$A45,'Daily Sale entry '!$Z$2:$Z$1501,"Cash deposit 现金存入"),2)) | I45: =IF($A45="","",ROUND(B45+D45+E45+F45+G45+H45,2)) | J45: =IF($A45="","",'AR & AP'!K46) | K45: =IF($A45="","",ROUND(I45-J45-SUMIFS('Daily Sale entry '!$AC$2:$AC$1501,'Daily Sale entry '!$X$2:$X$1501,"<="&$A45,'Daily Sale entry '!$Z$2:$Z$1501,"Other deposit 其他存入")+SUMIFS('Daily Sale entry '!$AD$2:$AD$1501,'Daily Sale entry '!$X$2:$X$1501,"<="&$A45)+('Opening Balance'!$B$8+SUM('Daily Sale entry '!$L$2:M45)-F45),2)) | L45: =IF($A45="","",IF(ABS('Sales & Collection'!$B$614)>'Opening Balance'!$B$16,"ALERT 警报: Different "&TEXT('Sales & Collection'!$B$614,"#,##0.00")&" 差额过大",""))
A46: =IF('Daily Sale entry '!A46="","",'Daily Sale entry '!A46) | B46: =IF($A46="","",ROUND('Opening Balance'!$B$4+SUM('Daily Sale entry '!$K$2:K46)+SUMIFS('Daily Sale entry '!$AC$2:$AC$1501,'Daily Sale entry '!$X$2:$X$1501,"<="&$A46)-SUMIFS('Daily Sale entry '!$AD$2:$AD$1501,'Daily Sale entry '!$X$2:$X$1501,"<="&$A46)+SUMPRODUCT(('Daily Sale entry '!$Q$2:$Q$1501="Collection 收款")*('Daily Sale entry '!$R$2:$R$1501="Cheque 支票")*('Daily Sale entry '!$V$2:$V$1501<>"")*('Daily Sale entry '!$V$2:$V$1501<=$A46)*('Daily Sale entry '!$S$2:$S$1501-'Opening Balance'!$B$15*('Daily Sale entry '!$R$2:$R$1501="Cheque 支票")*('Daily Sale entry '!$S$2:$S$1501-TRUNC('Daily Sale entry '!$S$2:$S$1501))))-'Opening Balance'!$B$15*SUMPRODUCT(('Daily Sale entry '!$X$2:$X$1501<=$A46)*('Daily Sale entry '!$Z$2:$Z$1501="Online collection 网上收款")*('Daily Sale entry '!$AA$2:$AA$1501<>"")*('Daily Sale entry '!$AC$2:$AC$1501-TRUNC('Daily Sale entry '!$AC$2:$AC$1501))),2)) | C46: =IF($A46="","",'Opening Balance'!$B$5+SUM('Daily Sale entry '!$I$2:I46)-SUMIFS('Daily Sale entry '!$AB$2:$AB$1501,'Daily Sale entry '!$X$2:$X$1501,"<="&$A46,'Daily Sale entry '!$Z$2:$Z$1501,"Cheque deposit 支票存入")-COUNTIFS('Daily Sale entry '!$Q$2:$Q$1501,"Collection 收款",'Daily Sale entry '!$R$2:$R$1501,"Cheque 支票",'Daily Sale entry '!$V$2:$V$1501,"<="&$A46)) | D46: =IF($A46="","",ROUND('Opening Balance'!$B$6+SUM('Daily Sale entry '!$J$2:J46)-SUMIFS('Daily Sale entry '!$AC$2:$AC$1501,'Daily Sale entry '!$X$2:$X$1501,"<="&$A46,'Daily Sale entry '!$Z$2:$Z$1501,"Cheque deposit 支票存入")-SUMPRODUCT(('Daily Sale entry '!$Q$2:$Q$1501="Collection 收款")*('Daily Sale entry '!$R$2:$R$1501="Cheque 支票")*('Daily Sale entry '!$V$2:$V$1501<>"")*('Daily Sale entry '!$V$2:$V$1501<=$A46)*('Daily Sale entry '!$S$2:$S$1501-'Opening Balance'!$B$15*('Daily Sale entry '!$R$2:$R$1501="Cheque 支票")*('Daily Sale entry '!$S$2:$S$1501-TRUNC('Daily Sale entry '!$S$2:$S$1501)))),2)) | E46: =IF($A46="","",'Opening Balance'!$B$7) | F46: =IF($A46="","",ROUND(SUMIFS('Daily Sale entry '!$L$2:$L$367,'Daily Sale entry '!$A$2:$A$367,">="&DATE(YEAR($A46),MONTH($A46),1),'Daily Sale entry '!$A$2:$A$367,"<="&$A46)+SUMIFS('Daily Sale entry '!$M$2:$M$367,'Daily Sale entry '!$A$2:$A$367,">="&DATE(YEAR($A46),MONTH($A46),1),'Daily Sale entry '!$A$2:$A$367,"<="&$A46)+IF(AND(YEAR($A46)=YEAR('Daily Sale entry '!$A$2),MONTH($A46)=MONTH('Daily Sale entry '!$A$2)),'Opening Balance'!$B$8,0),2)) | G46: =IF($A46="","",MOD(ROUND('Opening Balance'!$B$9+SUMIFS('Sales & Collection'!$L$1:$L$619,'Sales & Collection'!$K$1:$K$619,"cash collection*"),2),'Opening Balance'!$B$11)) | H46: =IF($A46="","",ROUND('Opening Balance'!$B$10+'Opening Balance'!$B$9+SUMIFS('Sales & Collection'!$L$1:$L$619,'Sales & Collection'!$K$1:$K$619,"cash collection*")-G46-SUMIFS('Daily Sale entry '!$AC$2:$AC$1501,'Daily Sale entry '!$X$2:$X$1501,"<="&$A46,'Daily Sale entry '!$Z$2:$Z$1501,"Cash deposit 现金存入"),2)) | I46: =IF($A46="","",ROUND(B46+D46+E46+F46+G46+H46,2)) | J46: =IF($A46="","",'AR & AP'!K47) | K46: =IF($A46="","",ROUND(I46-J46-SUMIFS('Daily Sale entry '!$AC$2:$AC$1501,'Daily Sale entry '!$X$2:$X$1501,"<="&$A46,'Daily Sale entry '!$Z$2:$Z$1501,"Other deposit 其他存入")+SUMIFS('Daily Sale entry '!$AD$2:$AD$1501,'Daily Sale entry '!$X$2:$X$1501,"<="&$A46)+('Opening Balance'!$B$8+SUM('Daily Sale entry '!$L$2:M46)-F46),2)) | L46: =IF($A46="","",IF(ABS('Sales & Collection'!$B$628)>'Opening Balance'!$B$16,"ALERT 警报: Different "&TEXT('Sales & Collection'!$B$628,"#,##0.00")&" 差额过大",""))
